Workbook

Sheet Client Info
A1: Client ID | B1: Business Type | C1: Name | D1: Address | E1: City | F1: Province | G1: PostalCode
A2: 10000 | B2: B2B - LPs | C2: Atlas Growers
A3: 20007 | B3: Provincial Distributor | C3: MBLL | D3: PO Box 1023 | E3: Winnipeg | F3: MB | G3: R3C2X1

Sheet productGTIN_internalSKU
A1: QA_product_name | B1: cannabislog_product_description | C1: cannabislog_stage | D1: product_description_stage | E1: canSKU_labelled | F1: canSKU_packaged | G1: canSKU_bulk_preroll | H1: canSKU_bulk
A2: Spa Bath Salts 180 g | B2: bath salt SPA 180 gram | C2: topical_labelled | D2: =B2&"_"&C2 -> bath salt SPA 180 gram_topical_labelled | E2: 13 | H2: 172
A3: CBD Bacon Oil 10 mg 27.3g | B3: CBD Bacon Oil 10 mg 27.3g | C3: extract_ingested_labelled | D3: =B3&"_"&C3 -> CBD Bacon Oil 10 mg 27.3g_extract_ingested_labelled | E3: 17
A4: Neem Cream 120 g | B4: CBD Neem Cream 120g | C4: extract_topical_labelled_RTV | D4: =B4&"_"&C4 -> CBD Neem Cream 120g_extract_topical_labelled_RTV | E4: 139
A5: Chronic Mint 1g | B5: Chronic Mint preroll 1 x 1g | C5: preroll_labelled | D5: =B5&"_"&C5 -> Chronic Mint preroll 1 x 1g_preroll_labelled | E5: 24 | H5: 25
A6: Chronic mint 3x0.5g preroll | B6: Chronic Mint preroll 3 x 0.5g | C6: preroll_labelled | D6: =B6&"_"&C6 -> Chronic Mint preroll 3 x 0.5g_preroll_labelled | E6: 26
A7: Extra Strength Roll-on Topical Cream | B7: Extra Strength Roll-on 88g | C7: topical_labelled | D7: =B7&"_"&C7 -> Extra Strength Roll-on 88g_topical_labelled | E7: 31
A8: Galactic cake 1 g preroll | B8: Galactic Cake preroll 1 x 1g | C8: preroll_labelled | D8: =B8&"_"&C8 -> Galactic Cake preroll 1 x 1g_preroll_labelled | E8: 34 | F8: 114 | H8: 35
A9: Galactic cake 3x0.5g preroll | B9: Galactic Cake preroll 3 x 0.5g | C9: preroll_labelled | D9: =B9&"_"&C9 -> Galactic Cake preroll 3 x 0.5g_preroll_labelled | E9: 36 | F9: 115
A10: Gelato 14 g | B10: Gelato dried flower 14g | C10: driedflower_labelled | D10: =B10&"_"&C10 -> Gelato dried flower 14g_driedflower_labelled | E10: 38 | F10: 116 | H10: 37
A11: Gelato Prerolls 1g | B11: Gelato preroll 1 x 1g | C11: preroll_labelled | D11: =B11&"_"&C11 -> Gelato preroll 1 x 1g_preroll_labelled | E11: 44 | H11: 45
A12: Gelato Prerolls 3x0.5g | B12: Gelato preroll 3 x 0.5g | C12: preroll_labelled | D12: =B12&"_"&C12 -> Gelato preroll 3 x 0.5g_preroll_labelled | E12: 46 | H12: 43
A13: Gorilla bomb 3x0.5g preroll | B13: Gorilla Bomb preroll 0.5g | C13: preroll_labelled | D13: =B13&"_"&C13 -> Gorilla Bomb preroll 0.5g_preroll_labelled | E13: 130 | F13: 52 | H13: 49
A14: Gorilla bomb 1 g preroll | B14: Gorilla Bomb preroll 1 x 1g | C14: preroll_labelled | D14: =B14&"_"&C14 -> Gorilla Bomb preroll 1 x 1g_preroll_labelled | E14: 50 | F14: 117 | H14: 51
A15: Grease monkey 1 g | B15: Grease Monkey preroll 1 x 1g | C15: preroll_labelled | D15: =B15&"_"&C15 -> Grease Monkey preroll 1 x 1g_preroll_labelled | E15: 57 | H15: 58
A16: Grease monkey 3x0.5 g | B16: Grease Monkey preroll 3 x 0.5g | C16: preroll_labelled | D16: =B16&"_"&C16 -> Grease Monkey preroll 3 x 0.5g_preroll_labelled | E16: 59 | F16: 119 | H16: 56

Sheet internal_cansku_inventory
A1: product_name | B1: product_description | C1: stage | D1: product_description_stage | E1: canSKU
B2: unknown dried flower | C2: driedflower_unknown | D2: =B2&"_"&C2 -> unknown dried flower_driedflower_unknown | E2: 1
B3: 20:1 Mango CBD:THC extract 29.5g | C3: extract_ingested_labelled | D3: =B3&"_"&C3 -> 20:1 Mango CBD:THC extract 29.5g_extract_ingested_labelled | E3: 2
B4: 4:1 Black Cherry CBD:THC extract 29.5g | C4: extract_ingested_labelled | D4: =B4&"_"&C4 -> 4:1 Black Cherry CBD:THC extract 29.5g_extract_ingested_labelled | E4: 3
B5: Abby Leaf Inc Licorish Gumball dried flower | C5: driedflower_bulk_BURB | D5: =B5&"_"&C5 -> Abby Leaf Inc Licorish Gumball dried flower_driedflower_bulk_BURB | E5: 4
B6: Abby Leaf Inc Unicorn Poop Grade | C6: driedflower_bulk_BURB | D6: =B6&"_"&C6 -> Abby Leaf Inc Unicorn Poop Grade _driedflower_bulk_BURB | E6: 5
B7: Animal Cookies dried flower 3.5 g | C7: driedflower_packaged | D7: =B7&"_"&C7 -> Animal Cookies dried flower 3.5 g_driedflower_packaged | E7: 6
B8: Aum CBD oil 27.4g | C8: extract_ingested_labelled | D8: =B8&"_"&C8 -> Aum CBD oil 27.4g_extract_ingested_labelled | E8: 7
B9: Backforty Blends Glacial Gold Clay Face Mask | C9: topical_labelled_RTV | D9: =B9&"_"&C9 -> Backforty Blends Glacial Gold Clay Face Mask_topical_labelled_RTV | E9: 8
B10: Bacon CBD Extract | C10: extract_ingested_bulk | D10: =B10&"_"&C10 -> Bacon CBD Extract_extract_ingested_bulk | E10: 9
B11: Bacon CBD Extract 27.6g | C11: extract_ingested_labelled | D11: =B11&"_"&C11 -> Bacon CBD Extract 27.6g_extract_ingested_labelled | E11: 10
B12: Bacon CBD extract 29.5g | C12: extract_ingested_labelled | D12: =B12&"_"&C12 -> Bacon CBD extract 29.5g_extract_ingested_labelled | E12: 11
B13: Bacon CBD extract 54.8g | C13: extract_ingested_labelled | D13: =B13&"_"&C13 -> Bacon CBD extract 54.8g_extract_ingested_labelled | E13: 12
I198: =C198&"_RTV" -> _RTV
I199: =C199&"_RTV" -> _RTV
I200: =C200&"_RTV" -> _RTV
I201: =C201&"_RTV" -> _RTV
I202: =C202&"_RTV" -> _RTV
I203: =C203&"_RTV" -> _RTV
I216: =C216&"_RTV" -> _RTV
I236: =C236&"_RTV" -> _RTV

Sheet Sheet1
A1: sales_stream | B1: Shipping date | C1: distributor_stream | D1: po_number | E1: level | K1: PO_date | L1: sales_stream | M1: Shipping date | N1: distributor_stream | O1: po_number | P1: Partner | Q1: Product Price | R1: PO_price | AB1: 收到订单日期 | AC1: 销售渠道 | AD1: 发货日期 | AE1: 销售途径 | AF1: 订单号 | AG1: 品牌 | AH1: 订单价格
A2: BCLDB_WT | B2: 45797 | C2: Provincial Distribution | D2: PO_50044423 | E2: 1 | H2: level 1 | I2: =56*5.5*5.5 -> 1694 | K2: Shipping date | L2: distributor_stream | M2: po_number | N2: product_name | O2: ProductLot# | P2: Excised(Yes/No) | Q2: Excisedfor | R2: packondate_labelled | AA2: =AF2&AG2 -> PO_0082726_legacy250403-1Aviator Cannabis Co. | AB2: 45747 | AC2: OCS_redistribution | AD2: 45750 | AE2: Provincial Distribution | AF2: PO_0082726_legacy250403-1 | AG2: Aviator Cannabis Co. | AH2: {=SUMIF(S2:S57,AA2:AA23,R2:R57)} -> 0
A3: YLC | B3: 45799 | C3: Provincial Distribution | D3: PO_00023226 | E3: 2 | H3: level 2 | I3: 1375 | K3: 45790 | L3: Provincial Distribution | M3: PO_494609_OFDMB | N3: November Rain Blast Pre-Roll - Blueberry-3 x 0.5g Pre-Roll | Q3: MB | AA3: =AF3&AG3 -> PO_0082726_legacy250403-1Apothecary Botanicals | AB3: 45747 | AC3: OCS_redistribution | AD3: 45750 | AE3: Provincial Distribution | AF3: PO_0082726_legacy250403-1 | AG3: Apothecary Botanicals | AH3: 0
A4: BCDD | B4: 45797 | C4: Retail | D4: PO_1113 | E4: 3 | H4: level 3 | I4: 825 | K4: 45791 | L4: Retail | M4: PO_1111 | N4: November Rain Blast Pre-Roll - Watermelon-3 x 0.5g Pre-Roll | Q4: MB | AA4: =AF4&AG4 -> PO_1071Apothecary Botanicals | AB4: 45747 | AC4: BCDD | AD4: 45748 | AE4: Retail | AF4: PO_1071 | AG4: Apothecary Botanicals | AH4: 0 | BA4: po_shipdate | BB4: Appointment date | BC4: Appointment # | BD4: Tracking number | BE4: Released (Y/N) | BF4: PO_date | BG4: sales_stream | BH4: Shipping date | BI4: distributor_stream | BJ4: po_number | BK4: product_name | BL4: ProductLot# | BM4: Excised(Yes/No) | BN4: Excisedfor | BO4: packondate_labelled | BP4: quantity_unit | BQ4: unitpercase | BR4: cases | BV4: God's Space Needle Bubble Hash | BW4: WX2021050701A | BX4: 44510 | BY4: 30
A5: BCDD | B5: 45797 | C5: Retail | D5: PO_1114 | E5: 3 | H5: level 4 | I5: 825 | K5: 45790 | L5: Provincial Distribution | M5: PO_495906_OFDMB | N5: November Rain Pre-Roll - Rose-3 x 0.5g Pre-Roll | Q5: MB | AA5: =AF5&AG5 -> PO_1070Apothecary Botanicals | AB5: 45747 | AC5: BCDD | AD5: 45748 | AE5: Retail | AF5: PO_1070 | AG5: Apothecary Botanicals | AH5: 0 | BA5: 45792 | BC5: NEED BOOKING | BF5: 45749 | BG5: AGLC | BI5: Provincial Distribution | BJ5: PO_74167 | BK5: THC oil 30 ml | BL5: EX24101802V30 | BM5: THC oil 27.6g | BN5: extract_ingested_cased_MB | BO5: 45588 | BP5: 108 | BQ5: 6 | BR5: 18 | BV5: Tundra Bubble Bubble Hash | BW5: CW22011701 | BX5: 44879 | BY5: 30
A6: BCDD_ROGWORLD | B6: 45797 | C6: Retail | D6: PO_1114 | E6: 4 | H6: level 5 | I6: 750 | K6: 45791 | L6: Retail | M6: PO_1112 | N6: November Rain Infused Pre-Roll - Rose-3 x 0.5g Pre-Roll | O6: PR2303IN02F5P3 | P6: YES | Q6: BC | R6: 45478 | AA6: =AF6&AG6 -> PO_475927_OFDMBApothecary Botanicals | AB6: 45748 | AC6: MBLL_redistribution | AD6: 45748 | AE6: Provincial Distribution | AF6: PO_475927_OFDMB | AG6: Apothecary Botanicals | AH6: 0 | BA6: 45792 | BC6: NEED BOOKING | BF6: 45749 | BG6: AGLC | BI6: Provincial Distribution | BJ6: PO_74167 | BK6: November Rain Pre-Roll - Trident Pre-Roll -3 x 0.5g | BL6: PR241104F5P3 | BM6: November Rain Trident preroll 3 x 0.5g | BN6: preroll_cased_ON | BO6: 45588 | BP6: 300 | BQ6: 12 | BR6: 25 | BV6: Romulan Grape God Bubble Hash | BW6: CW2103051 | BX6: 44806 | BY6: 30
A7: BCDD | B7: 45797 | C7: Retail | D7: PO_1115 | E7: 5 | H7: level 6 | I7: 625 | K7: 45792 | L7: Retail | M7: PO_DD_Weeds2025051401 | N7: November Rain- White Widow Live Resin Extract 1G LTO! | O7: LR23032101 | P7: YES | Q7: BC | R7: 45793 | AA7: =AF7&AG7 -> PO_1072Apothecary Botanicals | AB7: 45748 | AC7: BCDD | AD7: 45750 | AE7: Retail | AF7: PO_1072 | AG7: Apothecary Botanicals | AH7: 0 | BA7: 45792 | BC7: NEED BOOKING | BF7: 45749 | BG7: AGLC | BI7: Provincial Distribution | BJ7: PO_74167 | BK7: November Rain Pre-Roll - Monkey King Pre-Roll- 2 x 0.5g | BL7: PR2401F5P2 | BM7: Monkey King preroll 2 x 0.5g | BN7: preroll_labelled | BO7: 45670 | BP7: 180 | BQ7: 12 | BR7: 15 | BV7: Venom OG Live Rosin | BW7: 25-FP001 | BX7: 45739 | BY7: 30
A8: BCDD | B8: 45797 | C8: Retail | D8: PO_1116 | E8: 6 | H8: level 7 | I8: 574.75 | K8: 45791 | L8: Intra Industry | M8: PO_02279 | N8: Gelato Prerolls 3x0.5g | O8: PR21071201G5 | P8: YES | Q8: BC | R8: 45779 | AA8: =AF8&AG8 -> PO_476527Apothecary Botanicals | AB8: 45749 | AC8: MBLL_redistribution | AD8: 45749 | AE8: Provincial Distribution | AF8: PO_476527 | AG8: Apothecary Botanicals | AH8: 0 | BA8: 45792 | BC8: NEED BOOKING | BF8: 45749 | BG8: AGLC | BI8: Provincial Distribution | BJ8: PO_74167 | BK8: November Rain Blast Pre-Roll - Blueberry-3 x 0.5g Pre-Roll | BN8: AB | BP8: 210 | BQ8: 6 | BR8: 35 | BV8: Northern Apple Jaxx Live Rosin | BW8: RP24001 | BX8: 45605 | BY8: 30
A9: BCDD | B9: 45797 | C9: Retail | D9: PO_1117 | E9: 6 | H9: level 8 | K9: 45793 | L9: Provincial Distribution | M9: PO_498186_OFDMB | N9: ROGWORLD-Lemonade Octane Live Resin Biodegradable Hemp Vape Pen 1g | O9: ROGEX001G1 | P9: YES | Q9: BC | R9: 45740 | AA9: =AF9&AG9 -> PO_1073Apothecary Botanicals | AB9: 45748 | AC9: BCDD | AD9: 45750 | AE9: Retail | AF9: PO_1073 | AG9: Apothecary Botanicals | AH9: 0 | BA9: 45792 | BC9: NEED BOOKING | BF9: 45749 | BG9: AGLC | BI9: Provincial Distribution | BJ9: PO_74167 | BK9: Midnight Kruntz 7g dried flower | BN9: AB | BP9: 300 | BQ9: 6 | BR9: 50 | BV9: Live Duo | BW9: FP23004 | BX9: 45689 | BY9: 18
A10: MBLL_redistribution | B10: 45797 | C10: Provincial Distribution | D10: PO_499949_OFDMB | E10: 7 | N10: Midnight Kruntz 10x0.5g preroll | O10: PR2501F5P10 | P10: YES | Q10: BC | R10: 45707 | AA10: =AF10&AG10 -> PO_74167Apothecary Botanicals | AB10: 45749 | AC10: AGLC | AE10: Provincial Distribution | AF10: PO_74167 | AG10: Apothecary Botanicals | AH10: 0 | BA10: 45803 | BC10: NEED BOOKING | BF10: 45757 | BG10: AGLC | BI10: Provincial Distribution | BJ10: PO_74327 | BK10: November Rain Blast Pre-Roll - Blueberry-3 x 0.5g Pre-Roll | BL10: PR251105F5P3 | BM10: YES | BN10: AB | BO10: 45763 | BP10: 600 | BQ10: 6 | BR10: 100 | BV10: Synergy Oil | BW10: EX24092701V30 | BX10: 45640
A11: BCDD | B11: 45799 | C11: Retail | D11: PO_1118 | E11: 8 | N11: November Rain Pre-roll - Animal Mintz 2x1g | O11: PR2507F1P2 | P11: YES | Q11: BC | R11: 45772 | AA11: =AF11&AG11 -> PO_Burb2025040201BURB | AB11: 45750 | AC11: DD_BURB | AD11: 45751 | AE11: Retail | AF11: PO_Burb2025040201 | AG11: BURB | AH11: 0 | BF11: 45762 | BG11: BCDD | BH11: 45764 | BI11: Retail | BJ11: PO_1095 | BK11: Pot Shot- Tropical Fruit | BL11: EX25012101V50 | BM11: YES | BN11: BC | BO11: 45700 | BP11: 24 | BQ11: 12 | BR11: 2
A12: BCDD | B12: 45799 | C12: Retail | D12: PO_1119 | E12: 9 | N12: Pot Shot- Tropical Fruit | Q12: MB | AA12: =AF12&AG12 -> PO_1075Apothecary Botanicals | AB12: 45750 | AC12: BCDD | AD12: 45750 | AE12: Retail | AF12: PO_1075 | AG12: Apothecary Botanicals | AH12: 0 | BF12: 45762 | BG12: BCDD | BH12: 45764 | BI12: Retail | BJ12: PO_1095 | BK12: Gastro-pop Diamond Infused 3x0.5g pre-rolls | BL12: PR2501INF5P3 | BM12: YES | BN12: BC | BO12: 45756 | BP12: 12 | BQ12: 12 | BR12: 1
A13: MBLL_redistribution | B13: 45798 | C13: Provincial Distribution | D13: PO_500367_OFDMB | E13: 10 | N13: November Rain Pre-roll - Animal Mintz 2x1g | O13: PR2507F1P2 | P13: YES | Q13: BC | R13: 45772 | AA13: =AF13&AG13 -> PO_1076Apothecary Botanicals | AB13: 45750 | AC13: BCDD | AD13: 45751 | AE13: Retail | AF13: PO_1076 | AG13: Apothecary Botanicals | AH13: 0 | BF13: 45762 | BG13: BCDD | BH13: 45764 | BI13: Retail | BJ13: PO_1095 | BK13: Blaster Multi Pack Prerolls 12x0.5g | BL13: PR251108F5P12 | BM13: YES | BN13: BC | BO13: 45755 | BP13: 12 | BQ13: 12 | BR13: 1
A14: MBLL_redistribution | B14: 45799 | C14: Provincial Distribution | D14: PO_500120 | E14: 11 | N14: Blaster Multi Pack Prerolls 12x0.5g | O14: PR251108F5P12 | P14: YES | Q14: BC | R14: 45777 | AA14: =AF14&AG14 | AH14: 594522 | BF14: 45762 | BG14: BCDD | BH14: 45764 | BI14: Retail | BJ14: PO_1095 | BK14: Gelato Prerolls 3x0.5g | BL14: PR2301F5P3 | BM14: YES | BN14: BC | BO14: 45742 | BP14: 12 | BQ14: 12 | BR14: 1
A15: BCDD | B15: 45800 | C15: Retail | D15: PO_1120 | N15: November Rain- White Widow Live Resin Extract 1G LTO! | O15: LR23032101 | P15: YES | Q15: BC | R15: 45793 | AA15: =AF15&AG15 | AH15: 594522 | BF15: 45762 | BG15: BCDD_ROGWORLD | BH15: 45764 | BI15: Retail | BJ15: PO_1095 | BK15: ROGWORLD-Lemonade Octane Live Resin Biodegradable Hemp Vape Pen 1g | BL15: ROGEX001G1 | BM15: YES | BN15: BC | BO15: 45740 | BP15: 12 | BQ15: 12 | BR15: 1
N16: November Rain Blast Pre-Roll - Blueberry-3 x 0.5g Pre-Roll | O16: PR241105F5P3 | P16: YES | Q16: BC | R16: 45581 | AA16: =AF16&AG16 | AH16: 594522 | BA16: 45779 | BF16: 45758 | BG16: BCLDB | BI16: Provincial Distribution | BJ16: PO_50043536 | BK16: Maximum Strength CBD Roll-on Topical Cream | BN16: BC | BP16: 600 | BQ16: 12 | BR16: 50
N17: Midnight Kruntz 10x0.5g preroll | O17: PR2516F5P10 | P17: YES | Q17: BC | R17: 45772 | AA17: =AF17&AG17 | AH17: 594522 | BA17: 45792 | BF17: 45757 | BG17: BCLDB_ROGWORLD | BI17: Provincial Distribution | BJ17: PO_50043425 | BK17: ROGWORLD-RUNTZ MUFFIN CRUMBLE-1G | BN17: BC | BP17: 1800 | BQ17: 12 | BR17: 150
N18: WEEDS-PINEAPPLE SOUR-28G | O18: 2025030701G28 | P18: YES | Q18: BC | R18: 45786 | AA18: =AF18&AG18 | AH18: 594522 | BA18: 45768 | BF18: 45754 | BG18: BCLDB_WT | BI18: Provincial Distribution | BJ18: PO_50043351 | BK18: Super Sativa Oil 27.6 g | BN18: BC | BP18: 420 | BQ18: 6 | BR18: 70
N19: Rilaxe The One Night Stand Blunt 1x1g | O19: PR2515F1P1 | P19: YES | Q19: ON | R19: 45772 | AA19: =AF19&AG19 | AH19: 594522 | BF19: 45761 | BG19: Cannmart | BI19: Intra Industry | BJ19: PO_02276 | BK19: Rilaxe The One Night Stand Blunt 1x1g | BN19: AB | BQ19: 12 | BR19: 0
N20: Pot Shot- Tropical Fruit | Q20: MB | AA20: =AF20&AG20 | AH20: 594522 | BF20: 45735 | BG20: DD_WT | BI20: Retail | BJ20: PO_sumtDDwt250317 | BK20: Grapefruit Cake MAC Live Rosin | BN20: BC | BP20: 12 | BQ20: 6 | BR20: 2
S21: =O21&P21 | AA21: =AF21&AG21 | AH21: 594522 | BA21: 45778 | BC21: NEED BOOKING | BF21: 45757 | BG21: OCS | BI21: Provincial Distribution | BJ21: PO_0082982 | BK21: Pot Shot- Coconut Lime | BN21: ON | BP21: 84 | BQ21: 12 | BR21: 7
S22: =O22&P22 | AA22: =AF22&AG22 | AH22: 594522 | AN22: PO_date | AO22: sales_stream | AP22: Shipping date | AQ22: po_number | BA22: 45778 | BC22: NEED BOOKING | BF22: 45757 | BG22: OCS | BI22: Provincial Distribution | BJ22: PO_0082982 | BK22: Apothecary Botanicals Topical CBD Mini Roll-on 45 g | BN22: ON | BP22: 12 | BQ22: 12 | BR22: 1
S23: =O23&P23 | AA23: =AF23&AG23 | AH23: 594522 | AO23: BCLDB_WT | AP23: 45744 | AQ23: PO_50041983 | BA23: 45778 | BC23: NEED BOOKING | BF23: 45757 | BG23: OCS | BI23: Provincial Distribution | BJ23: PO_0083270 | BK23: Maximum Strength CBD Roll-on Topical Cream | BN23: ON | BP23: 108 | BQ23: 12 | BR23: 9
S24: =O24&P24 | AO24: Medicibis | AP24: 45744 | AQ24: PO_00001786 | BA24: 45764 | BC24: NEED BOOKING | BF24: 45761 | BG24: OCS | BH24: 45764 | BI24: Provincial Distribution | BJ24: PO_0083524 | BK24: Pot Shot- Tropical Fruit | BL24: EX25012101V50 | BM24: YES | BN24: ON | BO24: 45700 | BP24: 60 | BQ24: 12 | BR24: 5
S25: =O25&P25 | AR25: OCS | AS25: 45743 | AT25: PO_0080542_legacy250327 | BA25: 45764 | BC25: NEED BOOKING | BF25: 45761 | BG25: OCS | BH25: 45764 | BI25: Provincial Distribution | BJ25: PO_0083524 | BK25: November Rain Blast Pre-Roll - Blueberry-3 x 0.5g Pre-Roll | BL25: PR241105F5P3 | BM25: YES | BN25: ON | BO25: 45756 | BP25: 24 | BQ25: 12 | BR25: 2
S26: =O26&P26 | AR26: BCLDB_WT | AS26: 45744 | AT26: PO_50042503 | BA26: 45764 | BC26: NEED BOOKING | BF26: 45761 | BG26: OCS | BH26: 45764 | BI26: Provincial Distribution | BJ26: PO_0083524 | BK26: November Rain Vape Canadian Thunder 0.5g Sativa | BL26: EX24111301G05 | BM26: YES | BN26: ON | BO26: 45749 | BP26: 12 | BQ26: 12 | BR26: 1
S27: =O27&P27 | AR27: BCLDB_WT | AS27: 45744 | AT27: PO_50042517 | BA27: 45776 | BF27: 45754 | BG27: SLGA_redistribution | BI27: Intra Industry | BJ27: PO_04-040725 | BK27: Midnight Kruntz 7g dried flower | BN27: SK | BP27: 360 | BQ27: 12 | BR27: 30
S28: =O28&P28 | U28: {=_xlfn.UNIQUE(K1:P57)} -> PO_date | V28: sales_stream | W28: Shipping date | X28: distributor_stream | Y28: po_number | Z28: Partner | AQ28: 45743 | AR28: Sample | AS28: 45743 | AT28: steve250327 | BA28: 45776 | BF28: 45754 | BG28: SLGA_redistribution | BI28: Intra Industry | BJ28: PO_04-040725 | BK28: Midnight Kruntz 10x0.5g preroll | BN28: SK | BP28: 180 | BQ28: 12 | BR28: 15
S29: =O29&P29 | U29: Shipping date | V29: distributor_stream | W29: po_number | X29: product_name | Y29: ProductLot# | Z29: Excised(Yes/No) | AQ29: 45741 | AR29: MBLL_redistribution | AS29: 45743 | AT29: PO_472627_OFDMB | BF29: 45763 | BG29: BCDD | BI29: Retail | BJ29: PO_1096 | BK29: November Rain Vape Tropical Meteor Shower 0.5g Sativa | BL29: EX24101703G05 | BM29: November Rain Vape Tropical Meteor Shower 0.5g Sativa | BN29: extract_inhaled_labelled | BO29: 45603 | BP29: 24 | BQ29: 12 | BR29: 2
S30: =O30&P30 | U30: 45790 | V30: Provincial Distribution | W30: PO_494609_OFDMB | X30: November Rain Blast Pre-Roll - Blueberry-3 x 0.5g Pre-Roll | Y30: 0 | Z30: 0 | AQ30: 45743 | AR30: NTLCC | AS30: 45744 | AT30: PO_10013414 | BF30: 45763 | BG30: BCDD | BI30: Retail | BJ30: PO_1096 | BK30: November Rain Vape Concord Grape 1g | BL30: EX25020601G1 | BM30: November Rain Concord Grape vape 1g | BN30: extract_inhaled_labelled | BO30: 45707 | BP30: 24 | BQ30: 12 | BR30: 2
S31: =O31&P31 | U31: 45791 | V31: Retail | W31: PO_1111 | X31: November Rain Blast Pre-Roll - Watermelon-3 x 0.5g Pre-Roll | Y31: 0 | Z31: 0 | AQ31: 45743 | AR31: BCDD | AS31: 45744 | AT31: PO_1069 | BF31: 45763 | BG31: BCDD | BI31: Retail | BJ31: PO_1096 | BK31: November Rain Blast Pre-Roll - Blueberry-3 x 0.5g Pre-Roll | BL31: PR241105F5P3 | BM31: November Rain Blueberry preroll 3 x 0.5g | BN31: preroll_labelled | BO31: 45581 | BP31: 1 | BQ31: 12 | BR31: 0.083333333
S32: =O32&P32 | U32: 45790 | V32: Provincial Distribution | W32: PO_495906_OFDMB | X32: November Rain Pre-Roll - Rose-3 x 0.5g Pre-Roll | Y32: 0 | Z32: 0 | AR32: BCDD | AS32: 45748 | AT32: PO_1071 | BF32: 45763 | BG32: BCDD | BI32: Retail | BJ32: PO_1096 | BK32: November Rain Blast Pre-Roll - Blueberry-3 x 0.5g Pre-Roll | BP32: 35 | BQ32: 12 | BR32: 2.9166667
S33: =O33&P33 | U33: 45791 | V33: Retail | W33: PO_1112 | X33: November Rain Infused Pre-Roll - Rose-3 x 0.5g Pre-Roll | Y33: PR2303IN02F5P3 | Z33: YES | AR33: BCDD | AS33: 45748 | AT33: PO_1070 | BF33: 45763 | BG33: BCDD | BI33: Retail | BJ33: PO_1096 | BK33: November Rain Blast Pre-Roll - Lemon ice tea-3 x 0.5g Pre-Roll | BL33: PR241101F5P3 | BM33: November Rain Lemon Ice Tea preroll 3 x 0.5g | BN33: preroll_labelled | BO33: 45707 | BP33: 17 | BQ33: 12 | BR33: 1.4166667
S34: =O34&P34 | U34: 45792 | V34: Retail | W34: PO_DD_Weeds2025051401 | X34: November Rain- White Widow Live Resin Extract 1G LTO! | Y34: LR23032101 | Z34: YES | AR34: MBLL_redistribution | AS34: 45749 | AT34: PO_476527 | BF34: 45763 | BG34: BCDD | BI34: Retail | BJ34: PO_1096 | BK34: November Rain Blast Pre-Roll - Lemon ice tea-3 x 0.5g Pre-Roll | BN34: BC | BP34: 19 | BQ34: 12 | BR34: 1.5833333
S35: =O35&P35 | U35: 45791 | V35: Intra Industry | W35: PO_02279 | X35: Gelato Prerolls 3x0.5g | Y35: PR21071201G5 | Z35: YES | BF35: 45764 | BG35: BCDD | BH35: 45764 | BI35: Retail | BJ35: PO_1097 | BK35: November Rain Pre-roll - Animal Mintz 2x1g | BN35: BC | BP35: 12 | BQ35: 12 | BR35: 1
S36: =O36&P36 | U36: 45793 | V36: Provincial Distribution | W36: PO_498186_OFDMB | X36: ROGWORLD-Lemonade Octane Live Resin Biodegradable Hemp Vape Pen 1g | Y36: ROGEX001G1 | Z36: YES | BF36: 45764 | BG36: BCDD_ROGWORLD | BH36: 45764 | BI36: Retail | BJ36: PO_1097 | BK36: ROGWORLD-Lemonade Octane Live Resin Biodegradable Hemp Vape Pen 1g | BN36: BC | BP36: 12 | BQ36: 12 | BR36: 1
S37: =O37&P37 | U37: 0 | V37: 0 | W37: 0 | X37: Midnight Kruntz 10x0.5g preroll | Y37: PR2501F5P10 | Z37: YES | BF37: 45763 | BG37: BCDD | BH37: 45764 | BI37: Retail | BJ37: PO_10013 | BK37: Pot Shot- Tropical Fruit | BN37: BC | BP37: 12 | BQ37: 12 | BR37: 1
S38: =O38&P38 | U38: 0 | V38: 0 | W38: 0 | X38: November Rain Pre-roll - Animal Mintz 2x1g | Y38: PR2507F1P2 | Z38: YES | BF38: 45763 | BG38: BCDD | BH38: 45764 | BI38: Retail | BJ38: PO_10013 | BK38: Pot Shot- Citrus | BN38: BC | BP38: 12 | BQ38: 12 | BR38: 1
S39: =O39&P39 | U39: 0 | V39: 0 | W39: 0 | X39: Pot Shot- Tropical Fruit | Y39: 0 | Z39: 0
S40: =O40&P40 | U40: 0 | V40: 0 | W40: 0 | X40: Blaster Multi Pack Prerolls 12x0.5g | Y40: PR251108F5P12 | Z40: YES
S41: =O41&P41 | U41: 0 | V41: 0 | W41: 0 | X41: November Rain- White Widow Live Resin Extract 1G LTO! | Y41: LR23032101 | Z41: YES
S42: =O42&P42 | U42: 0 | V42: 0 | W42: 0 | X42: November Rain Blast Pre-Roll - Blueberry-3 x 0.5g Pre-Roll | Y42: PR241105F5P3 | Z42: YES
S43: =O43&P43 | U43: 0 | V43: 0 | W43: 0 | X43: Midnight Kruntz 10x0.5g preroll | Y43: PR2516F5P10 | Z43: YES
S44: =O44&P44 | U44: 0 | V44: 0 | W44: 0 | X44: WEEDS-PINEAPPLE SOUR-28G | Y44: 2025030701G28 | Z44: YES
S45: =O45&P45 | U45: 0 | V45: 0 | W45: 0 | X45: Rilaxe The One Night Stand Blunt 1x1g | Y45: PR2515F1P1 | Z45: YES
S46: =O46&P46 | U46: 0 | V46: 0 | W46: 0 | X46: 0 | Y46: 0 | Z46: 0
S47: =O47&P47
S48: =O48&P48
S49: =O49&P49
S50: =O50&P50
S51: =O51&P51
S52: =O52&P52
S53: =O53&P53
S54: =O54&P54
S55: =O55&P55
S56: =O56&P56
S57: =O57&P57

Sheet Sheet2
A1: po_number | B1: product_name | C1: ProductLot# | D1: Excised(Yes/No) | E1: Excisedfor | F1: packondate_labelled | G1: quantity_unit | H1: unitpercase | I1: cases | J1: cannabis_netweight_gram
A2: PO_DD_Burb2025020401 | B2: Blue Gumdrop 5 x 0.5g Pre Roll | C2: PR2503F5P5 | D2: YES | E2: BC | F2: 45685 | G2: 324 | H2: 12 | I2: 27 | J2: 810
A3: PO_DD_Burb2025041701 | B3: Blue Gumdrop 5 x 0.5g Pre Roll | C3: PR2514F5P5 | D3: YES | E3: BC | F3: 45765 | G3: 480 | H3: 12 | I3: 40 | J3: 1200
A4: PO_Burb2025060501 | B4: Blue Gumdrop 5 x 0.5g Pre Roll | C4: PR2514F5P5 | D4: YES | E4: BC | F4: 45814 | G4: 408 | H4: 12 | I4: 34 | J4: 1020
A5: PO_50040988 | B5: Book Club-Blue Gumdrop 14g | C5: 2025010201G14 | D5: YES | E5: BC | F5: 45693 | G5: 750 | H5: 6 | I5: 125 | J5: 10500
A6: PO_50041554 | B6: Book Club-Blue Gumdrop 14g | C6: 2025010201G14 | D6: YES | E6: BC | F6: 45709 | G6: 600 | H6: 6 | I6: 100 | J6: 8400
A7: PO_DD_Burb_2025012801 | B7: Book Club-Blue Gumdrop 28g | C7: 2024120501G28 | D7: YES | E7: BC | F7: 45682 | G7: 144 | H7: 12 | I7: 12 | J7: 4032
A8: PO_Burb2025040201 | B8: Book Club-Blue Gumdrop 28g | C8: 2024120501G28 | D8: YES | E8: BC | F8: 45744 | G8: 108 | H8: 12 | I8: 9 | J8: 3024
A9: PO_Burb2025060501 | B9: Book Club-Blue Gumdrop 28g | C9: 2025042201G28 | D9: YES | E9: BC | F9: 45805 | G9: 180 | H9: 12 | I9: 15 | J9: 5040 | K9: =SUM(J2:J9) -> 34026
A10: DD_burb_2025022001 | B10: Book Club-Kruntz 28g | C10: 2024121801G28 | D10: yes | E10: BC | F10: 45707 | G10: 300 | H10: 12 | I10: 25 | J10: 8400
A11: DD_Burb2025031401 | B11: BOOK CLUB-LICORICE GUMBALL Preroll 5x0.5g | C11: PR2505F5P5 | D11: YES | E11: BC | F11: 45730 | G11: 492 | H11: 12 | I11: 41 | J11: 1230
A12: PO_Burb2025060501 | B12: BOOK CLUB-LICORICE GUMBALL Preroll 5x0.5g | C12: PR2505F5P5 | D12: YES | E12: BC | F12: 45814 | G12: 360 | H12: 12 | I12: 30 | J12: 900
A13: PO_DD2024102301 | B13: BOOK CLUB-LICORICE GUMBALL-14G | C13: 2024092002 | D13: YES | E13: BC | F13: 45581 | G13: 1149 | H13: 12 | I13: 95.75 | J13: 16086
A14: PO_DD2024102301 | B14: BOOK CLUB-LICORICE GUMBALL-14G | C14: 2024092003 | D14: YES | E14: BC | F14: 45581 | G14: 411 | H14: 12 | I14: 34.25 | J14: 5754 | K14: =SUM(J11:J14) -> 23970
A15: PO_DD_Burb_2025012801 | B15: Book Club-Pressure Pie 28g | C15: 2024110601G28 | D15: YES | E15: BC | F15: 45682 | G15: 144 | H15: 12 | I15: 12 | J15: 4032
A16: PO_Burb2025040201 | B16: Book Club-Pressure Pie 28g | C16: 2024110601G28 | D16: YES | E16: BC | F16: 45744 | G16: 156 | H16: 12 | I16: 13 | J16: 4368 | K16: =SUM(J15:J16)+SUM(J20:J22) -> 10260
A17: DD_Burb2025031401 | B17: BOOK CLUB-Unicorn Poop Preroll 5x0.5g | C17: PR2506F5P5 | D17: YES | E17: BC | F17: 45723 | G17: 492 | H17: 12 | I17: 41 | J17: 1230
A18: PO_Burb2025060501 | B18: BOOK CLUB-Unicorn Poop Preroll 5x0.5g | C18: PR2506F5P5 | D18: YES | E18: BC | F18: 45814 | G18: 516 | H18: 12 | I18: 43 | J18: 1290
A19: PO_DD2024102301 | B19: BOOK CLUB-UNICORN POOP-14G | C19: 2024092001 | D19: YES | E19: BC | F19: 45581 | G19: 888 | H19: 12 | I19: 74 | J19: 12432 | K19: =SUM(J17:J19) -> 14952
A20: PO_DD_Burb2025020401 | B20: Pressure Pie 5 x 0.5g Pre Roll | C20: PR2502F5P5 | D20: YES | E20: BC | F20: 45685 | G20: 336 | H20: 12 | I20: 28 | J20: 840
A21: PO_DD_Burb2025041701 | B21: Pressure Pie 5 x 0.5g Pre Roll | C21: PR2502F5P5 | D21: YES | E21: BC | F21: 45765 | G21: 396 | H21: 12 | I21: 33 | J21: 990
A22: PO_Burb2025060501 | B22: Pressure Pie 5 x 0.5g Pre Roll | C22: PR2502F5P5 | D22: YES | E22: BC | F22: 45814 | G22: 12 | H22: 12 | I22: 1 | J22: 30
L24: shipment (S) | M24: name | N24: receiving net (R) | O24: expected inventory (S-R) | P24: actual inventory (A) | Q24: A-E | R24: allowed difference (gram)=5% *R | S24: (A-E)/R | U24: OUTBOUND GROSS (O) | V24: # BAGV(B) | W24: (O-R)/R/B | X24: O-S | Y24: (O-S)/B/R
L25: =K9 -> 34026 | M25: blue gumdrop | N25: =8300+21800+5240 -> 35340 | O25: =N25-L25 -> 1314 | P25: =L55 -> 182 | Q25: =P25-O25 -> -1132 | R25: =0.05*N25 -> 1767 | S25: =Q25/N25 -> -0.032031692 | U25: 41073.5 | V25: 20 | W25: =(U25-N25)/N25/V25 -> 0.0081119128 | X25: =U25-L25 -> 7047.5 | Y25: =X25/V25/N25 -> 0.009970996
M26: kruntz
L30: =K14 -> 23970 | M30: licorice gumball | N30: =16000+5900 -> 21900 | O30: =N30-L30 -> -2070 | P30: =L53 -> 7447 | Q30: =P30-O30 -> 9517 | R30: =0.05*N30 -> 1095 | S30: =Q30/N30 -> 0.43456621 | T30: *** | U30: 22416 | V30: 10 | W30: =(U30-N30)/N30/V30 -> 0.0023561644 | X30: =U30-L30 -> -1554 | Y30: =X30/V30/N30 -> -0.0070958904
L32: =K16 -> 10260 | M32: pressure pie | N32: 15863 | O32: =N32-L32 -> 5603 | P32: =L50 -> 5056 | Q32: =P32-O32 -> -547 | R32: =0.05*N32 -> 793.15 | S32: =Q32/N32 -> -0.034482759 | U32: 11213 | V32: 7 | W32: =(U32-N32)/N32/V32 -> -0.041876424 | X32: =U32-L32 -> 953 | Y32: =X32/V32/N32 -> 0.0085824155
L35: =K19 -> 14952 | M35: unicorn poop | N35: 12500 | O35: =N35-L35 -> -2452 | P35: =L54 -> -3398 | Q35: =P35-O35 -> -946 | R35: =0.05*N35 -> 625 | S35: =Q35/N35 -> -0.07568 | T35: * | U35: 13002 | V35: 4 | W35: =(U35-N35)/N35/V35 -> 0.01004 | X35: =U35-L35 -> -1950 | Y35: =X35/V35/N35 -> -0.039
L38: =SUM(L25:L35) -> 83208 | M38: TOTAL | N38: =SUM(N25:N35) -> 85603 | O38: =SUM(O25:O35) -> 2395 | P38: =SUM(P25:P35) -> 9287 | Q38: =P38-O38 -> 6892 | R38: =0.05*N38 -> 4280.15 | S38: =Q38/N38 -> 0.080511197 | T38: * | U38: =SUM(U25:U37) -> 87704.5 | V38: =SUM(V25:V37) -> 41 | W38: =(U38-N38)/N38/V38 -> 0.0005987652 | X38: =U38-L38 -> 4496.5 | Y38: =X38/V38/N38 -> 0.0012811552
M39: R-S | N39: =N38-L38 -> 2395
M40: (R-S)/R | N40: =N39/N38 -> 0.027977991
L47: actual inventory | M47: product_description | N47: lot_number | O47: pack_on_date | P47: quantity_unit | Q47: unit_name | R47: gross_weight | S47: net_weight | T47: check_time
M48: Pressure Pie dried flower | N48: 2024110601 | O48: NA | P48: 1 | Q48: unit | R48: 1514 | S48: 1419 | T48: 45748.705
M49: Pressure Pie dried flower | N49: 2024110601 | O49: NA | P49: 1 | Q49: unit | R49: 3090 | S49: 3000 | T49: 45609.687
L50: =SUM(S48:S50) -> 5056 | M50: Pressure Pie dried flower | N50: 2024110601 | O50: NA | P50: 1 | Q50: unit | R50: 724 | S50: 637 | T50: 45748.705
M51: Licorice Gumball milled flower | N51: PR2505 | O51: NA | P51: 1 | Q51: pail | R51: 2358 | S51: 618 | T51: 45811.644
M52: Licorice Gumball milled flower | N52: PR2505 | O52: NA | P52: 1 | Q52: pail | R52: 4426 | S52: 2676 | T52: 45698.635
L53: =SUM(S51:S53) -> 7447 | M53: Licorice Gumball milled flower | N53: PR2505 | O53: NA | P53: 1 | Q53: pail | R53: 5867 | S53: 4153 | T53: 45698.635
L54: -3398 | M54: Unicorn Poop milled flower | N54: PR2506 | O54: NA | P54: 0 | Q54: pail | R54: -3398 | S54: NULL | T54: 45803.417
L55: 182 | M55: Blue Gum Dried Flower Grade A | N55: 2025042201 | O55: NA | P55: 1 | Q55: bag | R55: 240 | S55: 182 | T55: 45821.625

Sheet Sheet3
A1: PO | B1: weight | C1: length | D1: width | E1: height | F1: tracking | G1: cost
B2: 3 | C2: 6 | D2: 6 | E2: 6 | F2: 335446020356 | G2: 43.69
A3: PO_503021 | B3: 3 | C3: 6 | D3: 6 | E3: 6 | F3: 335459704466 | G3: 58
A4: PO_502181_APOTHECARY | B4: 2 | C4: 8 | D4: 6 | E4: 4 | F4: 335460761315 | G4: 40.3
A5: PO_503918 | B5: 3 | C5: 6 | D5: 6 | E5: 6 | F5: 335468042262 | G5: 42
A6: PO_00001976 | B6: 61 | C6: 22 | D6: 22 | E6: 22 | F6: 335470535790 | G6: 204.44
A7: PO_00001976 | B7: 15.8 | C7: 22 | D7: 10 | E7: 6 | F7: 335470535790 | G7: 204.44
A8: PO_00001976 | B8: 15.8 | C8: 22 | D8: 10 | E8: 6 | F8: 335470535790 | G8: 204.44
A9: PO_504787 | B9: 3 | C9: 6 | D9: 6 | E9: 6 | F9: 335470838434 | G9: 43.92
A10: PO_505918 | B10: 3 | C10: 6 | D10: 6 | E10: 6 | F10: 335478543960 | G10: 40.47
A11: PO_507848 | F11: 335489377077 | G11: 38.42
A12: PO_507266 | B12: 3 | C12: 6 | D12: 6 | E12: 6 | F12: 335489416180 | G12: 38.88
A13: PO_507860 | B13: 3 | C13: 6 | D13: 6 | E13: 6 | F13: 335489430561 | G13: 38.88
A14: PO_00023299 | B14: 16 | C14: 24 | D14: 12 | E14: 16 | F14: 335493026348 | G14: 136.26
A15: PO_508181 | B15: 13 | C15: 13 | D15: 13 | E15: 9 | F15: 335493961981 | G15: 50.14
A16: OFDMB250609 | B16: 45 | C16: 24 | D16: 19 | E16: 12 | F16: 335494035876 | G16: 87.85
A17: PO_1131 | B17: 6 | C17: 14 | D17: 14 | E17: 6 | F17: 335499234102 | G17: 35.89
A18: PO_05-05225 | B18: 12 | C18: 22 | D18: 17 | E18: 8 | F18: 335506475243 | G18: 233.93/3
A19: PO_05-05225 | B19: 18 | C19: 22 | D19: 17 | E19: 12 | F19: 335506475243 | G19: 233.93/3
A20: PO_05-05225 | B20: 90 | C20: 22 | D20: 22 | E20: 22 | F20: 335506475243 | G20: 233.93/3
A21: PO_512279 | B21: 1 | C21: 4 | D21: 3 | E21: 2 | F21: 335511282345 | G21: 40
A22: PO_1133 | B22: 3 | C22: 12 | D22: 10 | E22: 6 | F22: 335514537778
A23: PO_1138 | B23: 4 | C23: 5 | D23: 13 | E23: 10 | F23: 335520160920 | G23: 20.68
A24: PO_1137 | B24: 3 | C24: 6 | D24: 12 | E24: 12 | F24: 335520177619 | G24: 19.07
A25: PO_515049 | B25: 3 | C25: 8 | D25: 11 | E25: 4 | F25: 335523600518 | G25: 30.4
A26: highway250624 | B26: 1 | C26: 2 | D26: 4 | E26: 7 | F26: 335529225724 | G26: 34
A27: PO_1143 | B27: 3 | C27: 12 | D27: 12 | E27: 12 | F27: 335535301782 | G27: 30
A28: PO_06-062625 | B28: 18 | C28: 24 | D28: 12 | E28: 18 | F28: 335539111070 | G28: 79.14
A29: PO_520696 | B29: 2 | C29: 6 | D29: 6 | E29: 6 | F29: 335550586440 | G29: 41.43
A30: PO_519039 | B30: 2 | C30: 6 | D30: 6 | E30: 6 | F30: 335550589048 | G30: 38.42
A31: PO_524578 | B31: 1 | C31: 8 | D31: 6 | E31: 5 | F31: 335563652130 | G31: 38
A32: legacy250710 | B32: 16 | C32: 12 | D32: 12 | E32: 12 | F32: 335566393450 | G32: 95.26
A33: PO_00002111 | B33: 50 | C33: 20 | D33: 16 | E33: 8 | G33: 765.14
A34: PO_00002111 | B34: 100.8 | C34: 22 | D34: 18 | E34: 10 | G34: 765.14
A35: PO_00002111 | B35: 12 | C35: 22 | D35: 10 | E35: 6 | G35: 765.14
A36: PO_00002111 | B36: 11 | C36: 22 | D36: 10 | E36: 6 | G36: 765.14
A37: PO_00002111 | B37: 6 | C37: 22 | D37: 10 | E37: 6 | G37: 765.14
A38: PO_00002111 | B38: 11 | C38: 22 | D38: 10 | E38: 6 | G38: 765.14
A39: PO_00002111 | B39: 8.7 | C39: 12 | D39: 12 | E39: 6 | G39: 765.14
A40: PO_00002111 | B40: 11 | C40: 22 | D40: 10 | E40: 6 | G40: 765.14
A41: PO_00002111 | B41: 11 | C41: 22 | D41: 10 | E41: 6 | G41: 765.14
A42: PO_00002111 | B42: 11 | C42: 22 | D42: 10 | E42: 6 | G42: 765.14
A43: PO_00002111 | B43: 97 | C43: 22 | D43: 18 | E43: 10 | G43: 765.14
A44: PO_00002111 | B44: 5.7 | C44: 22 | D44: 10 | E44: 6 | G44: 765.14
... A48: PO_00002111 | B48: 26 | C48: 22 | D48: 10 | E48: 6 | G48: 765.14
A49: PO_00023385 | B49: 38 | C49: 22 | D49: 22 | E49: 22 | F49: https://www.purolator.com/en/shipping/tracker?pin=335584232813&sdate=2025-07-18 | G49: 22
A50: PO_4500882766 | B50: 60 | C50: 24 | D50: 18 | E50: 12
A51: PO_4500882766 | B51: 55 | C51: 18 | D51: 18 | E51: 12
A52: PO_526428 | B52: 2 | C52: 8 | D52: 6 | E52: 4 | F52: 335603103391 | G52: 38
A53: PO_529839 | B53: 1 | C53: 6 | D53: 4 | E53: 4 | F53: 335603168659 | G53: 40.47

Sheet Sheet4
A1: calculation_method | B1: net | F1: calculation_method | G1: (Multiple Items) | I1: calculation_method | J1: gross | N1: calculation_method | O1: gross
A3: Row Labels | B3: Sum of number_of_unit | F3: Row Labels | G3: Sum of quantity_change_unit | I3: Row Labels | J3: Sum of gross_weight | N3: Row Labels | O3: Sum of quantity_change_gross_weight
A4: #1 | B4: 0 | C4: =VLOOKUP(A4,F:G,2,0) -> #N/A | D4: =IF(ISERROR(C4),B4,B4+C4) -> 0 | I4: Abby Leaf Inc Licorish Gumball dried flower | J4: 6096 | K4: =VLOOKUP(I4,N:O,2,0) -> -5396 | L4: =IF(ISERROR(K4),J4,J4+K4) -> 700 | N4: Abby Leaf Inc Licorish Gumball dried flower | O4: -5396
A5: 20:1 Mango CBD:THC extract 29.5g | B5: 20 | C5: =VLOOKUP(A5,F:G,2,0) -> #N/A | D5: =IF(ISERROR(C5),B5,B5+C5) -> 20 | F5: Animal Mint pre-roll 2 x 1g | G5: -2646 | I5: Abby Leaf Inc Licorish Gumball dried flower Grade A | J5: 10898 | K5: =VLOOKUP(I5,N:O,2,0) -> -10898 | L5: =IF(ISERROR(K5),J5,J5+K5) -> 0 | N5: Abby Leaf Inc Licorish Gumball dried flower Grade A | O5: -10898
A6: 4:1 Black Cherry CBD:THC extract 29.5g | B6: 24 | C6: =VLOOKUP(A6,F:G,2,0) -> #N/A | D6: =IF(ISERROR(C6),B6,B6+C6) -> 24 | F6: Apothecary Botanicals Gelato 14g dried flower | G6: -60 | I6: Abby Leaf Inc Licorish Gumball dried flower Grade B | J6: 6122 | K6: =VLOOKUP(I6,N:O,2,0) -> -6122 | L6: =IF(ISERROR(K6),J6,J6+K6) -> 0 | N6: Abby Leaf Inc Licorish Gumball dried flower Grade B | O6: -6122
A7: Afghan Hash 1g | B7: 21 | C7: =VLOOKUP(A7,F:G,2,0) -> #N/A | D7: =IF(ISERROR(C7),B7,B7+C7) -> 21 | F7: Aum CBD oil 27.4g | G7: -703 | I7: Abby Leaf Inc Unicorn Poop Grade A | J7: 9072 | K7: =VLOOKUP(I7,N:O,2,0) -> -9070 | L7: =IF(ISERROR(K7),J7,J7+K7) -> 2 | N7: Abby Leaf Inc Unicorn Poop Grade A | O7: -9070
A8: Animal Cookies dried flower 3.5 g | B8: 66 | C8: =VLOOKUP(A8,F:G,2,0) -> #N/A | D8: =IF(ISERROR(C8),B8,B8+C8) -> 66 | F8: Bacon CBD extract 27.3g | G8: -70 | I8: Abby Leaf Inc Unicorn Poop Grade B | J8: 3930 | K8: =VLOOKUP(I8,N:O,2,0) -> -3932 | L8: =IF(ISERROR(K8),J8,J8+K8) -> -2 | N8: Abby Leaf Inc Unicorn Poop Grade B | O8: -3932
A9: Animal Mint pre-roll 2 x 1g | B9: 2639 | C9: =VLOOKUP(A9,F:G,2,0) -> -2646 | D9: =IF(ISERROR(C9),B9,B9+C9) -> -7 | F9: Bacon CBD Extract 27.6g | G9: -127 | I9: Animal Mint dried flower | J9: 7565 | K9: =VLOOKUP(I9,N:O,2,0) -> -655 | L9: =IF(ISERROR(K9),J9,J9+K9) -> 6910 | N9: Animal Mint dried flower | O9: -655
A10: Apothecary Botanicals Gelato 14g dried flower | B10: 60 | C10: =VLOOKUP(A10,F:G,2,0) -> -60 | D10: =IF(ISERROR(C10),B10,B10+C10) -> 0 | F10: Bacon CBD extract 54.8g | G10: -3 | I10: Animal Mint milled flower | J10: 10340 | K10: =VLOOKUP(I10,N:O,2,0) -> -28332 | L10: =IF(ISERROR(K10),J10,J10+K10) -> -17992 | N10: Animal Mint milled flower | O10: -28332
A11: Aum CBD oil 27.4g | B11: 442 | C11: =VLOOKUP(A11,F:G,2,0) -> -703 | D11: =IF(ISERROR(C11),B11,B11+C11) -> -261 | F11: bath salt SPA 180 gram | G11: -220 | I11: Atlas trims | J11: 4152 | K11: =VLOOKUP(I11,N:O,2,0) -> #N/A | L11: =IF(ISERROR(K11),J11,J11+K11) -> 4152 | N11: Bacon CBD Extract | O11: -13470
A12: Backforty Blends Glacial Gold Clay Face Mask | B12: 550 | C12: =VLOOKUP(A12,F:G,2,0) -> #N/A | D12: =IF(ISERROR(C12),B12,B12+C12) -> 550 | F12: Blue Gum Dried Flower 28g | G12: -108 | I12: Bacon CBD Extract | J12: 61265 | K12: =VLOOKUP(I12,N:O,2,0) -> -13470 | L12: =IF(ISERROR(K12),J12,J12+K12) -> 47795 | N12: bath salt SPA 180 gram | O12: -71400
A13: Bacon CBD extract 27.3g | B13: 72 | C13: =VLOOKUP(A13,F:G,2,0) -> -70 | D13: =IF(ISERROR(C13),B13,B13+C13) -> 2 | F13: Blueberry Punch Bubble Hash 1g | G13: -353 | I13: bath salt SPA 180 gram | J13: 71400 | K13: =VLOOKUP(I13,N:O,2,0) -> -71400 | L13: =IF(ISERROR(K13),J13,J13+K13) -> 0 | N13: Blue Bandita Live Rosin | O13: -3905
A14: Bacon CBD Extract 27.6g | B14: 136 | C14: =VLOOKUP(A14,F:G,2,0) -> -127 | D14: =IF(ISERROR(C14),B14,B14+C14) -> 9 | F14: CBD Bacon Oil 10 mg 27.3g | G14: -629 | I14: Berri Blunt milled flower | J14: 88.04 | K14: =VLOOKUP(I14,N:O,2,0) -> #N/A | L14: =IF(ISERROR(K14),J14,J14+K14) -> 88.04 | N14: Blue Gum Dried Flower | O14: -27440
A15: Bacon CBD extract 29.5g | B15: 9 | C15: =VLOOKUP(A15,F:G,2,0) -> #N/A | D15: =IF(ISERROR(C15),B15,B15+C15) -> 9 | F15: CBD Neem Cream 120g | G15: -60 | I15: Blue Bandita Live Rosin | J15: 3905 | K15: =VLOOKUP(I15,N:O,2,0) -> -3905 | L15: =IF(ISERROR(K15),J15,J15+K15) -> 0 | N15: Blue Gum Dried Flower Grade A | O15: -14058
A16: Bacon CBD extract 54.8g | B16: 20 | C16: =VLOOKUP(A16,F:G,2,0) -> -3 | D16: =IF(ISERROR(C16),B16,B16+C16) -> 17 | F16: Chronic Mint preroll 1 x 1g | G16: -12 | I16: Blue Gum Dried Flower | J16: 27440 | K16: =VLOOKUP(I16,N:O,2,0) -> -27440 | L16: =IF(ISERROR(K16),J16,J16+K16) -> 0 | N16: Canadian Thunder Rosin Vape | O16: -2355.54
... A62: Grease Monkey preroll 1 x 1g | B62: 206 | C62: =VLOOKUP(A62,F:G,2,0) -> -72 | D62: =IF(ISERROR(C62),B62,B62+C62) -> 134 | F62: November Rain Blaster Multipack 0.5g*12 | G62: -1027 | I62: Pressure Pie dried flower | J62: 16541 | K62: =VLOOKUP(I62,N:O,2,0) -> -16199 | L62: =IF(ISERROR(K62),J62,J62+K62) -> 342 | N62: Grand Total | O62: -975335.28
A63: Grease Monkey preroll 1g | B63: 537 | C63: =VLOOKUP(A63,F:G,2,0) -> #N/A | D63: =IF(ISERROR(C63),B63,B63+C63) -> 537 | F63: November Rain Blueberry preroll 0.5g | G63: -9783 | I63: Pressure Pie milled flower | J63: 2386 | K63: =VLOOKUP(I63,N:O,2,0) -> -6622 | L63: =IF(ISERROR(K63),J63,J63+K63) -> -4236
A64: Grease Monkey preroll 3 x 0.5g | B64: 759 | C64: =VLOOKUP(A64,F:G,2,0) -> -849 | D64: =IF(ISERROR(C64),B64,B64+C64) -> -90 | F64: November Rain Blueberry preroll 3 x 0.5g | G64: -3406 | I64: Rockstar dried flower | J64: 61218 | K64: =VLOOKUP(I64,N:O,2,0) -> -41549 | L64: =IF(ISERROR(K64),J64,J64+K64) -> 19669
A65: Hara milled flower 14g | B65: 404 | C65: =VLOOKUP(A65,F:G,2,0) -> -404 | D65: =IF(ISERROR(C65),B65,B65+C65) -> 0 | F65: November Rain Concord Grape vape 0.5g | G65: -557 | I65: Rockstar milled flower | J65: 15426 | K65: =VLOOKUP(I65,N:O,2,0) -> -11059 | L65: =IF(ISERROR(K65),J65,J65+K65) -> 4367
A66: Hara milled flower 7g | B66: 106 | C66: =VLOOKUP(A66,F:G,2,0) -> -106 | D66: =IF(ISERROR(C66),B66,B66+C66) -> 0 | F66: November Rain Concord Grape vape 1g | G66: -145 | I66: Rogue milled flower | J66: 0 | K66: =VLOOKUP(I66,N:O,2,0) -> #N/A | L66: =IF(ISERROR(K66),J66,J66+K66) -> 0
A67: Infused preroll | B67: 104 | C67: =VLOOKUP(A67,F:G,2,0) -> #N/A | D67: =IF(ISERROR(C67),B67,B67+C67) -> 104 | F67: November Rain Gastro-pop Diamond Infused 3x0.5g Pre-Rolls | G67: -1010 | I67: Runtz Muffin Crumble (Rohan) | J67: 8583 | K67: =VLOOKUP(I67,N:O,2,0) -> -2437 | L67: =IF(ISERROR(K67),J67,J67+K67) -> 6146
A68: Infused preroll 1 x 1g | B68: 87 | C68: =VLOOKUP(A68,F:G,2,0) -> -12 | D68: =IF(ISERROR(C68),B68,B68+C68) -> 75 | F68: November Rain Lemon Ice Tea preroll 0.5g | G68: -992 | I68: Spotlight Vape | J68: 1092.42 | K68: =VLOOKUP(I68,N:O,2,0) -> #N/A | L68: =IF(ISERROR(K68),J68,J68+K68) -> 1092.42
A69: Infused preroll 1g | B69: 1625 | C69: =VLOOKUP(A69,F:G,2,0) -> -200 | D69: =IF(ISERROR(C69),B69,B69+C69) -> 1425 | F69: November Rain Lemon Ice Tea preroll 3 x 0.5g | G69: -1152 | I69: Strawberry Drizzle Vape | J69: 5516.58 | K69: =VLOOKUP(I69,N:O,2,0) -> -3364.95 | L69: =IF(ISERROR(K69),J69,J69+K69) -> 2151.63
A70: Infused preroll 3 x 0.5g | B70: 268 | C70: =VLOOKUP(A70,F:G,2,0) -> #N/A | D70: =IF(ISERROR(C70),B70,B70+C70) -> 268 | F70: November Rain Preroll Rose Mintz 3x0.5g | G70: -120 | I70: Super Sativa Oil | J70: 33155 | K70: =VLOOKUP(I70,N:O,2,0) -> -33155 | L70: =IF(ISERROR(K70),J70,J70+K70) -> 0
A71: Island KTL Live Resin 1g | B71: 170 | C71: =VLOOKUP(A71,F:G,2,0) -> -169 | D71: =IF(ISERROR(C71),B71,B71+C71) -> 1 | F71: November Rain Rose preroll 0.5g | G71: -4052 | I71: THC CBD balanced 1:1 oil | J71: 3995 | K71: =VLOOKUP(I71,N:O,2,0) -> -3990 | L71: =IF(ISERROR(K71),J71,J71+K71) -> 5
A72: Island Pink dried flower | B72: 0 | C72: =VLOOKUP(A72,F:G,2,0) -> #N/A | D72: =IF(ISERROR(C72),B72,B72+C72) -> 0 | F72: November Rain Rose preroll 3 x 0.5g | G72: -2128 | I72: THC Distillate | J72: 16952.39 | K72: =VLOOKUP(I72,N:O,2,0) -> -16025.49 | L72: =IF(ISERROR(K72),J72,J72+K72) -> 926.9
A73: Licorice Gumball dried flower 14g | B73: 1560 | C73: =VLOOKUP(A73,F:G,2,0) -> -1560 | D73: =IF(ISERROR(C73),B73,B73+C73) -> 0 | F73: November Rain Trident preroll 3 x 0.5g | G73: -2426 | I73: THC oil | J73: 4150 | K73: =VLOOKUP(I73,N:O,2,0) -> -4150 | L73: =IF(ISERROR(K73),J73,J73+K73) -> 0
A74: Licorice Gumball pre-roll 5 x 0.5g | B74: 24 | C74: =VLOOKUP(A74,F:G,2,0) -> #N/A | D74: =IF(ISERROR(C74),B74,B74+C74) -> 24 | F74: November Rain Vape Canadian OG | G74: -120 | I74: THCA Diamond | J74: 2304 | K74: =VLOOKUP(I74,N:O,2,0) -> -746.87 | L74: =IF(ISERROR(K74),J74,J74+K74) -> 1557.13
... A86: November Rain Blaster Multipack 0.5g*12 | B86: 1007 | C86: =VLOOKUP(A86,F:G,2,0) -> -1027 | D86: =IF(ISERROR(C86),B86,B86+C86) -> -20 | F86: Pineapple Sour preroll 1g | G86: -85 | I86: Grand Total | J86: 1163512 | K86: =VLOOKUP(I86,N:O,2,0) -> -975335.28 | L86: =IF(ISERROR(K86),J86,J86+K86) -> 188176.74
A87: November Rain Blueberry preroll 0.5g | B87: 8696 | C87: =VLOOKUP(A87,F:G,2,0) -> -9783 | D87: =IF(ISERROR(C87),B87,B87+C87) -> -1087 | F87: Pot Shot Citrus 151mg | G87: -1366 | K87: =VLOOKUP(I87,N:O,2,0) -> #N/A | L87: =IF(ISERROR(K87),J87,J87+K87) -> 0
A88: November Rain Blueberry preroll 3 x 0.5g | B88: 2869 | C88: =VLOOKUP(A88,F:G,2,0) -> -3406 | D88: =IF(ISERROR(C88),B88,B88+C88) -> -537 | F88: Pot Shot Coconut Lime 151mg | G88: -751 | K88: =VLOOKUP(I88,N:O,2,0) -> #N/A | L88: =IF(ISERROR(K88),J88,J88+K88) -> 0
A89: November Rain Concord Grape vape 0.5g | B89: 967 | C89: =VLOOKUP(A89,F:G,2,0) -> -557 | D89: =IF(ISERROR(C89),B89,B89+C89) -> 410 | F89: Pot Shot Tropical Fruits 151mg | G89: -2406 | K89: =VLOOKUP(I89,N:O,2,0) -> #N/A | L89: =IF(ISERROR(K89),J89,J89+K89) -> 0
A90: November Rain Concord Grape vape 1g | B90: 142 | C90: =VLOOKUP(A90,F:G,2,0) -> -145 | D90: =IF(ISERROR(C90),B90,B90+C90) -> -3 | F90: Pressure Pie dried flower 28g | G90: -156 | K90: =VLOOKUP(I90,N:O,2,0) -> #N/A | L90: =IF(ISERROR(K90),J90,J90+K90) -> 0
A91: November Rain Gastro-pop Diamond Infused 3x0.5g Pre-Rolls | B91: 1567 | C91: =VLOOKUP(A91,F:G,2,0) -> -1010 | D91: =IF(ISERROR(C91),B91,B91+C91) -> 557 | F91: Rogworld Lemonade Octane vape 1g | G91: -630 | K91: =VLOOKUP(I91,N:O,2,0) -> #N/A | L91: =IF(ISERROR(K91),J91,J91+K91) -> 0
A92: November Rain Infused blueberry preroll 3*0.5g | B92: 11 | C92: =VLOOKUP(A92,F:G,2,0) -> #N/A | D92: =IF(ISERROR(C92),B92,B92+C92) -> 11 | F92: Rogworld-Bong Guru Rockstar-14g | G92: -55 | K92: =VLOOKUP(I92,N:O,2,0) -> #N/A | L92: =IF(ISERROR(K92),J92,J92+K92) -> 0
A93: November Rain Lemon Ice Tea preroll 0.5g | B93: 992 | C93: =VLOOKUP(A93,F:G,2,0) -> -992 | D93: =IF(ISERROR(C93),B93,B93+C93) -> 0 | F93: Rogworld-Bong Guru Rockstar-1g pre-roll | G93: -12 | K93: =VLOOKUP(I93,N:O,2,0) -> #N/A | L93: =IF(ISERROR(K93),J93,J93+K93) -> 0
A94: November Rain Lemon Ice Tea preroll 3 x 0.5g | B94: 1529 | C94: =VLOOKUP(A94,F:G,2,0) -> -1152 | D94: =IF(ISERROR(C94),B94,B94+C94) -> 377 | F94: Rogworld-Bong Guru Rockstar-5X0.5g pre-rolls | G94: -396 | K94: =VLOOKUP(I94,N:O,2,0) -> #N/A | L94: =IF(ISERROR(K94),J94,J94+K94) -> 0
A95: November Rain Preroll Rose Mintz 3x0.5g | B95: 168 | C95: =VLOOKUP(A95,F:G,2,0) -> -120 | D95: =IF(ISERROR(C95),B95,B95+C95) -> 48 | F95: Romulan Grape God Bubble Hash 1g | G95: -36 | K95: =VLOOKUP(I95,N:O,2,0) -> #N/A | L95: =IF(ISERROR(K95),J95,J95+K95) -> 0
A96: November Rain Rose preroll 0.5g | B96: 4169 | C96: =VLOOKUP(A96,F:G,2,0) -> -4052 | D96: =IF(ISERROR(C96),B96,B96+C96) -> 117 | F96: Rose Diamond Infused preroll 3x0.5g | G96: -48 | K96: =VLOOKUP(I96,N:O,2,0) -> #N/A | L96: =IF(ISERROR(K96),J96,J96+K96) -> 0
A97: November Rain Rose preroll 3 x 0.5g | B97: 1166 | C97: =VLOOKUP(A97,F:G,2,0) -> -2128 | D97: =IF(ISERROR(C97),B97,B97+C97) -> -962 | F97: Runtz Muffin Crumble (Rohan) | G97: -119 | K97: =VLOOKUP(I97,N:O,2,0) -> #N/A | L97: =IF(ISERROR(K97),J97,J97+K97) -> 0
A98: November Rain Trident preroll 3 x 0.5g | B98: 2235 | C98: =VLOOKUP(A98,F:G,2,0) -> -2426 | D98: =IF(ISERROR(C98),B98,B98+C98) -> -191 | F98: Strawberry preroll 0.5g | G98: -688 | K98: =VLOOKUP(I98,N:O,2,0) -> #N/A | L98: =IF(ISERROR(K98),J98,J98+K98) -> 0
... A110: Phant THCA diamonds 1g | B110: 99 | C110: =VLOOKUP(A110,F:G,2,0) -> #N/A | D110: =IF(ISERROR(C110),B110,B110+C110) -> 99 | F110: Grand Total | G110: -92455 | K110: =VLOOKUP(I110,N:O,2,0) -> #N/A | L110: =IF(ISERROR(K110),J110,J110+K110) -> 0
A111: Pineapple blaster preroll 0.5g | B111: 197 | C111: =VLOOKUP(A111,F:G,2,0) -> -129 | D111: =IF(ISERROR(C111),B111,B111+C111) -> 68 | K111: =VLOOKUP(I111,N:O,2,0) -> #N/A | L111: =IF(ISERROR(K111),J111,J111+K111) -> 0
A112: Pineapple Sour dired flower 28g | B112: 36 | C112: =VLOOKUP(A112,F:G,2,0) -> -36 | D112: =IF(ISERROR(C112),B112,B112+C112) -> 0 | K112: =VLOOKUP(I112,N:O,2,0) -> #N/A | L112: =IF(ISERROR(K112),J112,J112+K112) -> 0
A113: Pineapple Sour preroll 1g | B113: 85 | C113: =VLOOKUP(A113,F:G,2,0) -> -85 | D113: =IF(ISERROR(C113),B113,B113+C113) -> 0 | K113: =VLOOKUP(I113,N:O,2,0) -> #N/A | L113: =IF(ISERROR(K113),J113,J113+K113) -> 0
A114: Platinum Cookies dried flower 3.5g | B114: 37 | C114: =VLOOKUP(A114,F:G,2,0) -> #N/A | D114: =IF(ISERROR(C114),B114,B114+C114) -> 37 | K114: =VLOOKUP(I114,N:O,2,0) -> #N/A | L114: =IF(ISERROR(K114),J114,J114+K114) -> 0
A115: Pot Shot Citrus 151mg | B115: 764 | C115: =VLOOKUP(A115,F:G,2,0) -> -1366 | D115: =IF(ISERROR(C115),B115,B115+C115) -> -602 | K115: =VLOOKUP(I115,N:O,2,0) -> #N/A | L115: =IF(ISERROR(K115),J115,J115+K115) -> 0
A116: Pot Shot Coconut Lime 151mg | B116: 1706 | C116: =VLOOKUP(A116,F:G,2,0) -> -751 | D116: =IF(ISERROR(C116),B116,B116+C116) -> 955 | K116: =VLOOKUP(I116,N:O,2,0) -> #N/A | L116: =IF(ISERROR(K116),J116,J116+K116) -> 0
A117: Pot Shot Tropical Fruits 151mg | B117: 1857 | C117: =VLOOKUP(A117,F:G,2,0) -> -2406 | D117: =IF(ISERROR(C117),B117,B117+C117) -> -549 | K117: =VLOOKUP(I117,N:O,2,0) -> #N/A | L117: =IF(ISERROR(K117),J117,J117+K117) -> 0
A118: Pressure Pie dried flower 28g | B118: 156 | C118: =VLOOKUP(A118,F:G,2,0) -> -156 | D118: =IF(ISERROR(C118),B118,B118+C118) -> 0 | K118: =VLOOKUP(I118,N:O,2,0) -> #N/A | L118: =IF(ISERROR(K118),J118,J118+K118) -> 0
A119: Rogworld Lemonade Octane vape 1g | B119: 562 | C119: =VLOOKUP(A119,F:G,2,0) -> -630 | D119: =IF(ISERROR(C119),B119,B119+C119) -> -68 | K119: =VLOOKUP(I119,N:O,2,0) -> #N/A | L119: =IF(ISERROR(K119),J119,J119+K119) -> 0
A120: Rogworld-Bong Guru Rockstar-14g | B120: 55 | C120: =VLOOKUP(A120,F:G,2,0) -> -55 | D120: =IF(ISERROR(C120),B120,B120+C120) -> 0 | K120: =VLOOKUP(I120,N:O,2,0) -> #N/A | L120: =IF(ISERROR(K120),J120,J120+K120) -> 0
A121: Rogworld-Bong Guru Rockstar-1g pre-roll | B121: 36 | C121: =VLOOKUP(A121,F:G,2,0) -> -12 | D121: =IF(ISERROR(C121),B121,B121+C121) -> 24 | K121: =VLOOKUP(I121,N:O,2,0) -> #N/A | L121: =IF(ISERROR(K121),J121,J121+K121) -> 0
A122: Rogworld-Bong Guru Rockstar-5X0.5g pre-rolls | B122: 275 | C122: =VLOOKUP(A122,F:G,2,0) -> -396 | D122: =IF(ISERROR(C122),B122,B122+C122) -> -121 | K122: =VLOOKUP(I122,N:O,2,0) -> #N/A | L122: =IF(ISERROR(K122),J122,J122+K122) -> 0
... A152: Grand Total | B152: 100218 | C152: =VLOOKUP(A152,F:G,2,0) -> -92455 | D152: =IF(ISERROR(C152),B152,B152+C152) -> 7763 | K152: =VLOOKUP(I152,N:O,2,0) -> #N/A | L152: =IF(ISERROR(K152),J152,J152+K152) -> 0
C153: =VLOOKUP(A153,F:G,2,0) -> #N/A | D153: =IF(ISERROR(C153),B153,B153+C153) -> 0 | K153: =VLOOKUP(I153,N:O,2,0) -> #N/A | L153: =IF(ISERROR(K153),J153,J153+K153) -> 0
C154: =VLOOKUP(A154,F:G,2,0) -> #N/A | D154: =IF(ISERROR(C154),B154,B154+C154) -> 0 | K154: =VLOOKUP(I154,N:O,2,0) -> #N/A | L154: =IF(ISERROR(K154),J154,J154+K154) -> 0
C155: =VLOOKUP(A155,F:G,2,0) -> #N/A | D155: =IF(ISERROR(C155),B155,B155+C155) -> 0 | K155: =VLOOKUP(I155,N:O,2,0) -> #N/A | L155: =IF(ISERROR(K155),J155,J155+K155) -> 0
C156: =VLOOKUP(A156,F:G,2,0) -> #N/A | D156: =IF(ISERROR(C156),B156,B156+C156) -> 0 | K156: =VLOOKUP(I156,N:O,2,0) -> #N/A | L156: =IF(ISERROR(K156),J156,J156+K156) -> 0
C157: =VLOOKUP(A157,F:G,2,0) -> #N/A | D157: =IF(ISERROR(C157),B157,B157+C157) -> 0 | K157: =VLOOKUP(I157,N:O,2,0) -> #N/A | L157: =IF(ISERROR(K157),J157,J157+K157) -> 0
C158: =VLOOKUP(A158,F:G,2,0) -> #N/A | D158: =IF(ISERROR(C158),B158,B158+C158) -> 0 | K158: =VLOOKUP(I158,N:O,2,0) -> #N/A | L158: =IF(ISERROR(K158),J158,J158+K158) -> 0
C159: =VLOOKUP(A159,F:G,2,0) -> #N/A | D159: =IF(ISERROR(C159),B159,B159+C159) -> 0 | K159: =VLOOKUP(I159,N:O,2,0) -> #N/A | L159: =IF(ISERROR(K159),J159,J159+K159) -> 0
C160: =VLOOKUP(A160,F:G,2,0) -> #N/A | D160: =IF(ISERROR(C160),B160,B160+C160) -> 0 | K160: =VLOOKUP(I160,N:O,2,0) -> #N/A | L160: =IF(ISERROR(K160),J160,J160+K160) -> 0
C161: =VLOOKUP(A161,F:G,2,0) -> #N/A | D161: =IF(ISERROR(C161),B161,B161+C161) -> 0 | K161: =VLOOKUP(I161,N:O,2,0) -> #N/A | L161: =IF(ISERROR(K161),J161,J161+K161) -> 0
C162: =VLOOKUP(A162,F:G,2,0) -> #N/A | D162: =IF(ISERROR(C162),B162,B162+C162) -> 0 | K162: =VLOOKUP(I162,N:O,2,0) -> #N/A | L162: =IF(ISERROR(K162),J162,J162+K162) -> 0
C163: =VLOOKUP(A163,F:G,2,0) -> #N/A | D163: =IF(ISERROR(C163),B163,B163+C163) -> 0 | K163: =VLOOKUP(I163,N:O,2,0) -> #N/A | L163: =IF(ISERROR(K163),J163,J163+K163) -> 0
C164: =VLOOKUP(A164,F:G,2,0) -> #N/A | D164: =IF(ISERROR(C164),B164,B164+C164) -> 0 | K164: =VLOOKUP(I164,N:O,2,0) -> #N/A | L164: =IF(ISERROR(K164),J164,J164+K164) -> 0
... C222: =VLOOKUP(A222,F:G,2,0) -> #N/A | D222: =IF(ISERROR(C222),B222,B222+C222) -> 0 | K222: =VLOOKUP(I222,N:O,2,0) -> #N/A | L222: =IF(ISERROR(K222),J222,J222+K222) -> 0

Sheet cannabis_log
A1: inventory_id_head | B1: inventory_id_tail | C1: inventory_id | D1: status | E1: tote_number | F1: bag_number | G1: location | H1: stage | I1: product_description | J1: lot_number | K1: pack_on_date | L1: number_of_unit | M1: unit | N1: net_weight_per_unit | O1: gross_weight | P1: tare_weight | Q1: quantity_gram | R1: note | S1: time | T1: calculation_method | U1: product_description_stage | V1: internal_cansku
A2: 576 | B2: 0 | C2: =Table1[[#This Row],[inventory_id_head]]&"-"&Table1[[#This Row],[inventory_id_tail]] -> 576-0 | D2: Active | E2: T118EX | F2: NA | G2: =E2&F2 -> T118EXNA | H2: extract_inhaled_packaged | J2: EX24111301G05 | K2: 45642 | L2: 626 | M2: unit | N2: 0.5 | O2: 0 | P2: 0 | Q2: =L2*N2 -> 313 | S2: 45293.572 | T2: net | U2: =I2&"_"&H2 -> _extract_inhaled_packaged | V2: =IF(U2="_","",_xlfn.XLOOKUP(U2,internal_cansku_inventory!D:D,internal_cansku_inventory!E:E,"",0,1))
A3: 577 | B3: 0 | C3: =Table1[[#This Row],[inventory_id_head]]&"-"&Table1[[#This Row],[inventory_id_tail]] -> 577-0 | D3: Active | E3: T013TP | F3: NA | G3: =E3&F3 -> T013TPNA | H3: topical_labelled | J3: TP24120401G45 | K3: 45638 | L3: 300 | M3: unit | N3: 45 | O3: 0 | P3: 0 | Q3: =L3*N3 -> 13500 | S3: 45293.572 | T3: net | U3: =I3&"_"&H3 -> _topical_labelled | V3: =IF(U3="_","",_xlfn.XLOOKUP(U3,internal_cansku_inventory!D:D,internal_cansku_inventory!E:E,"",0,1))
A4: 578 | B4: 0 | C4: =Table1[[#This Row],[inventory_id_head]]&"-"&Table1[[#This Row],[inventory_id_tail]] -> 578-0 | D4: Active | E4: T014TP | F4: NA | G4: =E4&F4 -> T014TPNA | H4: topical_labelled | J4: TP24120401G45 | K4: 45638 | L4: 300 | M4: unit | N4: 45 | O4: 0 | P4: 0 | Q4: =L4*N4 -> 13500 | S4: 45293.572 | T4: net | U4: =I4&"_"&H4 -> _topical_labelled | V4: =IF(U4="_","",_xlfn.XLOOKUP(U4,internal_cansku_inventory!D:D,internal_cansku_inventory!E:E,"",0,1))
A5: 579 | B5: 0 | C5: =Table1[[#This Row],[inventory_id_head]]&"-"&Table1[[#This Row],[inventory_id_tail]] -> 579-0 | D5: Active | E5: P012TP | F5: NA | G5: =E5&F5 -> P012TPNA | H5: topical_bulk | J5: TP24120401 | K5: NA | L5: 1 | M5: pail | N5: =Table1[[#This Row],[gross_weight]]-Table1[[#This Row],[tare_weight]] -> 23062 | O5: 24830 | P5: =24830-23062 -> 1768 | Q5: =L5*N5 -> 23062 | S5: 45293.572 | T5: gross | U5: =I5&"_"&H5 -> _topical_bulk | V5: =IF(U5="_","",_xlfn.XLOOKUP(U5,internal_cansku_inventory!D:D,internal_cansku_inventory!E:E,"",0,1))
A6: 580 | B6: 0 | C6: =Table1[[#This Row],[inventory_id_head]]&"-"&Table1[[#This Row],[inventory_id_tail]] -> 580-0 | D6: Active | E6: P013TP | F6: NA | G6: =E6&F6 -> P013TPNA | H6: topical_bulk | J6: TP24120401 | K6: NA | L6: 1 | M6: pail | N6: =Table1[[#This Row],[gross_weight]]-Table1[[#This Row],[tare_weight]] -> 5192 | O6: 7130 | P6: =7130-5192 -> 1938 | Q6: =L6*N6 -> 5192 | S6: 45293.572 | T6: gross | U6: =I6&"_"&H6 -> _topical_bulk | V6: =IF(U6="_","",_xlfn.XLOOKUP(U6,internal_cansku_inventory!D:D,internal_cansku_inventory!E:E,"",0,1))
A7: 581 | B7: 0 | C7: =Table1[[#This Row],[inventory_id_head]]&"-"&Table1[[#This Row],[inventory_id_tail]] -> 581-0 | D7: Active | E7: P014TP | F7: NA | G7: =E7&F7 -> P014TPNA | H7: topical_bulk | J7: TP24120401 | K7: NA | L7: 1 | M7: pail | N7: =Table1[[#This Row],[gross_weight]]-Table1[[#This Row],[tare_weight]] -> 22994 | O7: 24750 | P7: =24750-22994 -> 1756 | Q7: =L7*N7 -> 22994 | S7: 45293.572 | T7: gross | U7: =I7&"_"&H7 -> _topical_bulk | V7: =IF(U7="_","",_xlfn.XLOOKUP(U7,internal_cansku_inventory!D:D,internal_cansku_inventory!E:E,"",0,1))
A8: 582 | B8: 0 | C8: =Table1[[#This Row],[inventory_id_head]]&"-"&Table1[[#This Row],[inventory_id_tail]] -> 582-0 | D8: Active | E8: P015TP | F8: NA | G8: =E8&F8 -> P015TPNA | H8: topical_bulk | J8: TP24120401 | K8: NA | L8: 1 | M8: pail | N8: =Table1[[#This Row],[gross_weight]]-Table1[[#This Row],[tare_weight]] -> 1756 | O8: 26400 | P8: 24644 | Q8: =L8*N8 -> 1756 | S8: 45293.572 | T8: gross | U8: =I8&"_"&H8 -> _topical_bulk | V8: =IF(U8="_","",_xlfn.XLOOKUP(U8,internal_cansku_inventory!D:D,internal_cansku_inventory!E:E,"",0,1))
A9: 583 | B9: 0 | C9: =Table1[[#This Row],[inventory_id_head]]&"-"&Table1[[#This Row],[inventory_id_tail]] -> 583-0 | D9: Active | E9: P016TP | F9: NA | G9: =E9&F9 -> P016TPNA | H9: topical_bulk | J9: TP24120401 | K9: NA | L9: 1 | M9: pail | N9: =Table1[[#This Row],[gross_weight]]-Table1[[#This Row],[tare_weight]] -> 1754 | O9: 26055 | P9: 24301 | Q9: =L9*N9 -> 1754 | S9: 45293.572 | T9: gross | U9: =I9&"_"&H9 -> _topical_bulk | V9: =IF(U9="_","",_xlfn.XLOOKUP(U9,internal_cansku_inventory!D:D,internal_cansku_inventory!E:E,"",0,1))
A10: 585 | B10: 0 | C10: =Table1[[#This Row],[inventory_id_head]]&"-"&Table1[[#This Row],[inventory_id_tail]] -> 585-0 | D10: Active | E10: T015TP | F10: NA | G10: =E10&F10 -> T015TPNA | H10: topical_labelled | J10: TP24120401G45 | K10: 45638 | L10: 300 | M10: unit | N10: 45 | O10: 0 | P10: 0 | Q10: =L10*N10 -> 13500 | S10: 45293.665 | T10: net | U10: =I10&"_"&H10 -> _topical_labelled | V10: =IF(U10="_","",_xlfn.XLOOKUP(U10,internal_cansku_inventory!D:D,internal_cansku_inventory!E:E,"",0,1))
A11: 586 | B11: 0 | C11: =Table1[[#This Row],[inventory_id_head]]&"-"&Table1[[#This Row],[inventory_id_tail]] -> 586-0 | D11: Active | E11: T016TP | F11: NA | G11: =E11&F11 -> T016TPNA | H11: topical_labelled | J11: TP24120401G45 | K11: 45638 | L11: 138 | M11: unit | N11: 45 | O11: 0 | P11: 0 | Q11: =L11*N11 -> 6210 | S11: 45293.665 | T11: net | U11: =I11&"_"&H11 -> _topical_labelled | V11: =IF(U11="_","",_xlfn.XLOOKUP(U11,internal_cansku_inventory!D:D,internal_cansku_inventory!E:E,"",0,1))
A12: 587 | B12: 0 | C12: =Table1[[#This Row],[inventory_id_head]]&"-"&Table1[[#This Row],[inventory_id_tail]] -> 587-0 | D12: Active | E12: B001DF | F12: NA | G12: =E12&F12 -> B001DFNA | H12: driedflower_bulk_BURB | J12: 2025010201 | K12: NA | L12: 1 | M12: bag | N12: =Table1[[#This Row],[gross_weight]]-Table1[[#This Row],[tare_weight]] -> 4360 | O12: 4670 | P12: =4670-4360 -> 310 | Q12: =L12*N12 -> 4360 | R12: high potency_14g central | S12: 45293.665 | T12: gross | U12: =I12&"_"&H12 -> _driedflower_bulk_BURB | V12: =IF(U12="_","",_xlfn.XLOOKUP(U12,internal_cansku_inventory!D:D,internal_cansku_inventory!E:E,"",0,1))
A13: 588 | B13: 0 | C13: =Table1[[#This Row],[inventory_id_head]]&"-"&Table1[[#This Row],[inventory_id_tail]] -> 588-0 | D13: Active | E13: B002DF | F13: NA | G13: =E13&F13 -> B002DFNA | H13: driedflower_bulk_BURB | J13: 2025010201 | K13: NA | L13: 1 | M13: bag | N13: =Table1[[#This Row],[gross_weight]]-Table1[[#This Row],[tare_weight]] -> 4360 | O13: 4670 | P13: =4670-4360 -> 310 | Q13: =L13*N13 -> 4360 | R13: high potency_14g central | S13: 45293.665 | T13: gross | U13: =I13&"_"&H13 -> _driedflower_bulk_BURB | V13: =IF(U13="_","",_xlfn.XLOOKUP(U13,internal_cansku_inventory!D:D,internal_cansku_inventory!E:E,"",0,1))
A14: 589 | B14: 0 | C14: =Table1[[#This Row],[inventory_id_head]]&"-"&Table1[[#This Row],[inventory_id_tail]] -> 589-0 | D14: Active | E14: B003DF | F14: NA | G14: =E14&F14 -> B003DFNA | H14: driedflower_bulk_BURB | J14: 2025010201 | K14: NA | L14: 1 | M14: bag | N14: 4360 | O14: 4665 | P14: 305 | Q14: =L14*N14 -> 4360 | R14: high potency_14g central | S14: 45293.665 | T14: gross | U14: =I14&"_"&H14 -> _driedflower_bulk_BURB | V14: =IF(U14="_","",_xlfn.XLOOKUP(U14,internal_cansku_inventory!D:D,internal_cansku_inventory!E:E,"",0,1))
A15: 590 | B15: 0 | C15: =Table1[[#This Row],[inventory_id_head]]&"-"&Table1[[#This Row],[inventory_id_tail]] -> 590-0 | D15: Active | E15: B004DF | F15: NA | G15: =E15&F15 -> B004DFNA | H15: driedflower_bulk_BURB | J15: 2025010201 | K15: NA | L15: 1 | M15: bag | N15: =Table1[[#This Row],[gross_weight]]-Table1[[#This Row],[tare_weight]] -> 4360 | O15: 4665 | P15: 305 | Q15: =L15*N15 -> 4360 | R15: high potency_14g central | S15: 45293.665 | T15: gross | U15: =I15&"_"&H15 -> _driedflower_bulk_BURB | V15: =IF(U15="_","",_xlfn.XLOOKUP(U15,internal_cansku_inventory!D:D,internal_cansku_inventory!E:E,"",0,1))
A16: 591 | B16: 0 | C16: =Table1[[#This Row],[inventory_id_head]]&"-"&Table1[[#This Row],[inventory_id_tail]] -> 591-0 | D16: Active | E16: B005DF | F16: NA | G16: =E16&F16 -> B005DFNA | H16: driedflower_bulk_BURB | J16: 2025010201 | K16: NA | L16: 1 | M16: bag | N16: =Table1[[#This Row],[gross_weight]]-Table1[[#This Row],[tare_weight]] -> 4360 | O16: 4670 | P16: =4670-4360 -> 310 | Q16: =L16*N16 -> 4360 | R16: high potency_14g central_small flower | S16: 45293.665 | T16: gross | U16: =I16&"_"&H16 -> _driedflower_bulk_BURB | V16: =IF(U16="_","",_xlfn.XLOOKUP(U16,internal_cansku_inventory!D:D,internal_cansku_inventory!E:E,"",0,1))
A17: 440 | B17: 0 | C17: =Table1[[#This Row],[inventory_id_head]]&"-"&Table1[[#This Row],[inventory_id_tail]] -> 440-0 | D17: Closed | E17: NA | F17: NA | G17: OFDMB | H17: extract_ingested_cased_MB | J17: EX24022302V30 | K17: 45588 | L17: 8 | M17: case | N17: =29.3*12 -> 351.6 | O17: 0 | P17: 0 | Q17: =L17*N17 -> 2812.8 | S17: 45297.408 | T17: net | U17: =I17&"_"&H17 -> _extract_ingested_cased_MB | V17: =IF(U17="_","",_xlfn.XLOOKUP(U17,internal_cansku_inventory!D:D,internal_cansku_inventory!E:E,"",0,1))
A18: 3 | B18: 0 | C18: =Table1[[#This Row],[inventory_id_head]]&"-"&Table1[[#This Row],[inventory_id_tail]] -> 3-0 | D18: Active | E18: T001ED | F18: NA | G18: =E18&F18 -> T001EDNA | H18: extract_inhaled_packaged | J18: PE2205CP085D | K18: NA | L18: 99 | M18: jar | N18: 1 | O18: 0 | P18: 0 | Q18: =L18*N18 -> 99 | R18: Unlabelled | S18: 45484 | T18: net | U18: =I18&"_"&H18 -> _extract_inhaled_packaged | V18: =IF(U18="_","",_xlfn.XLOOKUP(U18,internal_cansku_inventory!D:D,internal_cansku_inventory!E:E,"",0,1))
A19: 5 | B19: 0 | C19: =Table1[[#This Row],[inventory_id_head]]&"-"&Table1[[#This Row],[inventory_id_tail]] -> 5-0 | D19: Active | E19: T001DF | F19: NA | G19: =E19&F19 -> T001DFNA | H19: driedflower_packaged | J19: 211007 | K19: 44495 | L19: 66 | M19: jar | N19: 3.5 | O19: 0 | P19: 0 | Q19: =L19*N19 -> 231 | S19: 45484 | T19: net | U19: =I19&"_"&H19 -> _driedflower_packaged | V19: =IF(U19="_","",_xlfn.XLOOKUP(U19,internal_cansku_inventory!D:D,internal_cansku_inventory!E:E,"",0,1))
A20: 6 | B20: 0 | C20: =Table1[[#This Row],[inventory_id_head]]&"-"&Table1[[#This Row],[inventory_id_tail]] -> 6-0 | D20: Active | E20: T002DF | F20: NA | G20: =E20&F20 -> T002DFNA | H20: driedflower_packaged | J20: 2022042902 | K20: NA | L20: 156 | M20: jar | N20: 3.5 | O20: 0 | P20: 0 | Q20: =L20*N20 -> 546 | R20: Unlabelled | S20: 45484 | T20: net | U20: =I20&"_"&H20 -> _driedflower_packaged | V20: =IF(U20="_","",_xlfn.XLOOKUP(U20,internal_cansku_inventory!D:D,internal_cansku_inventory!E:E,"",0,1))
A21: 7 | B21: 0 | C21: =Table1[[#This Row],[inventory_id_head]]&"-"&Table1[[#This Row],[inventory_id_tail]] -> 7-0 | D21: Active | E21: T003DF | F21: NA | G21: =E21&F21 -> T003DFNA | H21: driedflower_packaged | J21: 2022042902 | K21: NA | L21: 319 | M21: jar | N21: 3.5 | O21: 0 | P21: 0 | Q21: =L21*N21 -> 1116.5 | R21: Unlabelled | S21: 45484 | T21: net | U21: =I21&"_"&H21 -> _driedflower_packaged | V21: =IF(U21="_","",_xlfn.XLOOKUP(U21,internal_cansku_inventory!D:D,internal_cansku_inventory!E:E,"",0,1))
A22: 8 | B22: 0 | C22: =Table1[[#This Row],[inventory_id_head]]&"-"&Table1[[#This Row],[inventory_id_tail]] -> 8-0 | D22: Active | E22: T004DF | F22: NA | G22: =E22&F22 -> T004DFNA | H22: driedflower_packaged | J22: 2022012401R1 | K22: 45100 | L22: 82 | M22: pouch | N22: 14 | O22: 0 | P22: 0 | Q22: =L22*N22 -> 1148 | S22: 45484 | T22: net | U22: =I22&"_"&H22 -> _driedflower_packaged | V22: =IF(U22="_","",_xlfn.XLOOKUP(U22,internal_cansku_inventory!D:D,internal_cansku_inventory!E:E,"",0,1))
A23: 9 | B23: 0 | C23: =Table1[[#This Row],[inventory_id_head]]&"-"&Table1[[#This Row],[inventory_id_tail]] -> 9-0 | D23: Active | E23: T001MF | F23: NA | G23: =E23&F23 -> T001MFNA | H23: driedflower_milled_labelled | J23: CPR22112801G14 | K23: 44941 | L23: 404 | M23: pouch | N23: 14 | O23: 0 | P23: 0 | Q23: =L23*N23 -> 5656 | R23: AB stamped | S23: 45484 | T23: net | U23: =I23&"_"&H23 -> _driedflower_milled_labelled | V23: =IF(U23="_","",_xlfn.XLOOKUP(U23,internal_cansku_inventory!D:D,internal_cansku_inventory!E:E,"",0,1))
A24: 10 | B24: 0 | C24: =Table1[[#This Row],[inventory_id_head]]&"-"&Table1[[#This Row],[inventory_id_tail]] -> 10-0 | D24: Active | E24: T002MF | F24: NA | G24: =E24&F24 -> T002MFNA | H24: driedflower_milled_labelled | J24: CPR22112801G7 | K24: 44941 | L24: 106 | M24: pouch | N24: 7 | O24: 0 | P24: 0 | Q24: =L24*N24 -> 742 | S24: 45484 | T24: net | U24: =I24&"_"&H24 -> _driedflower_milled_labelled | V24: =IF(U24="_","",_xlfn.XLOOKUP(U24,internal_cansku_inventory!D:D,internal_cansku_inventory!E:E,"",0,1))
A25: 12 | B25: 0 | C25: =Table1[[#This Row],[inventory_id_head]]&"-"&Table1[[#This Row],[inventory_id_tail]] -> 12-0 | D25: Active | E25: T003MF | F25: B001MF | G25: =E25&F25 -> T003MFB001MF | H25: driedflower_milled_bulk | J25: PR2303IN | K25: 45253 | L25: 1 | M25: bag | N25: 41.02 | O25: 0 | P25: 0 | Q25: =L25*N25 -> 41.02 | S25: 45484 | T25: gross | U25: =I25&"_"&H25 -> _driedflower_milled_bulk | V25: =IF(U25="_","",_xlfn.XLOOKUP(U25,internal_cansku_inventory!D:D,internal_cansku_inventory!E:E,"",0,1))
A26: 13 | B26: 0 | C26: =Table1[[#This Row],[inventory_id_head]]&"-"&Table1[[#This Row],[inventory_id_tail]] -> 13-0 | D26: Active | E26: T003MF | F26: B002MF | G26: =E26&F26 -> T003MFB002MF | H26: driedflower_milled_bulk | J26: CPR22102101 | K26: NA | L26: 1 | M26: bag | N26: 169.94 | O26: 179.18 | P26: 9.24 | Q26: =L26*N26 -> 169.94 | S26: 45484 | T26: gross | U26: =I26&"_"&H26 -> _driedflower_milled_bulk | V26: =IF(U26="_","",_xlfn.XLOOKUP(U26,internal_cansku_inventory!D:D,internal_cansku_inventory!E:E,"",0,1))
A27: 14 | B27: 0 | C27: =Table1[[#This Row],[inventory_id_head]]&"-"&Table1[[#This Row],[inventory_id_tail]] -> 14-0 | D27: Active | E27: T003MF | F27: B003MF | G27: =E27&F27 -> T003MFB003MF | H27: driedflower_milled_bulk | J27: PR2304F7 | K27: NA | L27: 1 | M27: bag | N27: 72.83 | O27: 88.04 | P27: =O27-N27 -> 15.21 | Q27: =L27*N27 -> 72.83 | S27: 45484 | T27: gross | U27: =I27&"_"&H27 -> _driedflower_milled_bulk | V27: =IF(U27="_","",_xlfn.XLOOKUP(U27,internal_cansku_inventory!D:D,internal_cansku_inventory!E:E,"",0,1))
A28: 15 | B28: 0 | C28: =Table1[[#This Row],[inventory_id_head]]&"-"&Table1[[#This Row],[inventory_id_tail]] -> 15-0 | D28: Active | E28: T003MF | F28: B004MF | G28: =E28&F28 -> T003MFB004MF | H28: driedflower_milled_bulk | J28: NA | K28: NA | L28: 1 | M28: bag | N28: 904.95 | O28: 0 | P28: 0 | Q28: =L28*N28 -> 904.95 | R28: unknown lot | S28: 45484 | T28: gross | U28: =I28&"_"&H28 -> _driedflower_milled_bulk | V28: =IF(U28="_","",_xlfn.XLOOKUP(U28,internal_cansku_inventory!D:D,internal_cansku_inventory!E:E,"",0,1))
A29: 16 | B29: 0 | C29: =Table1[[#This Row],[inventory_id_head]]&"-"&Table1[[#This Row],[inventory_id_tail]] -> 16-0 | D29: Active | E29: T003MF | F29: B005MF | G29: =E29&F29 -> T003MFB005MF | H29: driedflower_milled_bulk | J29: NA | K29: 44902 | L29: 1 | M29: bag | N29: =O29-P29 -> 132.02 | O29: 143.26 | P29: 11.24 | Q29: =L29*N29 -> 132.02 | R29: unknown lot | S29: 45484 | T29: gross | U29: =I29&"_"&H29 -> _driedflower_milled_bulk | V29: =IF(U29="_","",_xlfn.XLOOKUP(U29,internal_cansku_inventory!D:D,internal_cansku_inventory!E:E,"",0,1))
A30: 17 | B30: 0 | C30: =Table1[[#This Row],[inventory_id_head]]&"-"&Table1[[#This Row],[inventory_id_tail]] -> 17-0 | D30: Active | E30: T005DF | F30: B001DF | G30: =E30&F30 -> T005DFB001DF | H30: driedflower_packaged | J30: 2021022501 | K30: 45014 | L30: 37 | M30: bag | N30: 3.5 | O30: 0 | P30: 0 | Q30: =L30*N30 -> 129.5 | S30: 45484 | T30: net | U30: =I30&"_"&H30 -> _driedflower_packaged | V30: =IF(U30="_","",_xlfn.XLOOKUP(U30,internal_cansku_inventory!D:D,internal_cansku_inventory!E:E,"",0,1))
A31: 18 | B31: 0 | C31: =Table1[[#This Row],[inventory_id_head]]&"-"&Table1[[#This Row],[inventory_id_tail]] -> 18-0 | D31: Active | E31: T005DF | F31: B002DF | G31: =E31&F31 -> T005DFB002DF | H31: driedflower_packaged | J31: SS201002CP-006 | K31: 44305 | L31: 27 | M31: bag | N31: 3.5 | O31: 0 | P31: 0 | Q31: =L31*N31 -> 94.5 | S31: 45484 | T31: net | U31: =I31&"_"&H31 -> _driedflower_packaged | V31: =IF(U31="_","",_xlfn.XLOOKUP(U31,internal_cansku_inventory!D:D,internal_cansku_inventory!E:E,"",0,1))
A32: 19 | B32: 0 | C32: =Table1[[#This Row],[inventory_id_head]]&"-"&Table1[[#This Row],[inventory_id_tail]] -> 19-0 | D32: Active | E32: T005DF | F32: B004DF | G32: =E32&F32 -> T005DFB004DF | H32: driedflower_packaged | J32: GS200219 | K32: 44180 | L32: 27 | M32: bag | N32: 3.5 | O32: 0 | P32: 0 | Q32: =L32*N32 -> 94.5 | S32: 45484 | T32: net | U32: =I32&"_"&H32 -> _driedflower_packaged | V32: =IF(U32="_","",_xlfn.XLOOKUP(U32,internal_cansku_inventory!D:D,internal_cansku_inventory!E:E,"",0,1))
A33: 20 | B33: 0 | C33: =Table1[[#This Row],[inventory_id_head]]&"-"&Table1[[#This Row],[inventory_id_tail]] -> 20-0 | D33: Active | E33: T006DF | F33: NA | G33: =E33&F33 -> T006DFNA | H33: driedflower_packaged | J33: 2022091603 | K33: 44842 | L33: 423 | M33: bag | N33: 3.5 | O33: 0 | P33: 0 | Q33: =L33*N33 -> 1480.5 | S33: 45484 | T33: net | U33: =I33&"_"&H33 -> _driedflower_packaged | V33: =IF(U33="_","",_xlfn.XLOOKUP(U33,internal_cansku_inventory!D:D,internal_cansku_inventory!E:E,"",0,1))
A34: 21 | B34: 0 | C34: =Table1[[#This Row],[inventory_id_head]]&"-"&Table1[[#This Row],[inventory_id_tail]] -> 21-0 | D34: Active | E34: T007DF | F34: NA | G34: =E34&F34 -> T007DFNA | H34: driedflower_packaged | J34: 2021031001 | K34: 44946 | L34: 240 | M34: bag | N34: 14 | O34: 0 | P34: 0 | Q34: =L34*N34 -> 3360 | R34: several MB stamped pouches | S34: 45484 | T34: net | U34: =I34&"_"&H34 -> _driedflower_packaged | V34: =IF(U34="_","",_xlfn.XLOOKUP(U34,internal_cansku_inventory!D:D,internal_cansku_inventory!E:E,"",0,1))
A35: 22 | B35: 0 | C35: =Table1[[#This Row],[inventory_id_head]]&"-"&Table1[[#This Row],[inventory_id_tail]] -> 22-0 | D35: Active | E35: T009DF | F35: B005DF | G35: =E35&F35 -> T009DFB005DF | H35: driedflower_bulk | J35: 2022051601 | K35: 44830 | L35: 1 | M35: bag | N35: 477.4 | O35: 502.4 | P35: 25 | Q35: =L35*N35 -> 477.4 | S35: 45484 | T35: gross | U35: =I35&"_"&H35 -> _driedflower_bulk | V35: =IF(U35="_","",_xlfn.XLOOKUP(U35,internal_cansku_inventory!D:D,internal_cansku_inventory!E:E,"",0,1))
A36: 24 | B36: 0 | C36: =Table1[[#This Row],[inventory_id_head]]&"-"&Table1[[#This Row],[inventory_id_tail]] -> 24-0 | D36: Active | E36: T008DF | F36: B007DF | G36: =E36&F36 -> T008DFB007DF | H36: driedflower_bulk | J36: 2022012401R1 | K36: 45079 | L36: 1 | M36: bag | N36: =O36-P36 -> 446.6 | O36: 471.6 | P36: 25 | Q36: =L36*N36 -> 446.6 | S36: 45484 | T36: gross | U36: =I36&"_"&H36 -> _driedflower_bulk | V36: =IF(U36="_","",_xlfn.XLOOKUP(U36,internal_cansku_inventory!D:D,internal_cansku_inventory!E:E,"",0,1))
A37: 25 | B37: 0 | C37: =Table1[[#This Row],[inventory_id_head]]&"-"&Table1[[#This Row],[inventory_id_tail]] -> 25-0 | D37: Active | E37: T008DF | F37: B008DF | G37: =E37&F37 -> T008DFB008DF | H37: driedflower_bulk | J37: 2022012401R1 | K37: 45079 | L37: 1 | M37: bag | N37: 916 | O37: 1007.2 | P37: =O37-N37 -> 91.2 | Q37: =L37*N37 -> 916 | R37: small buds | S37: 45484 | T37: gross | U37: =I37&"_"&H37 -> _driedflower_bulk | V37: =IF(U37="_","",_xlfn.XLOOKUP(U37,internal_cansku_inventory!D:D,internal_cansku_inventory!E:E,"",0,1))
A38: 26 | B38: 0 | C38: =Table1[[#This Row],[inventory_id_head]]&"-"&Table1[[#This Row],[inventory_id_tail]] -> 26-0 | D38: Closed | E38: T008DF | F38: B009DF | G38: =E38&F38 -> T008DFB009DF | H38: driedflower_bulk | J38: 2022012401R1 | K38: 44686 | L38: 1 | M38: bag | N38: 1000 | O38: 1025.7 | P38: =O38-N38 -> 25.7 | Q38: =L38*N38 -> 1000 | S38: 45484 | T38: gross | U38: =I38&"_"&H38 -> _driedflower_bulk | V38: =IF(U38="_","",_xlfn.XLOOKUP(U38,internal_cansku_inventory!D:D,internal_cansku_inventory!E:E,"",0,1))
A39: 27 | B39: 0 | C39: =Table1[[#This Row],[inventory_id_head]]&"-"&Table1[[#This Row],[inventory_id_tail]] -> 27-0 | D39: Closed | E39: T008DF | F39: B013DF | G39: =E39&F39 -> T008DFB013DF | H39: driedflower_bulk | J39: 2022012401R1 | K39: 44686 | L39: 1 | M39: bag | N39: 1000 | O39: 1026.3 | P39: =O39-N39 -> 26.3 | Q39: =L39*N39 -> 1000 | S39: 45484 | T39: gross | U39: =I39&"_"&H39 -> _driedflower_bulk | V39: =IF(U39="_","",_xlfn.XLOOKUP(U39,internal_cansku_inventory!D:D,internal_cansku_inventory!E:E,"",0,1))
A40: 28 | B40: 0 | C40: =Table1[[#This Row],[inventory_id_head]]&"-"&Table1[[#This Row],[inventory_id_tail]] -> 28-0 | D40: Closed | E40: T008DF | F40: B010DF | G40: =E40&F40 -> T008DFB010DF | H40: driedflower_bulk | J40: 2022012401R1 | K40: 44686 | L40: 1 | M40: bag | N40: 1000 | O40: 1020.7 | P40: =O40-N40 -> 20.7 | Q40: =L40*N40 -> 1000 | S40: 45484 | T40: gross | U40: =I40&"_"&H40 -> _driedflower_bulk | V40: =IF(U40="_","",_xlfn.XLOOKUP(U40,internal_cansku_inventory!D:D,internal_cansku_inventory!E:E,"",0,1))
A41: 29 | B41: 0 | C41: =Table1[[#This Row],[inventory_id_head]]&"-"&Table1[[#This Row],[inventory_id_tail]] -> 29-0 | D41: Closed | E41: T008DF | F41: B012DF | G41: =E41&F41 -> T008DFB012DF | H41: driedflower_bulk | J41: 2022012401R1 | K41: 44686 | L41: 1 | M41: bag | N41: 1000 | O41: 1020.4 | P41: =O41-N41 -> 20.4 | Q41: =L41*N41 -> 1000 | S41: 45484 | T41: gross | U41: =I41&"_"&H41 -> _driedflower_bulk | V41: =IF(U41="_","",_xlfn.XLOOKUP(U41,internal_cansku_inventory!D:D,internal_cansku_inventory!E:E,"",0,1))
A42: 30 | B42: 0 | C42: =Table1[[#This Row],[inventory_id_head]]&"-"&Table1[[#This Row],[inventory_id_tail]] -> 30-0 | D42: Closed | E42: T008DF | F42: B011DF | G42: =E42&F42 -> T008DFB011DF | H42: driedflower_bulk | J42: 2022012401R1 | K42: 44686 | L42: 1 | M42: bag | N42: 1000 | O42: 1026.1 | P42: =O42-N42 -> 26.1 | Q42: =L42*N42 -> 1000 | S42: 45484 | T42: gross | U42: =I42&"_"&H42 -> _driedflower_bulk | V42: =IF(U42="_","",_xlfn.XLOOKUP(U42,internal_cansku_inventory!D:D,internal_cansku_inventory!E:E,"",0,1))
A43: 31 | B43: 0 | C43: =Table1[[#This Row],[inventory_id_head]]&"-"&Table1[[#This Row],[inventory_id_tail]] -> 31-0 | D43: Active | E43: T008DF | F43: B016DF | G43: =E43&F43 -> T008DFB016DF | H43: driedflower_bulk | J43: 2022012401R1 | K43: 44686 | L43: 1 | M43: bag | N43: 1000 | O43: 1024 | P43: =O43-N43 -> 24 | Q43: =L43*N43 -> 1000 | S43: 45484 | T43: gross | U43: =I43&"_"&H43 -> _driedflower_bulk | V43: =IF(U43="_","",_xlfn.XLOOKUP(U43,internal_cansku_inventory!D:D,internal_cansku_inventory!E:E,"",0,1))
A44: 32 | B44: 0 | C44: =Table1[[#This Row],[inventory_id_head]]&"-"&Table1[[#This Row],[inventory_id_tail]] -> 32-0 | D44: Active | E44: T008DF | F44: B015DF | G44: =E44&F44 -> T008DFB015DF | H44: driedflower_bulk | J44: 2022012401R1 | K44: 44686 | L44: 1 | M44: bag | N44: 1000 | O44: 1021.2 | P44: =O44-N44 -> 21.2 | Q44: =L44*N44 -> 1000 | S44: 45484 | T44: gross | U44: =I44&"_"&H44 -> _driedflower_bulk | V44: =IF(U44="_","",_xlfn.XLOOKUP(U44,internal_cansku_inventory!D:D,internal_cansku_inventory!E:E,"",0,1))
A45: 33 | B45: 0 | C45: =Table1[[#This Row],[inventory_id_head]]&"-"&Table1[[#This Row],[inventory_id_tail]] -> 33-0 | D45: Active | E45: T008DF | F45: B014DF | G45: =E45&F45 -> T008DFB014DF | H45: driedflower_bulk | J45: 2022012401R1 | K45: 44686 | L45: 1 | M45: bag | N45: 1000 | O45: 1027.6 | P45: =O45-N45 -> 27.6 | Q45: =L45*N45 -> 1000 | S45: 45484 | T45: gross | U45: =I45&"_"&H45 -> _driedflower_bulk | V45: =IF(U45="_","",_xlfn.XLOOKUP(U45,internal_cansku_inventory!D:D,internal_cansku_inventory!E:E,"",0,1))
A46: 34 | B46: 0 | C46: =Table1[[#This Row],[inventory_id_head]]&"-"&Table1[[#This Row],[inventory_id_tail]] -> 34-0 | D46: Active | E46: T008DF | F46: B018DF | G46: =E46&F46 -> T008DFB018DF | H46: driedflower_bulk | J46: 2022012401R1 | K46: 44686 | L46: 1 | M46: bag | N46: 1000 | O46: 1025 | P46: =O46-N46 -> 25 | Q46: =L46*N46 -> 1000 | S46: 45484 | T46: gross | U46: =I46&"_"&H46 -> _driedflower_bulk | V46: =IF(U46="_","",_xlfn.XLOOKUP(U46,internal_cansku_inventory!D:D,internal_cansku_inventory!E:E,"",0,1))
A47: 35 | B47: 0 | C47: =Table1[[#This Row],[inventory_id_head]]&"-"&Table1[[#This Row],[inventory_id_tail]] -> 35-0 | D47: Active | E47: T008DF | F47: B017DF | G47: =E47&F47 -> T008DFB017DF | H47: driedflower_bulk | J47: 2022012401R1 | K47: 44686 | L47: 1 | M47: bag | N47: 1000 | O47: 1016.1 | P47: =O47-N47 -> 16.1 | Q47: =L47*N47 -> 1000 | S47: 45484 | T47: gross | U47: =I47&"_"&H47 -> _driedflower_bulk | V47: =IF(U47="_","",_xlfn.XLOOKUP(U47,internal_cansku_inventory!D:D,internal_cansku_inventory!E:E,"",0,1))
A48: 36 | B48: 0 | C48: =Table1[[#This Row],[inventory_id_head]]&"-"&Table1[[#This Row],[inventory_id_tail]] -> 36-0 | D48: Active | E48: T008DF | F48: B019DF | G48: =E48&F48 -> T008DFB019DF | H48: driedflower_bulk | J48: 2022012401R1 | K48: 44686 | L48: 1 | M48: bag | N48: 982.3 | O48: 982.3 | P48: 0 | Q48: =L48*N48 -> 982.3 | S48: 45484 | T48: gross | U48: =I48&"_"&H48 -> _driedflower_bulk | V48: =IF(U48="_","",_xlfn.XLOOKUP(U48,internal_cansku_inventory!D:D,internal_cansku_inventory!E:E,"",0,1))
A49: 37 | B49: 0 | C49: =Table1[[#This Row],[inventory_id_head]]&"-"&Table1[[#This Row],[inventory_id_tail]] -> 37-0 | D49: Closed | E49: T008DF | F49: B020DF | G49: =E49&F49 -> T008DFB020DF | H49: driedflower_bulk | J49: 2022012401R1 | K49: 44686 | L49: 1 | M49: bag | N49: =O49-P49 -> 426.8 | O49: 450.8 | P49: 24 | Q49: =L49*N49 -> 426.8 | S49: 45484 | T49: gross | U49: =I49&"_"&H49 -> _driedflower_bulk | V49: =IF(U49="_","",_xlfn.XLOOKUP(U49,internal_cansku_inventory!D:D,internal_cansku_inventory!E:E,"",0,1))
A50: 38 | B50: 0 | C50: =Table1[[#This Row],[inventory_id_head]]&"-"&Table1[[#This Row],[inventory_id_tail]] -> 38-0 | D50: Active | E50: T009DF | F50: B021DF | G50: =E50&F50 -> T009DFB021DF | H50: driedflower_bulk | J50: 2022051601 | K50: 44830 | L50: 1 | M50: bag | N50: 1000 | O50: 1046.1 | P50: =O50-N50 -> 46.1 | Q50: =L50*N50 -> 1000 | S50: 45484 | T50: gross | U50: =I50&"_"&H50 -> _driedflower_bulk | V50: =IF(U50="_","",_xlfn.XLOOKUP(U50,internal_cansku_inventory!D:D,internal_cansku_inventory!E:E,"",0,1))
A51: 39 | B51: 0 | C51: =Table1[[#This Row],[inventory_id_head]]&"-"&Table1[[#This Row],[inventory_id_tail]] -> 39-0 | D51: Active | E51: T009DF | F51: B022DF | G51: =E51&F51 -> T009DFB022DF | H51: driedflower_bulk | J51: 2022051601 | K51: 44830 | L51: 1 | M51: bag | N51: 1000 | O51: 1047.1 | P51: =O51-N51 -> 47.1 | Q51: =L51*N51 -> 1000 | S51: 45484 | T51: gross | U51: =I51&"_"&H51 -> _driedflower_bulk | V51: =IF(U51="_","",_xlfn.XLOOKUP(U51,internal_cansku_inventory!D:D,internal_cansku_inventory!E:E,"",0,1))
A52: 40 | B52: 0 | C52: =Table1[[#This Row],[inventory_id_head]]&"-"&Table1[[#This Row],[inventory_id_tail]] -> 40-0 | D52: Active | E52: T009DF | F52: B023DF | G52: =E52&F52 -> T009DFB023DF | H52: driedflower_bulk | J52: 2022051601 | K52: 44830 | L52: 1 | M52: bag | N52: 1000 | O52: 1042.1 | P52: =O52-N52 -> 42.1 | Q52: =L52*N52 -> 1000 | S52: 45484 | T52: gross | U52: =I52&"_"&H52 -> _driedflower_bulk | V52: =IF(U52="_","",_xlfn.XLOOKUP(U52,internal_cansku_inventory!D:D,internal_cansku_inventory!E:E,"",0,1))
A53: 42 | B53: 0 | C53: =Table1[[#This Row],[inventory_id_head]]&"-"&Table1[[#This Row],[inventory_id_tail]] -> 42-0 | D53: Active | E53: T009DF | F53: B025DF | G53: =E53&F53 -> T009DFB025DF | H53: driedflower_bulk | J53: 2022051601 | K53: 44830 | L53: 1 | M53: bag | N53: 1000 | O53: 1046 | P53: =O53-N53 -> 46 | Q53: =L53*N53 -> 1000 | S53: 45484 | T53: gross | U53: =I53&"_"&H53 -> _driedflower_bulk | V53: =IF(U53="_","",_xlfn.XLOOKUP(U53,internal_cansku_inventory!D:D,internal_cansku_inventory!E:E,"",0,1))
A54: 43 | B54: 0 | C54: =Table1[[#This Row],[inventory_id_head]]&"-"&Table1[[#This Row],[inventory_id_tail]] -> 43-0 | D54: Active | E54: T009DF | F54: B026DF | G54: =E54&F54 -> T009DFB026DF | H54: driedflower_bulk | J54: 2022051601 | K54: 44830 | L54: 1 | M54: bag | N54: 1000 | O54: 1046 | P54: =O54-N54 -> 46 | Q54: =L54*N54 -> 1000 | S54: 45484 | T54: gross | U54: =I54&"_"&H54 -> _driedflower_bulk | V54: =IF(U54="_","",_xlfn.XLOOKUP(U54,internal_cansku_inventory!D:D,internal_cansku_inventory!E:E,"",0,1))
A55: 44 | B55: 0 | C55: =Table1[[#This Row],[inventory_id_head]]&"-"&Table1[[#This Row],[inventory_id_tail]] -> 44-0 | D55: Active | E55: T009DF | F55: B027DF | G55: =E55&F55 -> T009DFB027DF | H55: driedflower_bulk | J55: 2022051601 | K55: 44830 | L55: 1 | M55: bag | N55: 1000 | O55: 1046 | P55: =O55-N55 -> 46 | Q55: =L55*N55 -> 1000 | S55: 45484 | T55: gross | U55: =I55&"_"&H55 -> _driedflower_bulk | V55: =IF(U55="_","",_xlfn.XLOOKUP(U55,internal_cansku_inventory!D:D,internal_cansku_inventory!E:E,"",0,1))
A56: 45 | B56: 0 | C56: =Table1[[#This Row],[inventory_id_head]]&"-"&Table1[[#This Row],[inventory_id_tail]] -> 45-0 | D56: Active | E56: T010DF | F56: B028DF | G56: =E56&F56 -> T010DFB028DF | H56: driedflower_bulk | J56: 2022051603 | K56: 44830 | L56: 1 | M56: bag | N56: 1000 | O56: 1021 | P56: =O56-N56 -> 21 | Q56: =L56*N56 -> 1000 | S56: 45484 | T56: gross | U56: =I56&"_"&H56 -> _driedflower_bulk | V56: =IF(U56="_","",_xlfn.XLOOKUP(U56,internal_cansku_inventory!D:D,internal_cansku_inventory!E:E,"",0,1))
A57: 46 | B57: 0 | C57: =Table1[[#This Row],[inventory_id_head]]&"-"&Table1[[#This Row],[inventory_id_tail]] -> 46-0 | D57: Active | E57: T010DF | F57: B029DF | G57: =E57&F57 -> T010DFB029DF | H57: driedflower_bulk | J57: 2022051603 | K57: 44830 | L57: 1 | M57: bag | N57: 1000 | O57: 1025 | P57: =O57-N57 -> 25 | Q57: =L57*N57 -> 1000 | S57: 45484 | T57: gross | U57: =I57&"_"&H57 -> _driedflower_bulk | V57: =IF(U57="_","",_xlfn.XLOOKUP(U57,internal_cansku_inventory!D:D,internal_cansku_inventory!E:E,"",0,1))
A58: 47 | B58: 0 | C58: =Table1[[#This Row],[inventory_id_head]]&"-"&Table1[[#This Row],[inventory_id_tail]] -> 47-0 | D58: Active | E58: T010DF | F58: B030DF | G58: =E58&F58 -> T010DFB030DF | H58: driedflower_bulk | J58: 2022051603 | K58: 44830 | L58: 1 | M58: bag | N58: 500 | O58: 514 | P58: =O58-N58 -> 14 | Q58: =L58*N58 -> 500 | S58: 45484 | T58: gross | U58: =I58&"_"&H58 -> _driedflower_bulk | V58: =IF(U58="_","",_xlfn.XLOOKUP(U58,internal_cansku_inventory!D:D,internal_cansku_inventory!E:E,"",0,1))
A59: 48 | B59: 0 | C59: =Table1[[#This Row],[inventory_id_head]]&"-"&Table1[[#This Row],[inventory_id_tail]] -> 48-0 | D59: Active | E59: T010DF | F59: B031DF | G59: =E59&F59 -> T010DFB031DF | H59: driedflower_bulk | J59: 2022051603 | K59: 44830 | L59: 1 | M59: bag | N59: 1000 | O59: 1024 | P59: =O59-N59 -> 24 | Q59: =L59*N59 -> 1000 | S59: 45484 | T59: gross | U59: =I59&"_"&H59 -> _driedflower_bulk | V59: =IF(U59="_","",_xlfn.XLOOKUP(U59,internal_cansku_inventory!D:D,internal_cansku_inventory!E:E,"",0,1))
A60: 49 | B60: 0 | C60: =Table1[[#This Row],[inventory_id_head]]&"-"&Table1[[#This Row],[inventory_id_tail]] -> 49-0 | D60: Active | E60: T010DF | F60: B032DF | G60: =E60&F60 -> T010DFB032DF | H60: driedflower_bulk | J60: 2022051603 | K60: 44830 | L60: 1 | M60: bag | N60: 1000 | O60: 1028 | P60: =O60-N60 -> 28 | Q60: =L60*N60 -> 1000 | S60: 45484 | T60: gross | U60: =I60&"_"&H60 -> _driedflower_bulk | V60: =IF(U60="_","",_xlfn.XLOOKUP(U60,internal_cansku_inventory!D:D,internal_cansku_inventory!E:E,"",0,1))
A61: 50 | B61: 0 | C61: =Table1[[#This Row],[inventory_id_head]]&"-"&Table1[[#This Row],[inventory_id_tail]] -> 50-0 | D61: Active | E61: T011DF | F61: B033DF | G61: =E61&F61 -> T011DFB033DF | H61: driedflower_bulk | J61: 2022051601 | K61: 44830 | L61: 1 | M61: bag | N61: 1000 | O61: 1044 | P61: =O61-N61 -> 44 | Q61: =L61*N61 -> 1000 | S61: 45484 | T61: gross | U61: =I61&"_"&H61 -> _driedflower_bulk | V61: =IF(U61="_","",_xlfn.XLOOKUP(U61,internal_cansku_inventory!D:D,internal_cansku_inventory!E:E,"",0,1))
... A82: 72 | B82: 0 | C82: =Table1[[#This Row],[inventory_id_head]]&"-"&Table1[[#This Row],[inventory_id_tail]] -> 72-0 | D82: Active | E82: T010DF | F82: B055DF | G82: =E82&F82 -> T010DFB055DF | H82: driedflower_bulk | J82: 2022051603 | K82: 44830 | L82: 1 | M82: bag | N82: 994 | O82: 994 | P82: =O82-N82 -> 0 | Q82: =L82*N82 -> 994 | S82: 45484 | T82: gross | U82: =I82&"_"&H82 -> _driedflower_bulk | V82: =IF(U82="_","",_xlfn.XLOOKUP(U82,internal_cansku_inventory!D:D,internal_cansku_inventory!E:E,"",0,1))
A83: 73 | B83: 0 | C83: =Table1[[#This Row],[inventory_id_head]]&"-"&Table1[[#This Row],[inventory_id_tail]] -> 73-0 | D83: Closed | E83: T003BS | F83: NA | G83: =E83&F83 -> T003BSNA | H83: topical_labelled | J83: BS23041701G180 | K83: 45467 | L83: 120 | M83: bag | N83: 180 | O83: 0 | P83: 0 | Q83: =L83*N83 -> 21600 | S83: 45485 | T83: net | U83: =I83&"_"&H83 -> _topical_labelled | V83: =IF(U83="_","",_xlfn.XLOOKUP(U83,internal_cansku_inventory!D:D,internal_cansku_inventory!E:E,"",0,1))
A84: 80 | B84: 0 | C84: =Table1[[#This Row],[inventory_id_head]]&"-"&Table1[[#This Row],[inventory_id_tail]] -> 80-0 | D84: Closed | E84: P002MF | F84: NA | G84: =E84&F84 -> P002MFNA | H84: driedflower_milled_bulk | J84: PR2410 | K84: NA | L84: 1 | M84: pail | N84: 0 | O84: 4175 | P84: =5400-3635 -> 1765 | Q84: 0 | R84: Tare weight is inaccurate | S84: 45493 | T84: gross | U84: =I84&"_"&H84 -> _driedflower_milled_bulk | V84: =IF(U84="_","",_xlfn.XLOOKUP(U84,internal_cansku_inventory!D:D,internal_cansku_inventory!E:E,"",0,1))
A85: 81 | B85: 0 | C85: =Table1[[#This Row],[inventory_id_head]]&"-"&Table1[[#This Row],[inventory_id_tail]] -> 81-0 | D85: Active | E85: P003MF | F85: NA | G85: =E85&F85 -> P003MFNA | H85: driedflower_milled_bulk | J85: PR21102801 | K85: 44497 | L85: 1 | M85: pail | N85: =O85-P85 -> 2705 | O85: 4470 | P85: =5400-3635 -> 1765 | Q85: =L85*N85 -> 2705 | S85: 45495 | T85: gross | U85: =I85&"_"&H85 -> _driedflower_milled_bulk | V85: =IF(U85="_","",_xlfn.XLOOKUP(U85,internal_cansku_inventory!D:D,internal_cansku_inventory!E:E,"",0,1))
A86: 82 | B86: 0 | C86: =Table1[[#This Row],[inventory_id_head]]&"-"&Table1[[#This Row],[inventory_id_tail]] -> 82-0 | D86: Closed | E86: P001EX | F86: NA | G86: =E86&F86 -> P001EXNA | H86: extract_ingested_bulk | J86: NA | K86: 44938 | L86: 1 | M86: pail | N86: =O86-P86 -> 11705 | O86: =11705+1765 -> 13470 | P86: =5400-3635 -> 1765 | Q86: =L86*N86 -> 11705 | S86: 45495 | T86: gross | U86: =I86&"_"&H86 -> _extract_ingested_bulk | V86: =IF(U86="_","",_xlfn.XLOOKUP(U86,internal_cansku_inventory!D:D,internal_cansku_inventory!E:E,"",0,1))
A87: 83 | B87: 0 | C87: =Table1[[#This Row],[inventory_id_head]]&"-"&Table1[[#This Row],[inventory_id_tail]] -> 83-0 | D87: Closed | E87: P002EX | F87: NA | G87: =E87&F87 -> P002EXNA | H87: extract_ingested_bulk | J87: EX22040601 | K87: 44798 | L87: 1 | M87: pail | N87: =O87-P87 -> 19130 | O87: 20895 | P87: =5400-3635 -> 1765 | Q87: =L87*N87 -> 19130 | S87: 45495 | T87: gross | U87: =I87&"_"&H87 -> _extract_ingested_bulk | V87: =IF(U87="_","",_xlfn.XLOOKUP(U87,internal_cansku_inventory!D:D,internal_cansku_inventory!E:E,"",0,1))
A88: 88 | B88: 0 | C88: =Table1[[#This Row],[inventory_id_head]]&"-"&Table1[[#This Row],[inventory_id_tail]] -> 88-0 | D88: Active | E88: P004MF | F88: NA | G88: =E88&F88 -> P004MFNA | H88: driedflower_milled_bulk | J88: PR22022801 | K88: 44620 | L88: 1 | M88: pail | N88: =O88-P88 -> 1025 | O88: 2790 | P88: =5400-3635 -> 1765 | Q88: =L88*N88 -> 1025 | S88: 45495 | T88: gross | U88: =I88&"_"&H88 -> _driedflower_milled_bulk | V88: =IF(U88="_","",_xlfn.XLOOKUP(U88,internal_cansku_inventory!D:D,internal_cansku_inventory!E:E,"",0,1))
A89: 89 | B89: 0 | C89: =Table1[[#This Row],[inventory_id_head]]&"-"&Table1[[#This Row],[inventory_id_tail]] -> 89-0 | D89: Active | E89: P005MF | F89: NA | G89: =E89&F89 -> P005MFNA | H89: driedflower_milled_bulk | J89: PR22030301 | K89: 44623 | L89: 1 | M89: pail | N89: =O89-P89 -> 1860 | O89: 3625 | P89: =5400-3635 -> 1765 | Q89: =L89*N89 -> 1860 | S89: 45495 | T89: gross | U89: =I89&"_"&H89 -> _driedflower_milled_bulk | V89: =IF(U89="_","",_xlfn.XLOOKUP(U89,internal_cansku_inventory!D:D,internal_cansku_inventory!E:E,"",0,1))
A90: 91 | B90: 0 | C90: =Table1[[#This Row],[inventory_id_head]]&"-"&Table1[[#This Row],[inventory_id_tail]] -> 91-0 | D90: Active | E90: P007EX | F90: NA | G90: =E90&F90 -> P007EXNA | H90: extract_ingested_bulk | J90: EX24022301 | K90: 45345 | L90: 1 | M90: pail | N90: =O90-P90 -> 2385 | O90: 4150 | P90: =5400-3635 -> 1765 | Q90: =L90*N90 -> 2385 | S90: 45495 | T90: gross | U90: =I90&"_"&H90 -> _extract_ingested_bulk | V90: =IF(U90="_","",_xlfn.XLOOKUP(U90,internal_cansku_inventory!D:D,internal_cansku_inventory!E:E,"",0,1))
A91: 92 | B91: 0 | C91: =Table1[[#This Row],[inventory_id_head]]&"-"&Table1[[#This Row],[inventory_id_tail]] -> 92-0 | D91: Closed | E91: P008EX | F91: NA | G91: =E91&F91 -> P008EXNA | H91: extract_ingested_bulk | J91: EX24022302 | K91: 45345 | L91: 1 | M91: pail | N91: =O91-P91 -> 2230 | O91: 3995 | P91: =5400-3635 -> 1765 | Q91: =L91*N91 -> 2230 | S91: 45495 | T91: gross | U91: =I91&"_"&H91 -> _extract_ingested_bulk | V91: =IF(U91="_","",_xlfn.XLOOKUP(U91,internal_cansku_inventory!D:D,internal_cansku_inventory!E:E,"",0,1))
A92: 93 | B92: 0 | C92: =Table1[[#This Row],[inventory_id_head]]&"-"&Table1[[#This Row],[inventory_id_tail]] -> 93-0 | D92: Active | E92: P008MF | F92: NA | G92: =E92&F92 -> P008MFNA | H92: driedflower_milled_bulk | J92: PR21062101 | K92: 44255 | L92: 1 | M92: pail | N92: =O92-P92 -> 3770 | O92: 5535 | P92: =5400-3635 -> 1765 | Q92: =L92*N92 -> 3770 | S92: 45495 | T92: gross | U92: =I92&"_"&H92 -> _driedflower_milled_bulk | V92: =IF(U92="_","",_xlfn.XLOOKUP(U92,internal_cansku_inventory!D:D,internal_cansku_inventory!E:E,"",0,1))
A93: 94 | B93: 0 | C93: =Table1[[#This Row],[inventory_id_head]]&"-"&Table1[[#This Row],[inventory_id_tail]] -> 94-0 | D93: Active | E93: P009MF | F93: NA | G93: =E93&F93 -> P009MFNA | H93: driedflower_milled_bulk | J93: PR21102801 | K93: 44620 | L93: 1 | M93: pail | N93: =O93-P93 -> 1540 | O93: 3305 | P93: =5400-3635 -> 1765 | Q93: =L93*N93 -> 1540 | S93: 45495 | T93: gross | U93: =I93&"_"&H93 -> _driedflower_milled_bulk | V93: =IF(U93="_","",_xlfn.XLOOKUP(U93,internal_cansku_inventory!D:D,internal_cansku_inventory!E:E,"",0,1))
A94: 95 | B94: 0 | C94: =Table1[[#This Row],[inventory_id_head]]&"-"&Table1[[#This Row],[inventory_id_tail]] -> 95-0 | D94: Closed | E94: P001TP | F94: NA | G94: =E94&F94 -> P001TPNA | H94: topical_bulk | J94: TP24041201 | K94: 45448 | L94: 1 | M94: pail | N94: =O94-P94 -> 16820 | O94: 18585 | P94: =5400-3635 -> 1765 | Q94: =L94*N94 -> 16820 | S94: 45495 | T94: gross | U94: =I94&"_"&H94 -> _topical_bulk | V94: =IF(U94="_","",_xlfn.XLOOKUP(U94,internal_cansku_inventory!D:D,internal_cansku_inventory!E:E,"",0,1))
A95: 96 | B95: 0 | C95: =Table1[[#This Row],[inventory_id_head]]&"-"&Table1[[#This Row],[inventory_id_tail]] -> 96-0 | D95: Active | E95: P007MF | F95: NA | G95: =E95&F95 -> P007MFNA | H95: driedflower_milled_bulk | J95: PR2301 | K95: 44206 | L95: 1 | M95: pail | N95: =O95-P95 -> 3360 | O95: 5125 | P95: =5400-3635 -> 1765 | Q95: =L95*N95 -> 3360 | S95: 45495 | T95: gross | U95: =I95&"_"&H95 -> _driedflower_milled_bulk | V95: =IF(U95="_","",_xlfn.XLOOKUP(U95,internal_cansku_inventory!D:D,internal_cansku_inventory!E:E,"",0,1))
A96: 98 | B96: 0 | C96: =Table1[[#This Row],[inventory_id_head]]&"-"&Table1[[#This Row],[inventory_id_tail]] -> 98-0 | D96: Active | E96: P011MF | F96: NA | G96: =E96&F96 -> P011MFNA | H96: driedflower_milled_bulk | J96: CPR22102001 | K96: NA | L96: 1 | M96: pail | N96: =O96-P96 -> 1665 | O96: 3430 | P96: =5400-3635 -> 1765 | Q96: =L96*N96 -> 1665 | S96: 45496 | T96: gross | U96: =I96&"_"&H96 -> _driedflower_milled_bulk | V96: =IF(U96="_","",_xlfn.XLOOKUP(U96,internal_cansku_inventory!D:D,internal_cansku_inventory!E:E,"",0,1))
A97: 100 | B97: 0 | C97: =Table1[[#This Row],[inventory_id_head]]&"-"&Table1[[#This Row],[inventory_id_tail]] -> 100-0 | D97: Active | E97: P013MF | F97: NA | G97: =E97&F97 -> P013MFNA | H97: driedflower_milled_bulk | J97: CPR22102102 | K97: NA | L97: 1 | M97: pail | N97: =O97-P97 -> 815 | O97: 2580 | P97: =5400-3635 -> 1765 | Q97: =L97*N97 -> 815 | S97: 45496 | T97: gross | U97: =I97&"_"&H97 -> _driedflower_milled_bulk | V97: =IF(U97="_","",_xlfn.XLOOKUP(U97,internal_cansku_inventory!D:D,internal_cansku_inventory!E:E,"",0,1))
A98: 101 | B98: 0 | C98: =Table1[[#This Row],[inventory_id_head]]&"-"&Table1[[#This Row],[inventory_id_tail]] -> 101-0 | D98: Active | E98: P014MF | F98: NA | G98: =E98&F98 -> P014MFNA | H98: driedflower_milled_bulk | J98: PR21102801 | K98: 44497 | L98: 1 | M98: pail | N98: =O98-P98 -> 2595 | O98: 4360 | P98: =5400-3635 -> 1765 | Q98: =L98*N98 -> 2595 | S98: 45496 | T98: gross | U98: =I98&"_"&H98 -> _driedflower_milled_bulk | V98: =IF(U98="_","",_xlfn.XLOOKUP(U98,internal_cansku_inventory!D:D,internal_cansku_inventory!E:E,"",0,1))
A99: 102 | B99: 0 | C99: =Table1[[#This Row],[inventory_id_head]]&"-"&Table1[[#This Row],[inventory_id_tail]] -> 102-0 | D99: Active | E99: P015MF | F99: NA | G99: =E99&F99 -> P015MFNA | H99: driedflower_milled_bulk | J99: PR22030701 | K99: 44627 | L99: 1 | M99: pail | N99: =O99-P99 -> 2935 | O99: 4700 | P99: 1765 | Q99: =L99*N99 -> 2935 | S99: 45496 | T99: gross | U99: =I99&"_"&H99 -> _driedflower_milled_bulk | V99: =IF(U99="_","",_xlfn.XLOOKUP(U99,internal_cansku_inventory!D:D,internal_cansku_inventory!E:E,"",0,1))
A100: 103 | B100: 0 | C100: =Table1[[#This Row],[inventory_id_head]]&"-"&Table1[[#This Row],[inventory_id_tail]] -> 103-0 | D100: Active | E100: P016MF | F100: NA | G100: =E100&F100 -> P016MFNA | H100: driedflower_milled_bulk | J100: PR21062101 | K100: NA | L100: 1 | M100: pail | N100: =O100-P100 -> 685 | O100: 2450 | P100: 1765 | Q100: =L100*N100 -> 685 | S100: 45496 | T100: gross | U100: =I100&"_"&H100 -> _driedflower_milled_bulk | V100: =IF(U100="_","",_xlfn.XLOOKUP(U100,internal_cansku_inventory!D:D,internal_cansku_inventory!E:E,"",0,1))
A101: 110 | B101: 0 | C101: =Table1[[#This Row],[inventory_id_head]]&"-"&Table1[[#This Row],[inventory_id_tail]] -> 110-0 | D101: Active | E101: T005PR | F101: NA | G101: =E101&F101 -> T005PRNA | H101: preroll_packaged | J101: PR2410F5P3 | K101: NA | L101: =90+610 -> 700 | M101: unit | N101: 1.5 | O101: 0 | P101: 0 | Q101: =L101*N101 -> 1050 | S101: 45499 | T101: net | U101: =I101&"_"&H101 -> _preroll_packaged | V101: =IF(U101="_","",_xlfn.XLOOKUP(U101,internal_cansku_inventory!D:D,internal_cansku_inventory!E:E,"",0,1))
A102: 111 | B102: 0 | C102: =Table1[[#This Row],[inventory_id_head]]&"-"&Table1[[#This Row],[inventory_id_tail]] -> 111-0 | D102: Active | E102: T006PR | F102: NA | G102: T006PRNA | H102: preroll_labelled | J102: CPR22102102G1 | K102: 44999 | L102: 213 | M102: unit | N102: 1 | O102: 0 | P102: 0 | Q102: 213 | S102: 45499 | T102: net | U102: =I102&"_"&H102 -> _preroll_labelled | V102: =IF(U102="_","",_xlfn.XLOOKUP(U102,internal_cansku_inventory!D:D,internal_cansku_inventory!E:E,"",0,1))
A103: 112 | B103: 0 | C103: =Table1[[#This Row],[inventory_id_head]]&"-"&Table1[[#This Row],[inventory_id_tail]] -> 112-0 | D103: Active | E103: T003PR | F103: B001PR | G103: T003PRB001PR | H103: preroll_labelled | J103: CPR22102102G5 | K103: 44999 | L103: 5 | M103: unit | N103: 1.5 | O103: 0 | P103: 0 | Q103: 7.5 | S103: 45499 | T103: net | U103: =I103&"_"&H103 -> _preroll_labelled | V103: =IF(U103="_","",_xlfn.XLOOKUP(U103,internal_cansku_inventory!D:D,internal_cansku_inventory!E:E,"",0,1))
A104: 113 | B104: 0 | C104: =Table1[[#This Row],[inventory_id_head]]&"-"&Table1[[#This Row],[inventory_id_tail]] -> 113-0 | D104: Active | E104: T007PR | F104: NA | G104: T007PRNA | H104: preroll_labelled | J104: CPR22102001G5 | K104: 45014 | L104: 134 | M104: unit | N104: 1.5 | O104: 0 | P104: 0 | Q104: 201 | S104: 45499 | T104: net | U104: =I104&"_"&H104 -> _preroll_labelled | V104: =IF(U104="_","",_xlfn.XLOOKUP(U104,internal_cansku_inventory!D:D,internal_cansku_inventory!E:E,"",0,1))
A105: 117 | B105: 0 | C105: =Table1[[#This Row],[inventory_id_head]]&"-"&Table1[[#This Row],[inventory_id_tail]] -> 117-0 | D105: Active | E105: T011PR | F105: NA | G105: =E105&F105 -> T011PRNA | H105: preroll_bulk | J105: PR22051901G1 | K105: 45016 | L105: 537 | M105: unit | N105: 1 | O105: 0 | P105: 0 | Q105: =L105*N105 -> 537 | S105: 45499 | T105: net | U105: =I105&"_"&H105 -> _preroll_bulk | V105: =IF(U105="_","",_xlfn.XLOOKUP(U105,internal_cansku_inventory!D:D,internal_cansku_inventory!E:E,"",0,1))
A106: 118 | B106: 0 | C106: =Table1[[#This Row],[inventory_id_head]]&"-"&Table1[[#This Row],[inventory_id_tail]] -> 118-0 | D106: Active | E106: T012PR | F106: NA | G106: =E106&F106 -> T012PRNA | H106: preroll_labelled | J106: PR22051901G1 | K106: 45798 | L106: 206 | M106: unit | N106: 1 | O106: 0 | P106: 0 | Q106: =L106*N106 -> 206 | S106: 45499 | T106: net | U106: =I106&"_"&H106 -> _preroll_labelled | V106: =IF(U106="_","",_xlfn.XLOOKUP(U106,internal_cansku_inventory!D:D,internal_cansku_inventory!E:E,"",0,1))
A107: 120 | B107: 0 | C107: =Table1[[#This Row],[inventory_id_head]]&"-"&Table1[[#This Row],[inventory_id_tail]] -> 120-0 | D107: Active | E107: T015PR | F107: NA | G107: =E107&F107 -> T015PRNA | H107: preroll_bulk | J107: CPR22102102G1 | K107: 45016 | L107: 1545 | M107: unit | N107: 1 | O107: 0 | P107: 0 | Q107: =L107*N107 -> 1545 | S107: 45499 | T107: net | U107: =I107&"_"&H107 -> _preroll_bulk | V107: =IF(U107="_","",_xlfn.XLOOKUP(U107,internal_cansku_inventory!D:D,internal_cansku_inventory!E:E,"",0,1))
A108: 123 | B108: 0 | C108: =Table1[[#This Row],[inventory_id_head]]&"-"&Table1[[#This Row],[inventory_id_tail]] -> 123-0 | D108: Active | E108: T016PR | F108: NA | G108: =E108&F108 -> T016PRNA | H108: preroll_bulk | J108: PR21071201G1 | K108: NA | L108: 534 | M108: unit | N108: 1 | O108: 0 | P108: 0 | Q108: =L108*N108 -> 534 | S108: 45502 | T108: net | U108: =I108&"_"&H108 -> _preroll_bulk | V108: =IF(U108="_","",_xlfn.XLOOKUP(U108,internal_cansku_inventory!D:D,internal_cansku_inventory!E:E,"",0,1))
A109: 125 | B109: 0 | C109: =Table1[[#This Row],[inventory_id_head]]&"-"&Table1[[#This Row],[inventory_id_tail]] -> 125-0 | D109: Active | E109: T018PR | F109: NA | G109: =E109&F109 -> T018PRNA | H109: preroll_labelled | J109: PR21071201G5 | K109: 45051 | L109: 34 | M109: unit | N109: 1 | O109: 0 | P109: 0 | Q109: =L109*N109 -> 34 | S109: 45502 | T109: net | U109: =I109&"_"&H109 -> _preroll_labelled | V109: =IF(U109="_","",_xlfn.XLOOKUP(U109,internal_cansku_inventory!D:D,internal_cansku_inventory!E:E,"",0,1))
A110: 127 | B110: 0 | C110: =Table1[[#This Row],[inventory_id_head]]&"-"&Table1[[#This Row],[inventory_id_tail]] -> 127-0 | D110: Active | E110: T019PR | F110: NA | G110: =E110&F110 -> T019PRNA | H110: preroll_bulk | J110: PR21091301 | K110: 44960 | L110: =716+615+661+600+67 -> 2659 | M110: unit | N110: 0.01 | O110: 0 | P110: 0 | Q110: =L110*N110 -> 26.59 | R110: 67 damaged; unknown individual weight | S110: 45502 | T110: net | U110: =I110&"_"&H110 -> _preroll_bulk | V110: =IF(U110="_","",_xlfn.XLOOKUP(U110,internal_cansku_inventory!D:D,internal_cansku_inventory!E:E,"",0,1))
A111: 128 | B111: 0 | C111: =Table1[[#This Row],[inventory_id_head]]&"-"&Table1[[#This Row],[inventory_id_tail]] -> 128-0 | D111: Active | E111: T019PR | F111: NA | G111: =E111&F111 -> T019PRNA | H111: preroll_bulk | J111: 2021042701G5 | K111: 45112 | L111: 377 | M111: unit | N111: 0.5 | O111: 0 | P111: 0 | Q111: =L111*N111 -> 188.5 | S111: 45502 | T111: net | U111: =I111&"_"&H111 -> _preroll_bulk | V111: =IF(U111="_","",_xlfn.XLOOKUP(U111,internal_cansku_inventory!D:D,internal_cansku_inventory!E:E,"",0,1))
A112: 129 | B112: 0 | C112: =Table1[[#This Row],[inventory_id_head]]&"-"&Table1[[#This Row],[inventory_id_tail]] -> 129-0 | D112: Active | E112: T019PR | F112: NA | G112: =E112&F112 -> T019PRNA | H112: preroll_bulk | J112: PR21071201 | K112: 44960 | L112: 46 | M112: unit | N112: 0.01 | O112: 0 | P112: 0 | Q112: =L112*N112 -> 0.46 | R112: unknown individual weight | S112: 45502 | T112: net | U112: =I112&"_"&H112 -> _preroll_bulk | V112: =IF(U112="_","",_xlfn.XLOOKUP(U112,internal_cansku_inventory!D:D,internal_cansku_inventory!E:E,"",0,1))
A113: 130 | B113: 0 | C113: =Table1[[#This Row],[inventory_id_head]]&"-"&Table1[[#This Row],[inventory_id_tail]] -> 130-0 | D113: Active | E113: T020PR | F113: NA | G113: =E113&F113 -> T020PRNA | H113: preroll_bulk | J113: PR23040301F5P3 | K113: 45022 | L113: 1252 | M113: unit | N113: 0.35 | O113: 0 | P113: 0 | Q113: =L113*N113 -> 438.2 | S113: 45502 | T113: net | U113: =I113&"_"&H113 -> _preroll_bulk | V113: =IF(U113="_","",_xlfn.XLOOKUP(U113,internal_cansku_inventory!D:D,internal_cansku_inventory!E:E,"",0,1))
A114: 131 | B114: 0 | C114: =Table1[[#This Row],[inventory_id_head]]&"-"&Table1[[#This Row],[inventory_id_tail]] -> 131-0 | D114: Active | E114: T021PR | F114: NA | G114: =E114&F114 -> T021PRNA | H114: preroll_labelled | J114: PR22031601ING5 | K114: 45051 | L114: 268 | M114: unit | N114: 1.5 | O114: 0 | P114: 0 | Q114: =L114*N114 -> 402 | S114: 45502 | T114: net | U114: =I114&"_"&H114 -> _preroll_labelled | V114: =IF(U114="_","",_xlfn.XLOOKUP(U114,internal_cansku_inventory!D:D,internal_cansku_inventory!E:E,"",0,1))
A115: 132 | B115: 0 | C115: =Table1[[#This Row],[inventory_id_head]]&"-"&Table1[[#This Row],[inventory_id_tail]] -> 132-0 | D115: Active | E115: T021PR | F115: NA | G115: =E115&F115 -> T021PRNA | H115: preroll_bulk | J115: PR22031601IN | K115: 45502 | L115: 778 | M115: unit | N115: 0.5 | O115: 0 | P115: 0 | Q115: =L115*N115 -> 389 | S115: 45502 | T115: net | U115: =I115&"_"&H115 -> _preroll_bulk | V115: =IF(U115="_","",_xlfn.XLOOKUP(U115,internal_cansku_inventory!D:D,internal_cansku_inventory!E:E,"",0,1))
A116: 133 | B116: 0 | C116: =Table1[[#This Row],[inventory_id_head]]&"-"&Table1[[#This Row],[inventory_id_tail]] -> 133-0 | D116: Active | E116: T021PR | F116: NA | G116: =E116&F116 -> T021PRNA | H116: preroll_labelled | J116: PR2301INF1P1 | K116: 45059 | L116: 3 | M116: unit | N116: 1 | O116: 0 | P116: 0 | Q116: =L116*N116 -> 3 | S116: 45502 | T116: net | U116: =I116&"_"&H116 -> _preroll_labelled | V116: =IF(U116="_","",_xlfn.XLOOKUP(U116,internal_cansku_inventory!D:D,internal_cansku_inventory!E:E,"",0,1))
A117: 134 | B117: 0 | C117: =Table1[[#This Row],[inventory_id_head]]&"-"&Table1[[#This Row],[inventory_id_tail]] -> 134-0 | D117: Active | E117: T022PR | F117: NA | G117: =E117&F117 -> T022PRNA | H117: preroll_bulk | J117: PR2302INF1 | K117: NA | L117: =79+7*143+300+151+44+50 -> 1625 | M117: unit | N117: 1 | O117: 0 | P117: 0 | Q117: =L117*N117 -> 1625 | S117: 45502 | T117: net | U117: =I117&"_"&H117 -> _preroll_bulk | V117: =IF(U117="_","",_xlfn.XLOOKUP(U117,internal_cansku_inventory!D:D,internal_cansku_inventory!E:E,"",0,1))
A118: 135 | B118: 0 | C118: =Table1[[#This Row],[inventory_id_head]]&"-"&Table1[[#This Row],[inventory_id_tail]] -> 135-0 | D118: Active | E118: T022PR | F118: NA | G118: =E118&F118 -> T022PRNA | H118: preroll_bulk | J118: PR22031601IN | K118: NA | L118: 104 | M118: unit | N118: 0.01 | O118: 0 | P118: 0 | Q118: =L118*N118 -> 1.04 | R118: unknown individual weight | S118: 45502 | T118: net | U118: =I118&"_"&H118 -> _preroll_bulk | V118: =IF(U118="_","",_xlfn.XLOOKUP(U118,internal_cansku_inventory!D:D,internal_cansku_inventory!E:E,"",0,1))
A119: 136 | B119: 0 | C119: =Table1[[#This Row],[inventory_id_head]]&"-"&Table1[[#This Row],[inventory_id_tail]] -> 136-0 | D119: Active | E119: T023PR | F119: NA | G119: =E119&F119 -> T023PRNA | H119: preroll_bulk | J119: PR21102801 | K119: NA | L119: 398 | M119: unit | N119: 1 | O119: 0 | P119: 0 | Q119: =L119*N119 -> 398 | S119: 45502 | T119: net | U119: =I119&"_"&H119 -> _preroll_bulk | V119: =IF(U119="_","",_xlfn.XLOOKUP(U119,internal_cansku_inventory!D:D,internal_cansku_inventory!E:E,"",0,1))
A120: 138 | B120: 0 | C120: =Table1[[#This Row],[inventory_id_head]]&"-"&Table1[[#This Row],[inventory_id_tail]] -> 138-0 | D120: Closed | E120: T024PR | F120: NA | G120: =E120&F120 -> T024PRNA | H120: preroll_bulk | J120: CPR22102101G1 | K120: NA | L120: 221 | M120: unit | N120: 1 | O120: 0 | P120: 0 | Q120: =L120*N120 -> 221 | S120: 45502 | T120: net | U120: =I120&"_"&H120 -> _preroll_bulk | V120: =IF(U120="_","",_xlfn.XLOOKUP(U120,internal_cansku_inventory!D:D,internal_cansku_inventory!E:E,"",0,1))
...

Sheet dailychange
A1: movement | B1: time | C1: purpose | D1: purpose_description | E1: inventory_id | F1: lot_number | G1: product_name | H1: stage | I1: pack_on_date | J1: quantity_change_unit | K1: quantity_change_gross_weight | L1: quantity_change_net_weight | M1: note | N1: calculation_method | O1: netweight_for_netmethod
A2: =IF(ISBLANK(J2),"",IF(J2+K2+L2<0,"outbound","inbound")) -> outbound | B2: 45485 | C2: production | D2: relabel POD | E2: 1-0 | F2: BS23041701G180 | H2: =IF(ISBLANK(E2),"",_xlfn.XLOOKUP(E2,cannabis_log!C:C,cannabis_log!H:H,"",0,1)) -> topical_labelled | I2: 45467 | J2: -47 | K2: 0 | L2: -8460 | N2: net | O2: 180
A3: =IF(ISBLANK(J3),"",IF(J3+K3+L3<0,"outbound","inbound")) -> outbound | B3: 45485.001 | C3: sampling | D3: making 31 rosebud preroll for AB sales + AGLC order | E3: 4-0 | F3: PR2303 | H3: =IF(ISBLANK(E3),"",_xlfn.XLOOKUP(E3,cannabis_log!C:C,cannabis_log!H:H,"",0,1)) -> driedflower_milled_bulk | I3: NA | J3: -1 | K3: -830 | L3: 0 | N3: gross | O3: 0
A4: =IF(ISBLANK(J4),"",IF(J4+K4+L4<0,"outbound","inbound")) -> inbound | B4: 45489 | C4: storage | D4: PO_DD2024071702 | E4: 1-0 | F4: BS23041701G180 | H4: =IF(ISBLANK(E4),"",_xlfn.XLOOKUP(E4,cannabis_log!C:C,cannabis_log!H:H,"",0,1)) -> topical_labelled | I4: 45467 | J4: 47 | K4: 0 | L4: 8460 | N4: net | O4: 180
A5: =IF(ISBLANK(J5),"",IF(J5+K5+L5<0,"outbound","inbound")) -> outbound | B5: 45489.001 | C5: shipment | D5: PO_DD2024071702 | E5: 1-0 | F5: BS23041701G180 | H5: =IF(ISBLANK(E5),"",_xlfn.XLOOKUP(E5,cannabis_log!C:C,cannabis_log!H:H,"",0,1)) -> topical_labelled | I5: 45467 | J5: -6 | K5: 0 | L5: -1080 | N5: net | O5: 180
A6: =IF(ISBLANK(J6),"",IF(J6+K6+L6<0,"outbound","inbound")) -> inbound | B6: 45489.001 | C6: storage | E6: 4-0 | F6: PR2303 | H6: =IF(ISBLANK(E6),"",_xlfn.XLOOKUP(E6,cannabis_log!C:C,cannabis_log!H:H,"",0,1)) -> driedflower_milled_bulk | I6: NA | J6: 1 | K6: 830 | L6: 0 | N6: gross | O6: 0
A7: =IF(ISBLANK(J7),"",IF(J7+K7+L7<0,"outbound","inbound")) -> outbound | B7: 45495 | C7: sampling | D7: Sampling for Torre BBQ | E7: 1-0 | F7: BS23041701G180 | H7: =IF(ISBLANK(E7),"",_xlfn.XLOOKUP(E7,cannabis_log!C:C,cannabis_log!H:H,"",0,1)) -> topical_labelled | I7: 45467 | J7: -41 | K7: 0 | L7: -7380 | N7: net | O7: 180
A8: =IF(ISBLANK(J8),"",IF(J8+K8+L8<0,"outbound","inbound")) -> outbound | B8: 45495.001 | C8: sampling | D8: Sampling for Torre BBQ | E8: 73-0 | F8: BS23041701G180 | H8: =IF(ISBLANK(E8),"",_xlfn.XLOOKUP(E8,cannabis_log!C:C,cannabis_log!H:H,"",0,1)) -> topical_labelled | I8: 45467 | J8: -9 | K8: 0 | L8: -1620 | N8: net | O8: 180
A9: =IF(ISBLANK(J9),"",IF(J9+K9+L9<0,"outbound","inbound")) -> outbound | B9: 45495.001 | C9: sampling | D9: Sampling for Torre BBQ | E9: 77-0 | F9: TP24041201 | H9: =IF(ISBLANK(E9),"",_xlfn.XLOOKUP(E9,cannabis_log!C:C,cannabis_log!H:H,"",0,1)) -> topical_labelled | I9: 45448 | J9: -4 | K9: 0 | L9: -352 | N9: net | O9: 88
A10: =IF(ISBLANK(J10),"",IF(J10+K10+L10<0,"outbound","inbound")) -> outbound | B10: 45495.002 | C10: sampling | E10: 77-0 | F10: TP24041201 | H10: =IF(ISBLANK(E10),"",_xlfn.XLOOKUP(E10,cannabis_log!C:C,cannabis_log!H:H,"",0,1)) -> topical_labelled | I10: 45448 | J10: -4 | K10: 0 | L10: -352 | N10: net | O10: 88
A11: =IF(ISBLANK(J11),"",IF(J11+K11+L11<0,"outbound","inbound")) -> outbound | B11: 45495.003 | C11: production | E11: 79-0 | F11: PR2410 | H11: =IF(ISBLANK(E11),"",_xlfn.XLOOKUP(E11,cannabis_log!C:C,cannabis_log!H:H,"",0,1)) -> driedflower_milled_bulk | I11: NA | J11: -1 | K11: -3635 | L11: 0 | N11: gross | O11: 0
A12: =IF(ISBLANK(J12),"",IF(J12+K12+L12<0,"outbound","inbound")) -> inbound | B12: 45495.003 | C12: storage | E12: 79-0 | F12: PR2410 | H12: =IF(ISBLANK(E12),"",_xlfn.XLOOKUP(E12,cannabis_log!C:C,cannabis_log!H:H,"",0,1)) -> driedflower_milled_bulk | I12: NA | J12: 1 | K12: 5210 | L12: 0 | N12: gross | O12: 0
A13: =IF(ISBLANK(J13),"",IF(J13+K13+L13<0,"outbound","inbound")) -> outbound | B13: 45495.004 | C13: production | E13: 80-0 | F13: PR2410 | H13: =IF(ISBLANK(E13),"",_xlfn.XLOOKUP(E13,cannabis_log!C:C,cannabis_log!H:H,"",0,1)) -> driedflower_milled_bulk | I13: NA | J13: -1 | K13: -2410 | L13: 0 | N13: gross | O13: 0
A14: =IF(ISBLANK(J14),"",IF(J14+K14+L14<0,"outbound","inbound")) -> inbound | B14: 45496 | C14: storage | D14: samples return from Torre BBQ | E14: 1-0 | F14: BS23041701G180 | H14: =IF(ISBLANK(E14),"",_xlfn.XLOOKUP(E14,cannabis_log!C:C,cannabis_log!H:H,"",0,1)) -> topical_labelled | I14: 45467 | J14: 50 | K14: 0 | L14: 9000 | N14: net | O14: 180
A15: =IF(ISBLANK(J15),"",IF(J15+K15+L15<0,"outbound","inbound")) -> outbound | B15: 45496.001 | C15: sampling | D15: Sampling for Torre BBQ | E15: 4-0 | F15: PR2303 | H15: =IF(ISBLANK(E15),"",_xlfn.XLOOKUP(E15,cannabis_log!C:C,cannabis_log!H:H,"",0,1)) -> driedflower_milled_bulk | I15: NA | J15: -1 | K15: -830 | L15: 0 | N15: gross | O15: 0
A16: =IF(ISBLANK(J16),"",IF(J16+K16+L16<0,"outbound","inbound")) -> outbound | B16: 45496.001 | C16: production | E16: 79-0 | F16: PR2410 | H16: =IF(ISBLANK(E16),"",_xlfn.XLOOKUP(E16,cannabis_log!C:C,cannabis_log!H:H,"",0,1)) -> driedflower_milled_bulk | I16: NA | J16: 0 | K16: -655 | L16: 0 | N16: gross | O16: 0
A17: =IF(ISBLANK(J17),"",IF(J17+K17+L17<0,"outbound","inbound")) -> inbound | B17: 45497 | C17: storage | E17: 4-0 | F17: PR2303 | H17: =IF(ISBLANK(E17),"",_xlfn.XLOOKUP(E17,cannabis_log!C:C,cannabis_log!H:H,"",0,1)) -> driedflower_milled_bulk | I17: NA | J17: 1 | K17: 827.6 | L17: 0 | N17: gross | O17: 0
A18: =IF(ISBLANK(J18),"",IF(J18+K18+L18<0,"outbound","inbound")) -> outbound | B18: 45497 | C18: sampling | E18: 73-0 | F18: BS23041701G180 | H18: =IF(ISBLANK(E18),"",_xlfn.XLOOKUP(E18,cannabis_log!C:C,cannabis_log!H:H,"",0,1)) -> topical_labelled | I18: 45467 | J18: -9 | K18: 0 | L18: -1620 | N18: net | O18: 180
A19: =IF(ISBLANK(J19),"",IF(J19+K19+L19<0,"outbound","inbound")) -> outbound | B19: 45497.001 | C19: sampling | D19: sample for Steve | E19: 77-0 | F19: TP24041201 | H19: =IF(ISBLANK(E19),"",_xlfn.XLOOKUP(E19,cannabis_log!C:C,cannabis_log!H:H,"",0,1)) -> topical_labelled | I19: 45448 | J19: -1 | K19: 0 | L19: -88 | N19: net | O19: 88
A20: =IF(ISBLANK(J20),"",IF(J20+K20+L20<0,"outbound","inbound")) -> outbound | B20: 45497.001 | C20: production | E20: 84-0 | F20: NA | H20: =IF(ISBLANK(E20),"",_xlfn.XLOOKUP(E20,cannabis_log!C:C,cannabis_log!H:H,"",0,1)) -> extract_ingested_cased_BC | I20: NA | J20: 0 | K20: -375 | L20: 0 | N20: gross | O20: 0
A21: =IF(ISBLANK(J21),"",IF(J21+K21+L21<0,"outbound","inbound")) -> inbound | B21: 45497.002 | C21: storage | E21: 85-0 | F21: NA | H21: =IF(ISBLANK(E21),"",_xlfn.XLOOKUP(E21,cannabis_log!C:C,cannabis_log!H:H,"",0,1)) -> extract_ingested_cased_BC | I21: NA | J21: 0 | K21: 15 | L21: 0 | N21: gross | O21: 0
A22: =IF(ISBLANK(J22),"",IF(J22+K22+L22<0,"outbound","inbound")) -> outbound | B22: 45498 | C22: shipment | E22: 1-0 | F22: BS23041701G180 | H22: =IF(ISBLANK(E22),"",_xlfn.XLOOKUP(E22,cannabis_log!C:C,cannabis_log!H:H,"",0,1)) -> topical_labelled | I22: 45467 | J22: -6 | K22: 0 | L22: -1080 | N22: net | O22: 180
A23: =IF(ISBLANK(J23),"",IF(J23+K23+L23<0,"outbound","inbound")) -> outbound | B23: 45498.001 | C23: sampling | E23: 4-0 | F23: PR2303 | H23: =IF(ISBLANK(E23),"",_xlfn.XLOOKUP(E23,cannabis_log!C:C,cannabis_log!H:H,"",0,1)) -> driedflower_milled_bulk | I23: NA | J23: 0 | K23: -7.6 | L23: 0 | N23: gross | O23: 0
A24: =IF(ISBLANK(J24),"",IF(J24+K24+L24<0,"outbound","inbound")) -> outbound | B24: 45498.001 | C24: sampling | D24: sample for Jay | E24: 4-0 | F24: PR2303 | H24: =IF(ISBLANK(E24),"",_xlfn.XLOOKUP(E24,cannabis_log!C:C,cannabis_log!H:H,"",0,1)) -> driedflower_milled_bulk | I24: NA | J24: -1 | K24: -820 | L24: 0 | N24: gross | O24: 0
A25: =IF(ISBLANK(J25),"",IF(J25+K25+L25<0,"outbound","inbound")) -> inbound | B25: 45498.002 | C25: sampling | D25: sample for Jay | E25: 4-0 | F25: PR2303 | H25: =IF(ISBLANK(E25),"",_xlfn.XLOOKUP(E25,cannabis_log!C:C,cannabis_log!H:H,"",0,1)) -> driedflower_milled_bulk | I25: NA | J25: 1 | K25: 821.1 | L25: 0 | N25: gross | O25: 0
A26: =IF(ISBLANK(J26),"",IF(J26+K26+L26<0,"outbound","inbound")) -> outbound | B26: 45498.003 | C26: shipment | D26: PO_DD2024072302 | E26: 74-0 | F26: BS23101901G450 | H26: =IF(ISBLANK(E26),"",_xlfn.XLOOKUP(E26,cannabis_log!C:C,cannabis_log!H:H,"",0,1)) -> topical_labelled | I26: 45234 | J26: -7 | K26: 0 | L26: -3150 | N26: net | O26: 450
A27: =IF(ISBLANK(J27),"",IF(J27+K27+L27<0,"outbound","inbound")) -> outbound | B27: 45498.003 | C27: shipment | E27: 78-0 | F27: TP24041202 | H27: =IF(ISBLANK(E27),"",_xlfn.XLOOKUP(E27,cannabis_log!C:C,cannabis_log!H:H,"",0,1)) -> topical_labelled | I27: 45423 | J27: -12 | K27: 0 | L27: -1056 | N27: net | O27: 88
A28: =IF(ISBLANK(J28),"",IF(J28+K28+L28<0,"outbound","inbound")) -> outbound | B28: 45498.004 | C28: sampling | D28: sample for Jay | E28: 91-0 | F28: EX24022301 | H28: =IF(ISBLANK(E28),"",_xlfn.XLOOKUP(E28,cannabis_log!C:C,cannabis_log!H:H,"",0,1)) -> extract_ingested_bulk | I28: 45345 | J28: 0 | K28: -40 | L28: 0 | N28: gross | O28: 0
A29: =IF(ISBLANK(J29),"",IF(J29+K29+L29<0,"outbound","inbound")) -> outbound | B29: 45498.005 | C29: sampling | D29: sample for Jay | E29: 92-0 | F29: EX24022302 | H29: =IF(ISBLANK(E29),"",_xlfn.XLOOKUP(E29,cannabis_log!C:C,cannabis_log!H:H,"",0,1)) -> extract_ingested_bulk | I29: 45345 | J29: 0 | K29: -40 | L29: 0 | N29: gross | O29: 0
A30: =IF(ISBLANK(J30),"",IF(J30+K30+L30<0,"outbound","inbound")) -> outbound | B30: 45498.006 | C30: sampling | D30: sample for Jay | E30: 106-0 | F30: LR23032101 | H30: =IF(ISBLANK(E30),"",_xlfn.XLOOKUP(E30,cannabis_log!C:C,cannabis_log!H:H,"",0,1)) -> extract_inhaled_bulk | I30: NA | J30: 0 | K30: -6.3 | L30: 0 | N30: gross | O30: 0
A31: =IF(ISBLANK(J31),"",IF(J31+K31+L31<0,"outbound","inbound")) -> outbound | B31: 45499 | C31: production | E31: 79-0 | F31: PR2410 | H31: =IF(ISBLANK(E31),"",_xlfn.XLOOKUP(E31,cannabis_log!C:C,cannabis_log!H:H,"",0,1)) -> driedflower_milled_bulk | I31: NA | J31: -1 | K31: -6320 | L31: 0 | N31: gross | O31: 0
A32: =IF(ISBLANK(J32),"",IF(J32+K32+L32<0,"outbound","inbound")) -> outbound | B32: 45502 | C32: production | D32: Packaging and labelling | E32: 84-0 | F32: NA | H32: =IF(ISBLANK(E32),"",_xlfn.XLOOKUP(E32,cannabis_log!C:C,cannabis_log!H:H,"",0,1)) -> extract_ingested_cased_BC | I32: 45482 | J32: -1 | K32: -15145 | L32: 0 | N32: gross | O32: 0
A33: =IF(ISBLANK(J33),"",IF(J33+K33+L33<0,"outbound","inbound")) -> outbound | B33: 45502.001 | C33: production | D33: Packaging and labelling | E33: 85-0 | F33: NA | H33: =IF(ISBLANK(E33),"",_xlfn.XLOOKUP(E33,cannabis_log!C:C,cannabis_log!H:H,"",0,1)) -> extract_ingested_cased_BC | I33: 45482 | J33: -1 | K33: -15115 | L33: 0 | N33: gross | O33: 0
A34: =IF(ISBLANK(J34),"",IF(J34+K34+L34<0,"outbound","inbound")) -> outbound | B34: 45502.001 | C34: production | D34: Packaging and labelling | E34: 86-0 | F34: NA | H34: =IF(ISBLANK(E34),"",_xlfn.XLOOKUP(E34,cannabis_log!C:C,cannabis_log!H:H,"",0,1)) -> extract_ingested_bulk | I34: 45482 | J34: -1 | K34: -14210 | L34: 0 | N34: gross | O34: 0
A35: =IF(ISBLANK(J35),"",IF(J35+K35+L35<0,"outbound","inbound")) -> outbound | B35: 45502.002 | C35: production | D35: Packaging and labelling | E35: 87-0 | F35: NA | H35: =IF(ISBLANK(E35),"",_xlfn.XLOOKUP(E35,cannabis_log!C:C,cannabis_log!H:H,"",0,1)) -> extract_ingested_bulk | I35: 45482 | J35: -1 | K35: -15770 | L35: 0 | N35: gross | O35: 0
A36: =IF(ISBLANK(J36),"",IF(J36+K36+L36<0,"outbound","inbound")) -> outbound | B36: 45503 | C36: shipment | D36: PO_02127 | E36: 78-0 | F36: TP24041202 | H36: =IF(ISBLANK(E36),"",_xlfn.XLOOKUP(E36,cannabis_log!C:C,cannabis_log!H:H,"",0,1)) -> topical_labelled | I36: 45423 | J36: -240 | K36: 0 | L36: -21120 | N36: net | O36: 88
A37: =IF(ISBLANK(J37),"",IF(J37+K37+L37<0,"outbound","inbound")) -> outbound | B37: 45503.001 | C37: shipment | D37: PO_DD2024072901 | E37: 104-0 | F37: PR21071201G1 | H37: =IF(ISBLANK(E37),"",_xlfn.XLOOKUP(E37,cannabis_log!C:C,cannabis_log!H:H,"",0,1)) -> preroll_labelled | I37: 44888 | J37: -36 | K37: 0 | L37: -36 | N37: net | O37: 1
A38: =IF(ISBLANK(J38),"",IF(J38+K38+L38<0,"outbound","inbound")) -> outbound | B38: 45503.001 | C38: shipment | D38: PO_DD2024072901 | E38: 121-0 | F38: PR2406F1P1 | H38: =IF(ISBLANK(E38),"",_xlfn.XLOOKUP(E38,cannabis_log!C:C,cannabis_log!H:H,"",0,1)) -> preroll_labelled | I38: 45462 | J38: -36 | K38: 0 | L38: -36 | N38: net | O38: 1
A39: =IF(ISBLANK(J39),"",IF(J39+K39+L39<0,"outbound","inbound")) -> outbound | B39: 45505.674 | C39: production | D39: Packaging and labelling | E39: 154-0 | F39: PR241001F5 | H39: =IF(ISBLANK(E39),"",_xlfn.XLOOKUP(E39,cannabis_log!C:C,cannabis_log!H:H,"",0,1)) -> preroll_bulk | I39: NA | J39: -268 | K39: 0 | L39: -134 | N39: net | O39: 0.5
A40: =IF(ISBLANK(J40),"",IF(J40+K40+L40<0,"outbound","inbound")) -> outbound | B40: 45510.706 | C40: reconciliation | D40: missing outbound record | E40: 79-0 | F40: PR2410 | H40: =IF(ISBLANK(E40),"",_xlfn.XLOOKUP(E40,cannabis_log!C:C,cannabis_log!H:H,"",0,1)) -> driedflower_milled_bulk | I40: NA | J40: -1 | K40: -3365 | L40: 0 | N40: gross | O40: 0
A41: =IF(ISBLANK(J41),"",IF(J41+K41+L41<0,"outbound","inbound")) -> outbound | B41: 45511.693 | C41: production | D41: repackaging and labeling for PO_22485 | E41: 8-0 | F41: 2022012401R1 | H41: =IF(ISBLANK(E41),"",_xlfn.XLOOKUP(E41,cannabis_log!C:C,cannabis_log!H:H,"",0,1)) -> driedflower_packaged | I41: 45100 | J41: -73 | K41: 0 | L41: -1022 | M41: need 1 more pouch to replenish 72 | N41: net | O41: 14
A42: =IF(ISBLANK(J42),"",IF(J42+K42+L42<0,"outbound","inbound")) -> outbound | B42: 45512.574 | C42: sampling | D42: sampling for Steve 80*5=400g | E42: 95-0 | F42: TP24041201 | H42: =IF(ISBLANK(E42),"",_xlfn.XLOOKUP(E42,cannabis_log!C:C,cannabis_log!H:H,"",0,1)) -> topical_bulk | I42: 45448 | J42: -1 | K42: -18260 | L42: 0 | N42: gross | O42: 0
A43: =IF(ISBLANK(J43),"",IF(J43+K43+L43<0,"outbound","inbound")) -> inbound | B43: 45512.629 | C43: storage | E43: 95-0 | F43: TP24041201 | H43: =IF(ISBLANK(E43),"",_xlfn.XLOOKUP(E43,cannabis_log!C:C,cannabis_log!H:H,"",0,1)) -> topical_bulk | I43: 45448 | J43: 1 | K43: 18260 | L43: 0 | N43: gross | O43: 0
A44: =IF(ISBLANK(J44),"",IF(J44+K44+L44<0,"outbound","inbound")) -> inbound | B44: 45513.485 | C44: storage | E44: 79-0 | F44: PR2410 | H44: =IF(ISBLANK(E44),"",_xlfn.XLOOKUP(E44,cannabis_log!C:C,cannabis_log!H:H,"",0,1)) -> driedflower_milled_bulk | I44: NA | J44: 1 | K44: 2065 | L44: 0 | N44: gross | O44: 0
A45: =IF(ISBLANK(J45),"",IF(J45+K45+L45<0,"outbound","inbound")) -> outbound | B45: 45513.566 | C45: production | E45: 71-0 | F45: 2022012401R1 | H45: =IF(ISBLANK(E45),"",_xlfn.XLOOKUP(E45,cannabis_log!C:C,cannabis_log!H:H,"",0,1)) -> driedflower_bulk | I45: 44686 | J45: -1 | K45: -603.6 | L45: 0 | N45: gross | O45: 0
A46: =IF(ISBLANK(J46),"",IF(J46+K46+L46<0,"outbound","inbound")) -> outbound | B46: 45513.566 | C46: production | D46: PO_DD2024080901 | E46: 155-0 | F46: PR241005F5P3 | H46: =IF(ISBLANK(E46),"",_xlfn.XLOOKUP(E46,cannabis_log!C:C,cannabis_log!H:H,"",0,1)) -> preroll_packaged | I46: 45541 | J46: -36 | K46: 0 | L46: -54 | N46: net | O46: 1.5
A47: =IF(ISBLANK(J47),"",IF(J47+K47+L47<0,"outbound","inbound")) -> outbound | B47: 45513.566 | C47: production | D47: PO_DD2024080901 | E47: 149-0 | F47: PR241104F5P3 | H47: =IF(ISBLANK(E47),"",_xlfn.XLOOKUP(E47,cannabis_log!C:C,cannabis_log!H:H,"",0,1)) -> preroll_labelled | I47: 45567 | J47: -36 | K47: 0 | L47: -54 | N47: net | O47: 1.5
A48: =IF(ISBLANK(J48),"",IF(J48+K48+L48<0,"outbound","inbound")) -> outbound | B48: 45513.566 | C48: production | D48: PO_DD2024080901 | E48: 152-0 | F48: PR241101F5P3 | H48: =IF(ISBLANK(E48),"",_xlfn.XLOOKUP(E48,cannabis_log!C:C,cannabis_log!H:H,"",0,1)) -> preroll_labelled | I48: 45543 | J48: -36 | K48: 0 | L48: -54 | N48: net | O48: 1.5
A49: =IF(ISBLANK(J49),"",IF(J49+K49+L49<0,"outbound","inbound")) -> outbound | B49: 45513.566 | C49: production | D49: relabel | E49: 148-0 | F49: PR240603F5P3 | H49: =IF(ISBLANK(E49),"",_xlfn.XLOOKUP(E49,cannabis_log!C:C,cannabis_log!H:H,"",0,1)) -> preroll_labelled | I49: 45491 | J49: -68 | K49: 0 | L49: -102 | N49: net | O49: 1.5
A50: =IF(ISBLANK(J50),"",IF(J50+K50+L50<0,"outbound","inbound")) -> outbound | B50: 45513.566 | C50: production | D50: relabel | E50: 170-0 | F50: PR241003F5P3 | H50: =IF(ISBLANK(E50),"",_xlfn.XLOOKUP(E50,cannabis_log!C:C,cannabis_log!H:H,"",0,1)) -> preroll_labelled | I50: 45511 | J50: -12 | K50: 0 | L50: -18 | N50: net | O50: 1.5
A51: =IF(ISBLANK(J51),"",IF(J51+K51+L51<0,"outbound","inbound")) -> inbound | B51: 45513.603 | C51: storage | E51: 148-0 | F51: PR240603F5P3 | H51: =IF(ISBLANK(E51),"",_xlfn.XLOOKUP(E51,cannabis_log!C:C,cannabis_log!H:H,"",0,1)) -> preroll_labelled | I51: 45491 | J51: 24 | K51: 0 | L51: 36 | N51: net | O51: 1.5
A52: =IF(ISBLANK(J52),"",IF(J52+K52+L52<0,"outbound","inbound")) -> inbound | B52: 45513.603 | C52: storage | E52: 170-0 | F52: PR241003F5P3 | H52: =IF(ISBLANK(E52),"",_xlfn.XLOOKUP(E52,cannabis_log!C:C,cannabis_log!H:H,"",0,1)) -> preroll_labelled | I52: 45511 | J52: 56 | K52: 0 | L52: 84 | N52: net | O52: 1.5
A53: =IF(ISBLANK(J53),"",IF(J53+K53+L53<0,"outbound","inbound")) -> outbound | B53: 45513.674 | C53: production | D53: relabel | E53: 155-0 | F53: PR241005F5P3 | H53: =IF(ISBLANK(E53),"",_xlfn.XLOOKUP(E53,cannabis_log!C:C,cannabis_log!H:H,"",0,1)) -> preroll_packaged | I53: 45541 | J53: -103 | K53: 0 | L53: -154.5 | N53: net | O53: 1.5
A54: =IF(ISBLANK(J54),"",IF(J54+K54+L54<0,"outbound","inbound")) -> inbound | B54: 45513.695 | C54: storage | D54: relabel | E54: 155-0 | F54: PR241005F5P3 | H54: =IF(ISBLANK(E54),"",_xlfn.XLOOKUP(E54,cannabis_log!C:C,cannabis_log!H:H,"",0,1)) -> preroll_packaged | I54: 45541 | J54: 103 | K54: 0 | L54: 154.5 | N54: net | O54: 1.5
A55: =IF(ISBLANK(J55),"",IF(J55+K55+L55<0,"outbound","inbound")) -> outbound | B55: 45516.392 | C55: production | D55: milling | E55: 179-0 | F55: 2024080701 | H55: =IF(ISBLANK(E55),"",_xlfn.XLOOKUP(E55,cannabis_log!C:C,cannabis_log!H:H,"",0,1)) -> driedflower_bulk | I55: NA | J55: -1 | K55: -588.2 | L55: 0 | N55: gross | O55: 0
A56: =IF(ISBLANK(J56),"",IF(J56+K56+L56<0,"outbound","inbound")) -> outbound | B56: 45516.392 | C56: production | D56: milling | E56: 180-0 | F56: 2024080701 | H56: =IF(ISBLANK(E56),"",_xlfn.XLOOKUP(E56,cannabis_log!C:C,cannabis_log!H:H,"",0,1)) -> driedflower_bulk | I56: NA | J56: -1 | K56: -1107.2 | L56: 0 | N56: gross | O56: 0
A57: =IF(ISBLANK(J57),"",IF(J57+K57+L57<0,"outbound","inbound")) -> outbound | B57: 45516.392 | C57: production | D57: milling | E57: 181-0 | F57: 2024080701 | H57: =IF(ISBLANK(E57),"",_xlfn.XLOOKUP(E57,cannabis_log!C:C,cannabis_log!H:H,"",0,1)) -> driedflower_bulk | I57: NA | J57: -1 | K57: -1097.6 | L57: 0 | N57: gross | O57: 0
A58: =IF(ISBLANK(J58),"",IF(J58+K58+L58<0,"outbound","inbound")) -> outbound | B58: 45516.392 | C58: production | D58: milling | E58: 178-0 | F58: 2024080701 | H58: =IF(ISBLANK(E58),"",_xlfn.XLOOKUP(E58,cannabis_log!C:C,cannabis_log!H:H,"",0,1)) -> driedflower_bulk | I58: NA | J58: -1 | K58: -1102 | L58: 0 | N58: gross | O58: 0
A59: =IF(ISBLANK(J59),"",IF(J59+K59+L59<0,"outbound","inbound")) -> outbound | B59: 45516.538 | C59: shipment | D59: PO_02127_Revised | E59: 78-0 | F59: TP24041202 | H59: =IF(ISBLANK(E59),"",_xlfn.XLOOKUP(E59,cannabis_log!C:C,cannabis_log!H:H,"",0,1)) -> topical_labelled | I59: 45423 | J59: -48 | K59: 0 | L59: -4224 | M59: plus 12 ON stamped rollons (RTV not counted yet) | N59: net | O59: 88
A60: =IF(ISBLANK(J60),"",IF(J60+K60+L60<0,"outbound","inbound")) -> outbound | B60: 45516.628 | C60: production | D60: Packaging 14 gelato | E60: 36-0 | F60: 2022012401R1 | H60: =IF(ISBLANK(E60),"",_xlfn.XLOOKUP(E60,cannabis_log!C:C,cannabis_log!H:H,"",0,1)) -> driedflower_bulk | I60: 44686 | J60: -1 | K60: -982.3 | L60: 0 | N60: gross | O60: 0
A61: =IF(ISBLANK(J61),"",IF(J61+K61+L61<0,"outbound","inbound")) -> outbound | B61: 45516.64 | C61: production | D61: Packaging 14 gelato | E61: 34-0 | F61: 2022012401R1 | H61: =IF(ISBLANK(E61),"",_xlfn.XLOOKUP(E61,cannabis_log!C:C,cannabis_log!H:H,"",0,1)) -> driedflower_bulk | I61: 44686 | J61: -1 | K61: -1025 | L61: 0 | N61: gross | O61: 0
A62: =IF(ISBLANK(J62),"",IF(J62+K62+L62<0,"outbound","inbound")) -> inbound | B62: 45516.64 | C62: storage | D62: Too much trims | E62: 36-0 | F62: 2022012401R1 | H62: =IF(ISBLANK(E62),"",_xlfn.XLOOKUP(E62,cannabis_log!C:C,cannabis_log!H:H,"",0,1)) -> driedflower_bulk | I62: 44686 | J62: 1 | K62: 985 | L62: 0 | N62: gross | O62: 0
A63: =IF(ISBLANK(J63),"",IF(J63+K63+L63<0,"outbound","inbound")) -> inbound | B63: 45516.658 | C63: storage | D63: Packaging 14 gelato | E63: 71-0 | F63: 2022012401R1 | H63: =IF(ISBLANK(E63),"",_xlfn.XLOOKUP(E63,cannabis_log!C:C,cannabis_log!H:H,"",0,1)) -> driedflower_bulk | I63: 44686 | J63: 1 | K63: 177.65 | L63: 0 | N63: gross | O63: 0
A64: =IF(ISBLANK(J64),"",IF(J64+K64+L64<0,"outbound","inbound")) -> inbound | B64: 45516.658 | C64: storage | D64: Packaging 14 gelato | E64: 34-0 | F64: 2022012401R1 | H64: =IF(ISBLANK(E64),"",_xlfn.XLOOKUP(E64,cannabis_log!C:C,cannabis_log!H:H,"",0,1)) -> driedflower_bulk | I64: 44686 | J64: 1 | K64: 770 | L64: 0 | N64: gross | O64: 0
A65: =IF(ISBLANK(J65),"",IF(J65+K65+L65<0,"outbound","inbound")) -> outbound | B65: 45517.386 | C65: production | D65: blueberry preroll | E65: 79-0 | F65: PR2410 | H65: =IF(ISBLANK(E65),"",_xlfn.XLOOKUP(E65,cannabis_log!C:C,cannabis_log!H:H,"",0,1)) -> driedflower_milled_bulk | I65: NA | J65: -1 | K65: -2065 | L65: 0 | N65: gross | O65: 0
A66: =IF(ISBLANK(J66),"",IF(J66+K66+L66<0,"outbound","inbound")) -> outbound | B66: 45518 | C66: sampling | D66: sample for Jay | E66: 211-0 | F66: EX23060701V30 | H66: =IF(ISBLANK(E66),"",_xlfn.XLOOKUP(E66,cannabis_log!C:C,cannabis_log!H:H,"",0,1)) -> extract_ingested_labelled | I66: 45094 | J66: -1 | K66: 0 | L66: -27.4 | N66: net | O66: 27.4
A67: =IF(ISBLANK(J67),"",IF(J67+K67+L67<0,"outbound","inbound")) -> outbound | B67: 45519.554 | C67: packaging | D67: AGLC_PO_71087 | E67: 198-0 | F67: PR241005F5 | H67: =IF(ISBLANK(E67),"",_xlfn.XLOOKUP(E67,cannabis_log!C:C,cannabis_log!H:H,"",0,1)) -> preroll_bulk | I67: NA | J67: -605 | K67: 0 | L67: -302.5 | N67: net | O67: 0.5
A68: =IF(ISBLANK(J68),"",IF(J68+K68+L68<0,"outbound","inbound")) -> outbound | B68: 45519.554 | C68: packaging | D68: AGLC_PO_71087 | E68: 190-0 | F68: PR241005F5 | H68: =IF(ISBLANK(E68),"",_xlfn.XLOOKUP(E68,cannabis_log!C:C,cannabis_log!H:H,"",0,1)) -> preroll_bulk | I68: NA | J68: -160 | K68: 0 | L68: -80 | N68: net | O68: 0.5
A69: =IF(ISBLANK(J69),"",IF(J69+K69+L69<0,"outbound","inbound")) -> outbound | B69: 45519.554 | C69: sampling | D69: AGLC_PO_71087 | E69: 91-0 | F69: EX24022301 | H69: =IF(ISBLANK(E69),"",_xlfn.XLOOKUP(E69,cannabis_log!C:C,cannabis_log!H:H,"",0,1)) -> extract_ingested_bulk | I69: 45345 | J69: -1 | K69: -4110 | L69: 0 | N69: gross | O69: 0
A70: =IF(ISBLANK(J70),"",IF(J70+K70+L70<0,"outbound","inbound")) -> outbound | B70: 45520.456 | C70: shipment | D70: MBLL_PO_370928 | E70: 105-0 | F70: EX23100401V30 | H70: =IF(ISBLANK(E70),"",_xlfn.XLOOKUP(E70,cannabis_log!C:C,cannabis_log!H:H,"",0,1)) -> extract_ingested_labelled | I70: 45488 | J70: -12 | K70: 0 | L70: -331.2 | N70: net | O70: 27.6
A71: =IF(ISBLANK(J71),"",IF(J71+K71+L71<0,"outbound","inbound")) -> inbound | B71: 45520.61 | C71: storage | D71: return from sampling | E71: 119-0 | F71: PR2407F5 | H71: =IF(ISBLANK(E71),"",_xlfn.XLOOKUP(E71,cannabis_log!C:C,cannabis_log!H:H,"",0,1)) -> preroll_bulk | I71: 45443 | J71: 745 | K71: 0 | L71: 372.5 | N71: net | O71: 0.5
A72: =IF(ISBLANK(J72),"",IF(J72+K72+L72<0,"outbound","inbound")) -> outbound | B72: 45520.623 | C72: shipment | D72: PO_369117 | E72: 148-0 | F72: PR240603F5P3 | H72: =IF(ISBLANK(E72),"",_xlfn.XLOOKUP(E72,cannabis_log!C:C,cannabis_log!H:H,"",0,1)) -> preroll_labelled | I72: 45491 | J72: -24 | K72: 0 | L72: -36 | N72: net | O72: 1.5
A73: =IF(ISBLANK(J73),"",IF(J73+K73+L73<0,"outbound","inbound")) -> outbound | B73: 45520.623 | C73: shipment | D73: PO_369117 | E73: 170-0 | F73: PR241003F5P3 | H73: =IF(ISBLANK(E73),"",_xlfn.XLOOKUP(E73,cannabis_log!C:C,cannabis_log!H:H,"",0,1)) -> preroll_labelled | I73: 45511 | J73: -12 | K73: 0 | L73: -18 | N73: net | O73: 1.5
A74: =IF(ISBLANK(J74),"",IF(J74+K74+L74<0,"outbound","inbound")) -> outbound | B74: 45520.623 | C74: shipment | D74: PO_369117 | E74: 184-0 | F74: PR241003F5P3 | H74: =IF(ISBLANK(E74),"",_xlfn.XLOOKUP(E74,cannabis_log!C:C,cannabis_log!H:H,"",0,1)) -> preroll_packaged | I74: NA | J74: -48 | K74: 0 | L74: -72 | N74: net | O74: 1.5
A75: =IF(ISBLANK(J75),"",IF(J75+K75+L75<0,"outbound","inbound")) -> outbound | B75: 45520.679 | C75: production | D75: labelling | E75: 184-0 | F75: PR241003F5P3 | H75: =IF(ISBLANK(E75),"",_xlfn.XLOOKUP(E75,cannabis_log!C:C,cannabis_log!H:H,"",0,1)) -> preroll_packaged | I75: NA | J75: -48 | K75: 0 | L75: -72 | N75: net | O75: 1.5
A76: =IF(ISBLANK(J76),"",IF(J76+K76+L76<0,"outbound","inbound")) -> outbound | B76: 45523.41 | C76: production | D76: AGLC_PO_71087 | E76: 106-0 | F76: LR23032101 | H76: =IF(ISBLANK(E76),"",_xlfn.XLOOKUP(E76,cannabis_log!C:C,cannabis_log!H:H,"",0,1)) -> extract_inhaled_bulk | I76: NA | J76: -1 | K76: -2253.7 | L76: 0 | N76: gross | O76: 0
A77: =IF(ISBLANK(J77),"",IF(J77+K77+L77<0,"outbound","inbound")) -> outbound | B77: 45523.41 | C77: production | D77: AGLC_PO_71087 | E77: 75-0 | F77: 2024022201 | H77: =IF(ISBLANK(E77),"",_xlfn.XLOOKUP(E77,cannabis_log!C:C,cannabis_log!H:H,"",0,1)) -> extract_distillate_bulk | I77: 45407 | J77: -1 | K77: -524.6 | L77: 0 | N77: gross | O77: 0
A78: =IF(ISBLANK(J78),"",IF(J78+K78+L78<0,"outbound","inbound")) -> outbound | B78: 45523.419 | C78: production | D78: AGLC_PO_71087 | E78: 184-0 | F78: PR241003F5P3 | H78: =IF(ISBLANK(E78),"",_xlfn.XLOOKUP(E78,cannabis_log!C:C,cannabis_log!H:H,"",0,1)) -> preroll_packaged | I78: NA | J78: -68 | K78: 0 | L78: -102 | N78: net | O78: 1.5
A79: =IF(ISBLANK(J79),"",IF(J79+K79+L79<0,"outbound","inbound")) -> outbound | B79: 45523.436 | C79: packaging | D79: AGLC_PO_71087 | E79: 186-0 | F79: PR241003F5P3 | H79: =IF(ISBLANK(E79),"",_xlfn.XLOOKUP(E79,cannabis_log!C:C,cannabis_log!H:H,"",0,1)) -> preroll_bulk | I79: NA | J79: -67 | K79: 0 | L79: -33.5 | N79: net | O79: 0.5
A80: =IF(ISBLANK(J80),"",IF(J80+K80+L80<0,"outbound","inbound")) -> outbound | B80: 45523.436 | C80: packaging | D80: AGLC_PO_71087 | E80: 188-0 | F80: PR241003F5P3 | H80: =IF(ISBLANK(E80),"",_xlfn.XLOOKUP(E80,cannabis_log!C:C,cannabis_log!H:H,"",0,1)) -> preroll_bulk | I80: NA | J80: -337 | K80: 0 | L80: -168.5 | N80: net | O80: 0.5
A81: =IF(ISBLANK(J81),"",IF(J81+K81+L81<0,"outbound","inbound")) -> outbound | B81: 45523.436 | C81: production | D81: AGLC_PO_71087 | E81: 245-0 | F81: 2024030601 | H81: =IF(ISBLANK(E81),"",_xlfn.XLOOKUP(E81,cannabis_log!C:C,cannabis_log!H:H,"",0,1)) -> extract_inhaled_bulk | I81: 45296 | J81: -1 | K81: -123.6 | L81: 0 | N81: gross | O81: 0
A82: =IF(ISBLANK(J82),"",IF(J82+K82+L82<0,"outbound","inbound")) -> outbound | B82: 45523.436 | C82: packaging | D82: AGLC_PO_71087 | E82: 159-0 | F82: PR241002F5 | H82: =IF(ISBLANK(E82),"",_xlfn.XLOOKUP(E82,cannabis_log!C:C,cannabis_log!H:H,"",0,1)) -> preroll_bulk | I82: NA | J82: -242 | K82: 0 | L82: -121 | N82: net | O82: 0.5
A83: =IF(ISBLANK(J83),"",IF(J83+K83+L83<0,"outbound","inbound")) -> inbound | B83: 45523.467 | C83: storage | E83: 106-0 | F83: LR23032101 | H83: =IF(ISBLANK(E83),"",_xlfn.XLOOKUP(E83,cannabis_log!C:C,cannabis_log!H:H,"",0,1)) -> extract_inhaled_bulk | I83: NA | J83: 1 | K83: 2055 | L83: 0 | N83: gross | O83: 0
A84: =IF(ISBLANK(J84),"",IF(J84+K84+L84<0,"outbound","inbound")) -> outbound | B84: 45523.551 | C84: production | D84: put into tube | E84: 193-0 | F84: PR241005F5 | H84: =IF(ISBLANK(E84),"",_xlfn.XLOOKUP(E84,cannabis_log!C:C,cannabis_log!H:H,"",0,1)) -> preroll_bulk | I84: NA | J84: -241 | K84: 0 | L84: -120.5 | N84: net | O84: 0.5
A85: =IF(ISBLANK(J85),"",IF(J85+K85+L85<0,"outbound","inbound")) -> outbound | B85: 45523.551 | C85: production | D85: put into tube | E85: 194-0 | F85: PR241005F5 | H85: =IF(ISBLANK(E85),"",_xlfn.XLOOKUP(E85,cannabis_log!C:C,cannabis_log!H:H,"",0,1)) -> preroll_bulk | I85: NA | J85: -479 | K85: 0 | L85: -239.5 | N85: net | O85: 0.5
A86: =IF(ISBLANK(J86),"",IF(J86+K86+L86<0,"outbound","inbound")) -> outbound | B86: 45523.551 | C86: production | D86: put into tube | E86: 195-0 | F86: PR241005F5 | H86: =IF(ISBLANK(E86),"",_xlfn.XLOOKUP(E86,cannabis_log!C:C,cannabis_log!H:H,"",0,1)) -> preroll_bulk | I86: NA | J86: -484 | K86: 0 | L86: -242 | N86: net | O86: 0.5
A87: =IF(ISBLANK(J87),"",IF(J87+K87+L87<0,"outbound","inbound")) -> outbound | B87: 45523.551 | C87: production | D87: put into tube | E87: 196-0 | F87: PR241005F5 | H87: =IF(ISBLANK(E87),"",_xlfn.XLOOKUP(E87,cannabis_log!C:C,cannabis_log!H:H,"",0,1)) -> preroll_bulk | I87: NA | J87: -358 | K87: 0 | L87: -179 | N87: net | O87: 0.5
A88: =IF(ISBLANK(J88),"",IF(J88+K88+L88<0,"outbound","inbound")) -> outbound | B88: 45523.551 | C88: production | D88: put into tube | E88: 197-0 | F88: PR241005F5 | H88: =IF(ISBLANK(E88),"",_xlfn.XLOOKUP(E88,cannabis_log!C:C,cannabis_log!H:H,"",0,1)) -> preroll_bulk | I88: NA | J88: -487 | K88: 0 | L88: -243.5 | N88: net | O88: 0.5
A89: =IF(ISBLANK(J89),"",IF(J89+K89+L89<0,"outbound","inbound")) -> outbound | B89: 45523.551 | C89: production | D89: put into tube | E89: 199-0 | F89: PR241005F5 | H89: =IF(ISBLANK(E89),"",_xlfn.XLOOKUP(E89,cannabis_log!C:C,cannabis_log!H:H,"",0,1)) -> preroll_bulk | I89: NA | J89: -240 | K89: 0 | L89: -120 | N89: net | O89: 0.5
A90: =IF(ISBLANK(J90),"",IF(J90+K90+L90<0,"outbound","inbound")) -> outbound | B90: 45523.551 | C90: production | D90: put into tube, PO_373529 | E90: 160-0 | F90: PR241002F5 | H90: =IF(ISBLANK(E90),"",_xlfn.XLOOKUP(E90,cannabis_log!C:C,cannabis_log!H:H,"",0,1)) -> preroll_bulk | I90: NA | J90: -211 | K90: 0 | L90: -105.5 | N90: net | O90: 0.5
A91: =IF(ISBLANK(J91),"",IF(J91+K91+L91<0,"outbound","inbound")) -> outbound | B91: 45523.551 | C91: production | D91: put into tube, PO_373529 | E91: 161-0 | F91: PR241002F5 | H91: =IF(ISBLANK(E91),"",_xlfn.XLOOKUP(E91,cannabis_log!C:C,cannabis_log!H:H,"",0,1)) -> preroll_bulk | I91: NA | J91: -242 | K91: 0 | L91: -121 | N91: net | O91: 0.5
A92: =IF(ISBLANK(J92),"",IF(J92+K92+L92<0,"outbound","inbound")) -> outbound | B92: 45523.551 | C92: production | D92: put into tube, PO_373464 | E92: 189-0 | F92: PR241003F5P3 | H92: =IF(ISBLANK(E92),"",_xlfn.XLOOKUP(E92,cannabis_log!C:C,cannabis_log!H:H,"",0,1)) -> preroll_bulk | I92: NA | J92: -500 | K92: 0 | L92: -250 | N92: net | O92: 0.5
A93: =IF(ISBLANK(J93),"",IF(J93+K93+L93<0,"outbound","inbound")) -> outbound | B93: 45523.551 | C93: production | D93: put into tube, PO_373464 | E93: 187-0 | F93: PR241003F5P3 | H93: =IF(ISBLANK(E93),"",_xlfn.XLOOKUP(E93,cannabis_log!C:C,cannabis_log!H:H,"",0,1)) -> preroll_bulk | I93: NA | J93: -507 | K93: 0 | L93: -253.5 | N93: net | O93: 0.5
A94: =IF(ISBLANK(J94),"",IF(J94+K94+L94<0,"outbound","inbound")) -> outbound | B94: 45523.551 | C94: production | D94: relabeling | E94: 146-0 | F94: PR241002F5P3 | H94: =IF(ISBLANK(E94),"",_xlfn.XLOOKUP(E94,cannabis_log!C:C,cannabis_log!H:H,"",0,1)) -> preroll_labelled | I94: 45497 | J94: -160 | K94: 0 | L94: -240 | N94: net | O94: 1.5
A95: =IF(ISBLANK(J95),"",IF(J95+K95+L95<0,"outbound","inbound")) -> outbound | B95: 45523.565 | C95: shipment | D95: PO_372038 | E95: 150-0 | F95: PR2407F5P3 | H95: =IF(ISBLANK(E95),"",_xlfn.XLOOKUP(E95,cannabis_log!C:C,cannabis_log!H:H,"",0,1)) -> preroll_labelled | I95: 45498 | J95: -24 | K95: 0 | L95: -36 | N95: net | O95: 1.5
A96: =IF(ISBLANK(J96),"",IF(J96+K96+L96<0,"outbound","inbound")) -> outbound | B96: 45523.565 | C96: shipment | D96: PO_372049 | E96: 152-0 | F96: PR241101F5P3 | H96: =IF(ISBLANK(E96),"",_xlfn.XLOOKUP(E96,cannabis_log!C:C,cannabis_log!H:H,"",0,1)) -> preroll_labelled | I96: 45543 | J96: -12 | K96: 0 | L96: -18 | N96: net | O96: 1.5
A97: =IF(ISBLANK(J97),"",IF(J97+K97+L97<0,"outbound","inbound")) -> outbound | B97: 45523.565 | C97: shipment | D97: PO_372049 | E97: 150-0 | F97: PR2407F5P3 | H97: =IF(ISBLANK(E97),"",_xlfn.XLOOKUP(E97,cannabis_log!C:C,cannabis_log!H:H,"",0,1)) -> preroll_labelled | I97: 45498 | J97: -12 | K97: 0 | L97: -18 | N97: net | O97: 1.5
A98: =IF(ISBLANK(J98),"",IF(J98+K98+L98<0,"outbound","inbound")) -> outbound | B98: 45523.594 | C98: shipment | D98: PO_DD2024081601 | E98: 157-0 | F98: EX24010301V30 | H98: =IF(ISBLANK(E98),"",_xlfn.XLOOKUP(E98,cannabis_log!C:C,cannabis_log!H:H,"",0,1)) -> extract_ingested_labelled | I98: 45307 | J98: -12 | K98: 0 | L98: -327.6 | N98: net | O98: 27.3
A99: =IF(ISBLANK(J99),"",IF(J99+K99+L99<0,"outbound","inbound")) -> outbound | B99: 45523.594 | C99: shipment | D99: PO_DD2024081601 | E99: 105-0 | F99: EX23100401V30 | H99: =IF(ISBLANK(E99),"",_xlfn.XLOOKUP(E99,cannabis_log!C:C,cannabis_log!H:H,"",0,1)) -> extract_ingested_labelled | I99: 45488 | J99: -12 | K99: 0 | L99: -331.2 | N99: net | O99: 27.6
A100: =IF(ISBLANK(J100),"",IF(J100+K100+L100<0,"outbound","inbound")) -> outbound | B100: 45523.594 | C100: shipment | D100: PO_DD2024081601 | E100: 152-0 | F100: PR241101F5P3 | H100: =IF(ISBLANK(E100),"",_xlfn.XLOOKUP(E100,cannabis_log!C:C,cannabis_log!H:H,"",0,1)) -> preroll_labelled | I100: 45543 | J100: -12 | K100: 0 | L100: -18 | N100: net | O100: 1.5
...

Sheet planned_shipment
A1: Sequence | B1: Payment status | C1: Status | D1: po_shipdate | E1: Appointment date | F1: Appointment # | G1: Tracking_number | H1: Released (Y/N) | I1: PO_date | J1: sales_stream | K1: Shipping date | L1: distributor_stream | M1: po_number | N1: po_and_line | O1: po_line | P1: Product_name | Q1: ProductLot# | R1: Excised(Yes/No) | S1: Excisedfor | T1: packondate_labelled | U1: quantity_unit | V1: unitpercase | W1: cases | X1: cannabis_netweight_gram | Y1: productGTIN | Z1: customerSKU | AA1: ProductWeightIdentifier | AB1: Pre-excisedorDutyPaidProduct? | AC1: shipto | AD1: address | AE1: city | AF1: province | AG1: billto | AH1: unitprice | AI1: Partner | AJ1: Product Price | AK1: PO_price
A2: 2248 | B2: Not Applicable | C2: Shipped | E2: 45481 | F2: 47693 | H2: N | I2: Sent | J2: OCS | K2: 45474 | L2: Provincial Distribution | N2: =Table26[[#This Row],[po_number]]&"-"&Table26[[#This Row],[po_line]] -> -1 | O2: 1 | R2: No | U2: 12 | V2: 12 | W2: =IFERROR(U2/V2, "") -> 1 | X2: =IFERROR($AA2*$U2, "") | AA2: {=IF(P2="", "", _xlfn.XLOOKUP(P2,#REF!,#REF!,NA,0,-1))} | AC2: Ontario Cannabis Store | AD2: =IF($AC2="","",_xlfn.XLOOKUP($AC2,'[2]Client Info'!$C$2:$C$2535,'[2]Client Info'!$D$2:$D$2535)) -> 55 Quarterman Road | AE2: =IF($AC2="","",_xlfn.XLOOKUP($AC2,'[2]Client Info'!$C$2:$C$2715,'[2]Client Info'!$E$2:$E$2715)) -> Guelph | AF2: =IF($AC2="","",_xlfn.XLOOKUP($AC2,'[2]Client Info'!$C$2:$C$2715,'[2]Client Info'!$F$2:$F$2715)) -> ON | AG2: Ontario Cannabis Store | AI2: =_xlfn.XLOOKUP(Table26[[#This Row],[customerSKU]],customerSKU!G:G,customerSKU!O:O,"not found",0,1) -> not found | AJ2: =Table26[[#This Row],[unitprice]]*Table26[[#This Row],[quantity_unit]] -> 0 | AK2: {=_xlfn.IFS(Table26[[#This Row],[sales_stream]]="BCDD",Table26[[#This Row],[Product Price]]*1.05,Table26[[#This Row],[sales_stream]]="MBLL_redistribution",Table26[[#This Row],[Product Price]]*1.05,Table26[[#This Row],[sales_stream]]="MBLL",Table26[[#This Row],[Product Price]]*1.05)} -> #N/A
A3: 2247 | B3: Paid | C3: Shipped | I3: Sent | J3: CANNMART | K3: 45475 | L3: Provincial Distribution | N3: =Table26[[#This Row],[po_number]]&"-"&Table26[[#This Row],[po_line]] -> -1 | O3: 1 | Q3: PR2405F7P3-2 | R3: Yes | S3: AB | T3: 45460 | U3: =75*12 -> 900 | V3: 12 | W3: =IFERROR(U3/V3, "") -> 75 | X3: =IFERROR($AA3*$U3, "") | Y3: 00842572002453 | Z3: 4809951 | AA3: {=IF(P3="", "", _xlfn.XLOOKUP(P3,#REF!,#REF!,NA,0,-1))} | AC3: AGLC | AD3: =IF($AC3="","",_xlfn.XLOOKUP($AC3,'[2]Client Info'!$C$2:$C$2535,'[2]Client Info'!$D$2:$D$2535)) -> 12622-184 Street NW | AE3: =IF($AC3="","",_xlfn.XLOOKUP($AC3,'[2]Client Info'!$C$2:$C$2715,'[2]Client Info'!$E$2:$E$2715)) -> Edmonton | AF3: =IF($AC3="","",_xlfn.XLOOKUP($AC3,'[2]Client Info'!$C$2:$C$2715,'[2]Client Info'!$F$2:$F$2715)) -> AB | AG3: CannMart Inc | AH3: =140.28/12 -> 11.69 | AI3: =_xlfn.XLOOKUP(Table26[[#This Row],[customerSKU]],customerSKU!G:G,customerSKU!O:O,"not found",0,1) -> not found | AJ3: =Table26[[#This Row],[unitprice]]*Table26[[#This Row],[quantity_unit]] -> 10521 | AK3: {=_xlfn.IFS(Table26[[#This Row],[sales_stream]]="BCDD",Table26[[#This Row],[Product Price]]*1.05,Table26[[#This Row],[sales_stream]]="MBLL_redistribution",Table26[[#This Row],[Product Price]]*1.05,Table26[[#This Row],[sales_stream]]="MBLL",Table26[[#This Row],[Product Price]]*1.05)} -> #N/A
A4: 2246 | B4: Not Applicable | C4: Shipped | E4: 45488 | F4: 47694 | I4: Sent | J4: OCS | K4: 45476 | L4: Provincial Distribution | N4: =Table26[[#This Row],[po_number]]&"-"&Table26[[#This Row],[po_line]] -> -1 | O4: 1 | Q4: EX24061401V30 | R4: No | S4: PO_20250729-WD-GVA | T4: 45467 | U4: 48 | V4: 12 | W4: =IFERROR(U4/V4, "") -> 4 | X4: =IFERROR($AA4*$U4, "") | Y4: 00877579002601 | Z4: 110184 | AA4: {=IF(P4="", "", _xlfn.XLOOKUP(P4,#REF!,#REF!,NA,0,-1))} | AC4: Ontario Cannabis Store | AD4: =IF($AC4="","",_xlfn.XLOOKUP($AC4,'[2]Client Info'!$C$2:$C$2535,'[2]Client Info'!$D$2:$D$2535)) -> 55 Quarterman Road | AE4: =IF($AC4="","",_xlfn.XLOOKUP($AC4,'[2]Client Info'!$C$2:$C$2715,'[2]Client Info'!$E$2:$E$2715)) -> Guelph | AF4: =IF($AC4="","",_xlfn.XLOOKUP($AC4,'[2]Client Info'!$C$2:$C$2715,'[2]Client Info'!$F$2:$F$2715)) -> ON | AG4: Ontario Cannabis Store | AH4: 19.15 | AI4: =_xlfn.XLOOKUP(Table26[[#This Row],[customerSKU]],customerSKU!G:G,customerSKU!O:O,"not found",0,1) -> not found | AJ4: =Table26[[#This Row],[unitprice]]*Table26[[#This Row],[quantity_unit]] -> 919.2 | AK4: {=_xlfn.IFS(Table26[[#This Row],[sales_stream]]="BCDD",Table26[[#This Row],[Product Price]]*1.05,Table26[[#This Row],[sales_stream]]="MBLL_redistribution",Table26[[#This Row],[Product Price]]*1.05,Table26[[#This Row],[sales_stream]]="MBLL",Table26[[#This Row],[Product Price]]*1.05)} -> #N/A
A5: 2245 | B5: Not Applicable | C5: Shipped | E5: 45498 | I5: Sent | J5: NSLC | K5: 45477 | L5: Provincial Distribution | N5: =Table26[[#This Row],[po_number]]&"-"&Table26[[#This Row],[po_line]] -> -1 | O5: 1 | Q5: TP24041202 | R5: Yes | S5: NS | T5: 45423 | U5: =15*12 -> 180 | V5: 12 | W5: =IFERROR(U5/V5, "") -> 15 | X5: =IFERROR($AA5*$U5, "") | Y5: 00877579001564 | AA5: {=IF(P5="", "", _xlfn.XLOOKUP(P5,#REF!,#REF!,NA,0,-1))} | AC5: NSLC | AD5: =IF($AC5="","",_xlfn.XLOOKUP($AC5,'[2]Client Info'!$C$2:$C$2535,'[2]Client Info'!$D$2:$D$2535)) -> 80 Guilford Ave | AE5: =IF($AC5="","",_xlfn.XLOOKUP($AC5,'[2]Client Info'!$C$2:$C$2715,'[2]Client Info'!$E$2:$E$2715)) -> Dartmouth | AF5: =IF($AC5="","",_xlfn.XLOOKUP($AC5,'[2]Client Info'!$C$2:$C$2715,'[2]Client Info'!$F$2:$F$2715)) -> NS | AG5: NSLC | AH5: =198/12 -> 16.5 | AI5: =_xlfn.XLOOKUP(Table26[[#This Row],[customerSKU]],customerSKU!G:G,customerSKU!O:O,"not found",0,1) -> not found | AJ5: =Table26[[#This Row],[unitprice]]*Table26[[#This Row],[quantity_unit]] -> 2970 | AK5: {=_xlfn.IFS(Table26[[#This Row],[sales_stream]]="BCDD",Table26[[#This Row],[Product Price]]*1.05,Table26[[#This Row],[sales_stream]]="MBLL_redistribution",Table26[[#This Row],[Product Price]]*1.05,Table26[[#This Row],[sales_stream]]="MBLL",Table26[[#This Row],[Product Price]]*1.05)} -> #N/A
A6: 2241 | B6: Not Applicable | C6: cancelled_PO | D6: 45491 | F6: Cancelled | I6: Sent | J6: OCS | K6: 45481 | L6: Provincial Distribution | N6: =Table26[[#This Row],[po_number]]&"-"&Table26[[#This Row],[po_line]] -> -1 | O6: 1 | Q6: EX24061401V30 | R6: No | T6: 45467 | U6: 12 | V6: 12 | W6: =IFERROR(U6/V6, "") -> 1 | X6: =IFERROR($AA6*$U6, "") | Y6: 00877579002601 | Z6: 110184 | AA6: {=IF(P6="", "", _xlfn.XLOOKUP(P6,#REF!,#REF!,NA,0,-1))} | AC6: Ontario Cannabis Store | AD6: =IF($AC6="","",_xlfn.XLOOKUP($AC6,'Client Info'!$C$2:$C$2497,'Client Info'!$D$2:$D$2497,"",0,1)) | AE6: =IF($AC6="","",_xlfn.XLOOKUP($AC6,'Client Info'!$C$2:$C$2677,'Client Info'!$E$2:$E$2677,"",)) | AF6: =IF($AC6="","",_xlfn.XLOOKUP($AC6,'Client Info'!$C$2:$C$2677,'Client Info'!$F$2:$F$2677,"",0,1)) | AG6: Ontario Cannabis Store | AH6: 19.15 | AI6: =_xlfn.XLOOKUP(Table26[[#This Row],[customerSKU]],customerSKU!G:G,customerSKU!O:O,"not found",0,1) -> not found | AJ6: =Table26[[#This Row],[unitprice]]*Table26[[#This Row],[quantity_unit]] -> 229.8 | AK6: {=_xlfn.IFS(Table26[[#This Row],[sales_stream]]="BCDD",Table26[[#This Row],[Product Price]]*1.05,Table26[[#This Row],[sales_stream]]="MBLL_redistribution",Table26[[#This Row],[Product Price]]*1.05,Table26[[#This Row],[sales_stream]]="MBLL",Table26[[#This Row],[Product Price]]*1.05)} -> #N/A
A7: 2242 | B7: Not Applicable | C7: Shipped | D7: 45503 | E7: 45503 | F7: 48881 | I7: Sent | J7: OCS | K7: 45481 | L7: Provincial Distribution | N7: =Table26[[#This Row],[po_number]]&"-"&Table26[[#This Row],[po_line]] -> -1 | O7: 1 | Q7: EX24061401V30 | R7: No | T7: 45467 | U7: 24 | V7: 12 | W7: =IFERROR(U7/V7, "") -> 2 | X7: =IFERROR($AA7*$U7, "") | Y7: 00877579002601 | Z7: 110184 | AA7: {=IF(P7="", "", _xlfn.XLOOKUP(P7,#REF!,#REF!,NA,0,-1))} | AC7: Ontario Cannabis Store | AD7: =IF($AC7="","",_xlfn.XLOOKUP($AC7,'[2]Client Info'!$C$2:$C$2535,'[2]Client Info'!$D$2:$D$2535)) -> 55 Quarterman Road | AE7: =IF($AC7="","",_xlfn.XLOOKUP($AC7,'[2]Client Info'!$C$2:$C$2715,'[2]Client Info'!$E$2:$E$2715)) -> Guelph | AF7: =IF($AC7="","",_xlfn.XLOOKUP($AC7,'[2]Client Info'!$C$2:$C$2715,'[2]Client Info'!$F$2:$F$2715)) -> ON | AG7: Ontario Cannabis Store | AH7: 19.15 | AI7: =_xlfn.XLOOKUP(Table26[[#This Row],[customerSKU]],customerSKU!G:G,customerSKU!O:O,"not found",0,1) -> not found | AJ7: =Table26[[#This Row],[unitprice]]*Table26[[#This Row],[quantity_unit]] -> 459.6 | AK7: {=_xlfn.IFS(Table26[[#This Row],[sales_stream]]="BCDD",Table26[[#This Row],[Product Price]]*1.05,Table26[[#This Row],[sales_stream]]="MBLL_redistribution",Table26[[#This Row],[Product Price]]*1.05,Table26[[#This Row],[sales_stream]]="MBLL",Table26[[#This Row],[Product Price]]*1.05)} -> #N/A
A8: 2243 | B8: Paid | C8: Shipped | D8: 45481 | E8: 45481 | I8: Sent | J8: BCDD | K8: 45481 | L8: Retail | N8: =Table26[[#This Row],[po_number]]&"-"&Table26[[#This Row],[po_line]] -> -1 | O8: 1 | Q8: PR2406F1P3 | R8: Yes | S8: BC | T8: 45448 | U8: 24 | V8: 12 | W8: =IFERROR(U8/V8, "") -> 2 | X8: =IFERROR($AA8*$U8, "") | AA8: {=IF(P8="", "", _xlfn.XLOOKUP(P8,#REF!,#REF!,NA,0,-1))} | AC8: CITY CANNABIS CO | AD8: =IF($AC8="","",_xlfn.XLOOKUP($AC8,'[2]Client Info'!$C$2:$C$2535,'[2]Client Info'!$D$2:$D$2535)) -> 16A-215 Port Augusta St | AE8: =IF($AC8="","",_xlfn.XLOOKUP($AC8,'[2]Client Info'!$C$2:$C$2715,'[2]Client Info'!$E$2:$E$2715)) -> Comox | AF8: =IF($AC8="","",_xlfn.XLOOKUP($AC8,'[2]Client Info'!$C$2:$C$2715,'[2]Client Info'!$F$2:$F$2715)) -> BC | AG8: CITY CANNABIS CO | AH8: =101.04/12 -> 8.42 | AI8: =_xlfn.XLOOKUP(Table26[[#This Row],[customerSKU]],customerSKU!G:G,customerSKU!O:O,"not found",0,1) -> not found | AJ8: =Table26[[#This Row],[unitprice]]*Table26[[#This Row],[quantity_unit]] -> 202.08 | AK8: {=_xlfn.IFS(Table26[[#This Row],[sales_stream]]="BCDD",Table26[[#This Row],[Product Price]]*1.05,Table26[[#This Row],[sales_stream]]="MBLL_redistribution",Table26[[#This Row],[Product Price]]*1.05,Table26[[#This Row],[sales_stream]]="MBLL",Table26[[#This Row],[Product Price]]*1.05)} -> 212.184
A9: 2244 | B9: Paid | C9: Shipped | D9: 45481 | E9: 45481 | I9: Sent | J9: BCDD | K9: 45481 | L9: Retail | N9: =Table26[[#This Row],[po_number]]&"-"&Table26[[#This Row],[po_line]] -> -2 | O9: 2 | Q9: PR2407F5P3 | R9: Yes | S9: BC | T9: 45447 | U9: 24 | V9: 12 | W9: =IFERROR(U9/V9, "") -> 2 | X9: =IFERROR($AA9*$U9, "") | AA9: {=IF(P9="", "", _xlfn.XLOOKUP(P9,#REF!,#REF!,NA,0,-1))} | AC9: CITY CANNABIS CO | AD9: =IF($AC9="","",_xlfn.XLOOKUP($AC9,'[2]Client Info'!$C$2:$C$2535,'[2]Client Info'!$D$2:$D$2535)) -> 16A-215 Port Augusta St | AE9: =IF($AC9="","",_xlfn.XLOOKUP($AC9,'[2]Client Info'!$C$2:$C$2715,'[2]Client Info'!$E$2:$E$2715)) -> Comox | AF9: =IF($AC9="","",_xlfn.XLOOKUP($AC9,'[2]Client Info'!$C$2:$C$2715,'[2]Client Info'!$F$2:$F$2715)) -> BC | AG9: CITY CANNABIS CO | AH9: =100.08/12 -> 8.34 | AI9: =_xlfn.XLOOKUP(Table26[[#This Row],[customerSKU]],customerSKU!G:G,customerSKU!O:O,"not found",0,1) -> not found | AJ9: =Table26[[#This Row],[unitprice]]*Table26[[#This Row],[quantity_unit]] -> 200.16 | AK9: {=_xlfn.IFS(Table26[[#This Row],[sales_stream]]="BCDD",Table26[[#This Row],[Product Price]]*1.05,Table26[[#This Row],[sales_stream]]="MBLL_redistribution",Table26[[#This Row],[Product Price]]*1.05,Table26[[#This Row],[sales_stream]]="MBLL",Table26[[#This Row],[Product Price]]*1.05)} -> 210.168
A10: 2238 | B10: Not Applicable | C10: Shipped | D10: 45495 | E10: 45495 | H10: N | I10: Sent | J10: AGLC | K10: 45482 | L10: Provincial Distribution | N10: =Table26[[#This Row],[po_number]]&"-"&Table26[[#This Row],[po_line]] -> -1 | O10: 1 | Q10: LR23032101 | R10: Yes | S10: AB | T10: 45478 | U10: 120 | V10: 6 | W10: =IFERROR(U10/V10, "") -> 20 | X10: =IFERROR($AA10*$U10, "") | Y10: 00877579002465 | Z10: CNB-10505190 | AA10: {=IF(P10="", "", _xlfn.XLOOKUP(P10,#REF!,#REF!,NA,0,-1))} | AC10: AGLC | AD10: =IF($AC10="","",_xlfn.XLOOKUP($AC10,'[2]Client Info'!$C$2:$C$2535,'[2]Client Info'!$D$2:$D$2535)) -> 12622-184 Street NW | AE10: =IF($AC10="","",_xlfn.XLOOKUP($AC10,'[2]Client Info'!$C$2:$C$2715,'[2]Client Info'!$E$2:$E$2715)) -> Edmonton | AF10: =IF($AC10="","",_xlfn.XLOOKUP($AC10,'[2]Client Info'!$C$2:$C$2715,'[2]Client Info'!$F$2:$F$2715)) -> AB | AG10: AGLC | AH10: 21.99 | AI10: =_xlfn.XLOOKUP(Table26[[#This Row],[customerSKU]],customerSKU!G:G,customerSKU!O:O,"not found",0,1) -> not found | AJ10: =Table26[[#This Row],[unitprice]]*Table26[[#This Row],[quantity_unit]] -> 2638.8 | AK10: {=_xlfn.IFS(Table26[[#This Row],[sales_stream]]="BCDD",Table26[[#This Row],[Product Price]]*1.05,Table26[[#This Row],[sales_stream]]="MBLL_redistribution",Table26[[#This Row],[Product Price]]*1.05,Table26[[#This Row],[sales_stream]]="MBLL",Table26[[#This Row],[Product Price]]*1.05)} -> #N/A
A11: 2239 | B11: Not Applicable | C11: Shipped | D11: 45495 | E11: 45495 | H11: N | I11: Sent | J11: AGLC | K11: 45482 | L11: Provincial Distribution | N11: =Table26[[#This Row],[po_number]]&"-"&Table26[[#This Row],[po_line]] -> -2 | O11: 2 | Q11: PR2303IN01F5P3 | R11: Yes | S11: AB | T11: 45478 | U11: 600 | V11: 6 | W11: =IFERROR(U11/V11, "") -> 100 | X11: =IFERROR($AA11*$U11, "") | Y11: 00877579003998 | Z11: CNB-10510203 | AA11: {=IF(P11="", "", _xlfn.XLOOKUP(P11,#REF!,#REF!,NA,0,-1))} | AC11: AGLC | AD11: =IF($AC11="","",_xlfn.XLOOKUP($AC11,'[2]Client Info'!$C$2:$C$2535,'[2]Client Info'!$D$2:$D$2535)) -> 12622-184 Street NW | AE11: =IF($AC11="","",_xlfn.XLOOKUP($AC11,'[2]Client Info'!$C$2:$C$2715,'[2]Client Info'!$E$2:$E$2715)) -> Edmonton | AF11: =IF($AC11="","",_xlfn.XLOOKUP($AC11,'[2]Client Info'!$C$2:$C$2715,'[2]Client Info'!$F$2:$F$2715)) -> AB | AG11: AGLC | AH11: 21.99 | AI11: =_xlfn.XLOOKUP(Table26[[#This Row],[customerSKU]],customerSKU!G:G,customerSKU!O:O,"not found",0,1) -> not found | AJ11: =Table26[[#This Row],[unitprice]]*Table26[[#This Row],[quantity_unit]] -> 13194 | AK11: {=_xlfn.IFS(Table26[[#This Row],[sales_stream]]="BCDD",Table26[[#This Row],[Product Price]]*1.05,Table26[[#This Row],[sales_stream]]="MBLL_redistribution",Table26[[#This Row],[Product Price]]*1.05,Table26[[#This Row],[sales_stream]]="MBLL",Table26[[#This Row],[Product Price]]*1.05)} -> #N/A
A12: 2240 | B12: Not Applicable | C12: Shipped | D12: 45495 | E12: 45495 | H12: N | I12: Sent | J12: AGLC | K12: 45482 | L12: Provincial Distribution | N12: =Table26[[#This Row],[po_number]]&"-"&Table26[[#This Row],[po_line]] -> -3 | O12: 3 | Q12: PR2303IN02F5P3 | R12: Yes | S12: AB | T12: 45478 | U12: 600 | V12: 6 | W12: =IFERROR(U12/V12, "") -> 100 | X12: =IFERROR($AA12*$U12, "") | Y12: 00877579004018 | Z12: CNB-10510204 | AA12: {=IF(P12="", "", _xlfn.XLOOKUP(P12,#REF!,#REF!,NA,0,-1))} | AC12: AGLC | AD12: =IF($AC12="","",_xlfn.XLOOKUP($AC12,'[2]Client Info'!$C$2:$C$2535,'[2]Client Info'!$D$2:$D$2535)) -> 12622-184 Street NW | AE12: =IF($AC12="","",_xlfn.XLOOKUP($AC12,'[2]Client Info'!$C$2:$C$2715,'[2]Client Info'!$E$2:$E$2715)) -> Edmonton | AF12: =IF($AC12="","",_xlfn.XLOOKUP($AC12,'[2]Client Info'!$C$2:$C$2715,'[2]Client Info'!$F$2:$F$2715)) -> AB | AG12: AGLC | AH12: 20.99 | AI12: =_xlfn.XLOOKUP(Table26[[#This Row],[customerSKU]],customerSKU!G:G,customerSKU!O:O,"not found",0,1) -> not found | AJ12: =Table26[[#This Row],[unitprice]]*Table26[[#This Row],[quantity_unit]] -> 12594 | AK12: {=_xlfn.IFS(Table26[[#This Row],[sales_stream]]="BCDD",Table26[[#This Row],[Product Price]]*1.05,Table26[[#This Row],[sales_stream]]="MBLL_redistribution",Table26[[#This Row],[Product Price]]*1.05,Table26[[#This Row],[sales_stream]]="MBLL",Table26[[#This Row],[Product Price]]*1.05)} -> #N/A
A13: 2236 | B13: Paid | C13: Shipped | D13: 45485 | I13: Sent | J13: BCDD | K13: 45485 | L13: Retail | N13: =Table26[[#This Row],[po_number]]&"-"&Table26[[#This Row],[po_line]] -> -1 | O13: 1 | Q13: PR2406F1P3 | R13: Yes | S13: BC | T13: 45448 | U13: 12 | V13: 12 | W13: =IFERROR(U13/V13, "") -> 1 | X13: =IFERROR($AA13*$U13, "") | Y13: 00877579003219 | AA13: {=IF(P13="", "", _xlfn.XLOOKUP(P13,#REF!,#REF!,NA,0,-1))} | AC13: City Cannabis | AD13: =IF($AC13="","",_xlfn.XLOOKUP($AC13,'[2]Client Info'!$C$2:$C$2535,'[2]Client Info'!$D$2:$D$2535)) -> #N/A | AE13: =IF($AC13="","",_xlfn.XLOOKUP($AC13,'[2]Client Info'!$C$2:$C$2715,'[2]Client Info'!$E$2:$E$2715)) -> #N/A | AF13: =IF($AC13="","",_xlfn.XLOOKUP($AC13,'[2]Client Info'!$C$2:$C$2715,'[2]Client Info'!$F$2:$F$2715)) -> #N/A | AG13: City Cannabis | AI13: =_xlfn.XLOOKUP(Table26[[#This Row],[customerSKU]],customerSKU!G:G,customerSKU!O:O,"not found",0,1) -> not found | AJ13: =Table26[[#This Row],[unitprice]]*Table26[[#This Row],[quantity_unit]] -> 0 | AK13: {=_xlfn.IFS(Table26[[#This Row],[sales_stream]]="BCDD",Table26[[#This Row],[Product Price]]*1.05,Table26[[#This Row],[sales_stream]]="MBLL_redistribution",Table26[[#This Row],[Product Price]]*1.05,Table26[[#This Row],[sales_stream]]="MBLL",Table26[[#This Row],[Product Price]]*1.05)} -> 0
A14: 2237 | B14: Paid | C14: Shipped | D14: 45485 | I14: Sent | J14: BCDD | K14: 45485 | L14: Retail | N14: =Table26[[#This Row],[po_number]]&"-"&Table26[[#This Row],[po_line]] -> -2 | O14: 2 | Q14: PR2407F5P3 | R14: Yes | S14: BC | T14: 45447 | U14: 24 | V14: 12 | W14: =IFERROR(U14/V14, "") -> 2 | X14: =IFERROR($AA14*$U14, "") | Y14: 00877579002847 | AA14: {=IF(P14="", "", _xlfn.XLOOKUP(P14,#REF!,#REF!,NA,0,-1))} | AC14: City Cannabis | AD14: =IF($AC14="","",_xlfn.XLOOKUP($AC14,'[2]Client Info'!$C$2:$C$2535,'[2]Client Info'!$D$2:$D$2535)) -> #N/A | AE14: =IF($AC14="","",_xlfn.XLOOKUP($AC14,'[2]Client Info'!$C$2:$C$2715,'[2]Client Info'!$E$2:$E$2715)) -> #N/A | AF14: =IF($AC14="","",_xlfn.XLOOKUP($AC14,'[2]Client Info'!$C$2:$C$2715,'[2]Client Info'!$F$2:$F$2715)) -> #N/A | AG14: City Cannabis | AI14: =_xlfn.XLOOKUP(Table26[[#This Row],[customerSKU]],customerSKU!G:G,customerSKU!O:O,"not found",0,1) -> not found | AJ14: =Table26[[#This Row],[unitprice]]*Table26[[#This Row],[quantity_unit]] -> 0 | AK14: {=_xlfn.IFS(Table26[[#This Row],[sales_stream]]="BCDD",Table26[[#This Row],[Product Price]]*1.05,Table26[[#This Row],[sales_stream]]="MBLL_redistribution",Table26[[#This Row],[Product Price]]*1.05,Table26[[#This Row],[sales_stream]]="MBLL",Table26[[#This Row],[Product Price]]*1.05)} -> 0
A15: 2234 | B15: Not Applicable | C15: Shipped | I15: Sent | J15: Intra-company | K15: 45488 | L15: Intra Industry | N15: =Table26[[#This Row],[po_number]]&"-"&Table26[[#This Row],[po_line]] -> -1 | O15: 1 | Q15: PH23051101 | R15: No | T15: 45179 | U15: 108 | V15: 108 | W15: =IFERROR(U15/V15, "") -> 1 | X15: =IFERROR($AA15*$U15, "") | AA15: {=IF(P15="", "", _xlfn.XLOOKUP(P15,#REF!,#REF!,NA,0,-1))} | AC15: Whistler Therapeutics Corp | AD15: =IF($AC15="","",_xlfn.XLOOKUP($AC15,'[2]Client Info'!$C$2:$C$2535,'[2]Client Info'!$D$2:$D$2535)) -> #201 – 1420 Alpha Lake Road | AE15: =IF($AC15="","",_xlfn.XLOOKUP($AC15,'[2]Client Info'!$C$2:$C$2715,'[2]Client Info'!$E$2:$E$2715)) -> Whistler | AF15: =IF($AC15="","",_xlfn.XLOOKUP($AC15,'[2]Client Info'!$C$2:$C$2715,'[2]Client Info'!$F$2:$F$2715)) -> BC | AG15: Whistler Therapeutics Corp | AH15: 0 | AI15: =_xlfn.XLOOKUP(Table26[[#This Row],[customerSKU]],customerSKU!G:G,customerSKU!O:O,"not found",0,1) -> not found | AJ15: =Table26[[#This Row],[unitprice]]*Table26[[#This Row],[quantity_unit]] -> 0 | AK15: {=_xlfn.IFS(Table26[[#This Row],[sales_stream]]="BCDD",Table26[[#This Row],[Product Price]]*1.05,Table26[[#This Row],[sales_stream]]="MBLL_redistribution",Table26[[#This Row],[Product Price]]*1.05,Table26[[#This Row],[sales_stream]]="MBLL",Table26[[#This Row],[Product Price]]*1.05)} -> #N/A
A16: 2235 | B16: Not Applicable | C16: Shipped | I16: Sent | J16: Intra-company | K16: 45488 | L16: Intra Industry | N16: =Table26[[#This Row],[po_number]]&"-"&Table26[[#This Row],[po_line]] -> -2 | O16: 2 | Q16: ROT23004 | R16: No | T16: 45388 | U16: 100 | V16: 100 | W16: =IFERROR(U16/V16, "") -> 1 | X16: =IFERROR($AA16*$U16, "") | AA16: {=IF(P16="", "", _xlfn.XLOOKUP(P16,#REF!,#REF!,NA,0,-1))} | AC16: Whistler Therapeutics Corp | AD16: =IF($AC16="","",_xlfn.XLOOKUP($AC16,'[2]Client Info'!$C$2:$C$2535,'[2]Client Info'!$D$2:$D$2535)) -> #201 – 1420 Alpha Lake Road | AE16: =IF($AC16="","",_xlfn.XLOOKUP($AC16,'[2]Client Info'!$C$2:$C$2715,'[2]Client Info'!$E$2:$E$2715)) -> Whistler | AF16: =IF($AC16="","",_xlfn.XLOOKUP($AC16,'[2]Client Info'!$C$2:$C$2715,'[2]Client Info'!$F$2:$F$2715)) -> BC | AG16: Whistler Therapeutics Corp | AH16: 0 | AI16: =_xlfn.XLOOKUP(Table26[[#This Row],[customerSKU]],customerSKU!G:G,customerSKU!O:O,"not found",0,1) -> not found | AJ16: =Table26[[#This Row],[unitprice]]*Table26[[#This Row],[quantity_unit]] -> 0 | AK16: {=_xlfn.IFS(Table26[[#This Row],[sales_stream]]="BCDD",Table26[[#This Row],[Product Price]]*1.05,Table26[[#This Row],[sales_stream]]="MBLL_redistribution",Table26[[#This Row],[Product Price]]*1.05,Table26[[#This Row],[sales_stream]]="MBLL",Table26[[#This Row],[Product Price]]*1.05)} -> #N/A
A17: 2211 | B17: Paid | C17: Shipped | I17: Sent | J17: CANNMART | K17: 45492 | L17: Provincial Distribution | N17: =Table26[[#This Row],[po_number]]&"-"&Table26[[#This Row],[po_line]] -> -1 | O17: 1 | Q17: EFF2403H2 | R17: Yes | S17: QC | T17: 45443 | U17: =12*60 -> 720 | V17: 12 | W17: =IFERROR(U17/V17, "") -> 60 | X17: =IFERROR($AA17*$U17, "") | AA17: {=IF(P17="", "", _xlfn.XLOOKUP(P17,#REF!,#REF!,NA,0,-1))} | AC17: CannMart Inc | AD17: =IF($AC17="","",_xlfn.XLOOKUP($AC17,'[2]Client Info'!$C$2:$C$2535,'[2]Client Info'!$D$2:$D$2535)) -> 18, Canso rd | AE17: =IF($AC17="","",_xlfn.XLOOKUP($AC17,'[2]Client Info'!$C$2:$C$2715,'[2]Client Info'!$E$2:$E$2715)) -> Etobicoke | AF17: =IF($AC17="","",_xlfn.XLOOKUP($AC17,'[2]Client Info'!$C$2:$C$2715,'[2]Client Info'!$F$2:$F$2715)) -> ON | AG17: CannMart Inc | AI17: =_xlfn.XLOOKUP(Table26[[#This Row],[customerSKU]],customerSKU!G:G,customerSKU!O:O,"not found",0,1) -> not found | AJ17: =Table26[[#This Row],[unitprice]]*Table26[[#This Row],[quantity_unit]] -> 0 | AK17: {=_xlfn.IFS(Table26[[#This Row],[sales_stream]]="BCDD",Table26[[#This Row],[Product Price]]*1.05,Table26[[#This Row],[sales_stream]]="MBLL_redistribution",Table26[[#This Row],[Product Price]]*1.05,Table26[[#This Row],[sales_stream]]="MBLL",Table26[[#This Row],[Product Price]]*1.05)} -> #N/A
A18: 2212 | B18: Paid | C18: Shipped | I18: Sent | J18: CANNMART | K18: 45492 | L18: Provincial Distribution | N18: =Table26[[#This Row],[po_number]]&"-"&Table26[[#This Row],[po_line]] -> -1 | O18: 1 | Q18: EFF2403H2-1 | R18: Yes | S18: QC | T18: 45473 | U18: =272*12 -> 3264 | V18: 12 | W18: =IFERROR(U18/V18, "") -> 272 | X18: =IFERROR($AA18*$U18, "") | AA18: {=IF(P18="", "", _xlfn.XLOOKUP(P18,#REF!,#REF!,NA,0,-1))} | AC18: CannMart Inc | AD18: =IF($AC18="","",_xlfn.XLOOKUP($AC18,'[2]Client Info'!$C$2:$C$2535,'[2]Client Info'!$D$2:$D$2535)) -> 18, Canso rd | AE18: =IF($AC18="","",_xlfn.XLOOKUP($AC18,'[2]Client Info'!$C$2:$C$2715,'[2]Client Info'!$E$2:$E$2715)) -> Etobicoke | AF18: =IF($AC18="","",_xlfn.XLOOKUP($AC18,'[2]Client Info'!$C$2:$C$2715,'[2]Client Info'!$F$2:$F$2715)) -> ON | AG18: CannMart Inc | AI18: =_xlfn.XLOOKUP(Table26[[#This Row],[customerSKU]],customerSKU!G:G,customerSKU!O:O,"not found",0,1) -> not found | AJ18: =Table26[[#This Row],[unitprice]]*Table26[[#This Row],[quantity_unit]] -> 0 | AK18: {=_xlfn.IFS(Table26[[#This Row],[sales_stream]]="BCDD",Table26[[#This Row],[Product Price]]*1.05,Table26[[#This Row],[sales_stream]]="MBLL_redistribution",Table26[[#This Row],[Product Price]]*1.05,Table26[[#This Row],[sales_stream]]="MBLL",Table26[[#This Row],[Product Price]]*1.05)} -> #N/A
A19: 2213 | B19: Paid | C19: Shipped | I19: Sent | J19: CANNMART | K19: 45492 | L19: Provincial Distribution | N19: =Table26[[#This Row],[po_number]]&"-"&Table26[[#This Row],[po_line]] -> -2 | O19: 2 | Q19: EF5F2402H2 | R19: Yes | S19: QC | T19: 45478 | U19: =183*12 -> 2196 | V19: 12 | W19: =IFERROR(U19/V19, "") -> 183 | X19: =IFERROR($AA19*$U19, "") | AA19: {=IF(P19="", "", _xlfn.XLOOKUP(P19,#REF!,#REF!,NA,0,-1))} | AC19: CannMart Inc | AD19: =IF($AC19="","",_xlfn.XLOOKUP($AC19,'[2]Client Info'!$C$2:$C$2535,'[2]Client Info'!$D$2:$D$2535)) -> 18, Canso rd | AE19: =IF($AC19="","",_xlfn.XLOOKUP($AC19,'[2]Client Info'!$C$2:$C$2715,'[2]Client Info'!$E$2:$E$2715)) -> Etobicoke | AF19: =IF($AC19="","",_xlfn.XLOOKUP($AC19,'[2]Client Info'!$C$2:$C$2715,'[2]Client Info'!$F$2:$F$2715)) -> ON | AG19: CannMart Inc | AI19: =_xlfn.XLOOKUP(Table26[[#This Row],[customerSKU]],customerSKU!G:G,customerSKU!O:O,"not found",0,1) -> not found | AJ19: =Table26[[#This Row],[unitprice]]*Table26[[#This Row],[quantity_unit]] -> 0 | AK19: {=_xlfn.IFS(Table26[[#This Row],[sales_stream]]="BCDD",Table26[[#This Row],[Product Price]]*1.05,Table26[[#This Row],[sales_stream]]="MBLL_redistribution",Table26[[#This Row],[Product Price]]*1.05,Table26[[#This Row],[sales_stream]]="MBLL",Table26[[#This Row],[Product Price]]*1.05)} -> #N/A
A20: 2214 | B20: Paid | C20: Shipped | I20: Sent | J20: CANNMART | K20: 45492 | L20: Provincial Distribution | N20: =Table26[[#This Row],[po_number]]&"-"&Table26[[#This Row],[po_line]] -> -1 | O20: 1 | Q20: PR2405F7P3-2 | R20: Yes | S20: YT | T20: 45464 | U20: 12 | V20: 12 | W20: =IFERROR(U20/V20, "") -> 1 | X20: =IFERROR($AA20*$U20, "") | AA20: {=IF(P20="", "", _xlfn.XLOOKUP(P20,#REF!,#REF!,NA,0,-1))} | AC20: Cannabis Yukon | AD20: =IF($AC20="","",_xlfn.XLOOKUP($AC20,'[2]Client Info'!$C$2:$C$2535,'[2]Client Info'!$D$2:$D$2535)) -> 9031 Quartz Road | AE20: =IF($AC20="","",_xlfn.XLOOKUP($AC20,'[2]Client Info'!$C$2:$C$2715,'[2]Client Info'!$E$2:$E$2715)) -> White Horse | AF20: =IF($AC20="","",_xlfn.XLOOKUP($AC20,'[2]Client Info'!$C$2:$C$2715,'[2]Client Info'!$F$2:$F$2715)) -> YT | AG20: CannMart Inc | AI20: =_xlfn.XLOOKUP(Table26[[#This Row],[customerSKU]],customerSKU!G:G,customerSKU!O:O,"not found",0,1) -> not found | AJ20: =Table26[[#This Row],[unitprice]]*Table26[[#This Row],[quantity_unit]] -> 0 | AK20: {=_xlfn.IFS(Table26[[#This Row],[sales_stream]]="BCDD",Table26[[#This Row],[Product Price]]*1.05,Table26[[#This Row],[sales_stream]]="MBLL_redistribution",Table26[[#This Row],[Product Price]]*1.05,Table26[[#This Row],[sales_stream]]="MBLL",Table26[[#This Row],[Product Price]]*1.05)} -> #N/A
A21: 2215 | B21: Paid | C21: Shipped | D21: 45483 | I21: Sent | J21: CANNMART | K21: 45492 | L21: Provincial Distribution | N21: =Table26[[#This Row],[po_number]]&"-"&Table26[[#This Row],[po_line]] -> -1 | O21: 1 | Q21: TP24041202 | R21: Yes | S21: YT | T21: 45423 | U21: 12 | V21: 12 | W21: =IFERROR(U21/V21, "") -> 1 | X21: =IFERROR($AA21*$U21, "") | Y21: 00877579001550 | AA21: {=IF(P21="", "", _xlfn.XLOOKUP(P21,#REF!,#REF!,NA,0,-1))} | AC21: Cannabis Yukon | AD21: =IF($AC21="","",_xlfn.XLOOKUP($AC21,'[2]Client Info'!$C$2:$C$2535,'[2]Client Info'!$D$2:$D$2535)) -> 9031 Quartz Road | AE21: =IF($AC21="","",_xlfn.XLOOKUP($AC21,'[2]Client Info'!$C$2:$C$2715,'[2]Client Info'!$E$2:$E$2715)) -> White Horse | AF21: =IF($AC21="","",_xlfn.XLOOKUP($AC21,'[2]Client Info'!$C$2:$C$2715,'[2]Client Info'!$F$2:$F$2715)) -> YT | AG21: CannMart Inc | AH21: =228/12 -> 19 | AI21: =_xlfn.XLOOKUP(Table26[[#This Row],[customerSKU]],customerSKU!G:G,customerSKU!O:O,"not found",0,1) -> not found | AJ21: =Table26[[#This Row],[unitprice]]*Table26[[#This Row],[quantity_unit]] -> 228 | AK21: {=_xlfn.IFS(Table26[[#This Row],[sales_stream]]="BCDD",Table26[[#This Row],[Product Price]]*1.05,Table26[[#This Row],[sales_stream]]="MBLL_redistribution",Table26[[#This Row],[Product Price]]*1.05,Table26[[#This Row],[sales_stream]]="MBLL",Table26[[#This Row],[Product Price]]*1.05)} -> #N/A
A22: 2216 | B22: Paid | C22: Shipped | I22: Sent | J22: CANNMART | K22: 45492 | L22: Provincial Distribution | N22: =Table26[[#This Row],[po_number]]&"-"&Table26[[#This Row],[po_line]] -> -1 | O22: 1 | Q22: PR2408F7P3 | R22: Yes | S22: MB | T22: 45483 | U22: =15*12 -> 180 | V22: 12 | W22: =IFERROR(U22/V22, "") -> 15 | X22: =IFERROR($AA22*$U22, "") | AA22: {=IF(P22="", "", _xlfn.XLOOKUP(P22,#REF!,#REF!,NA,0,-1))} | AC22: CannMart Inc | AD22: =IF($AC22="","",_xlfn.XLOOKUP($AC22,'[2]Client Info'!$C$2:$C$2535,'[2]Client Info'!$D$2:$D$2535)) -> 18, Canso rd | AE22: =IF($AC22="","",_xlfn.XLOOKUP($AC22,'[2]Client Info'!$C$2:$C$2715,'[2]Client Info'!$E$2:$E$2715)) -> Etobicoke | AF22: =IF($AC22="","",_xlfn.XLOOKUP($AC22,'[2]Client Info'!$C$2:$C$2715,'[2]Client Info'!$F$2:$F$2715)) -> ON | AG22: CannMart Inc | AI22: =_xlfn.XLOOKUP(Table26[[#This Row],[customerSKU]],customerSKU!G:G,customerSKU!O:O,"not found",0,1) -> not found | AJ22: =Table26[[#This Row],[unitprice]]*Table26[[#This Row],[quantity_unit]] -> 0 | AK22: {=_xlfn.IFS(Table26[[#This Row],[sales_stream]]="BCDD",Table26[[#This Row],[Product Price]]*1.05,Table26[[#This Row],[sales_stream]]="MBLL_redistribution",Table26[[#This Row],[Product Price]]*1.05,Table26[[#This Row],[sales_stream]]="MBLL",Table26[[#This Row],[Product Price]]*1.05)} -> #N/A
A23: 2217 | B23: Paid | C23: Shipped | I23: Sent | J23: CANNMART | K23: 45492 | L23: Provincial Distribution | N23: =Table26[[#This Row],[po_number]]&"-"&Table26[[#This Row],[po_line]] -> -2 | O23: 2 | Q23: PR2408F7P3 | R23: Yes | S23: SK | T23: 45483 | U23: =15*12 -> 180 | V23: 12 | W23: =IFERROR(U23/V23, "") -> 15 | X23: =IFERROR($AA23*$U23, "") | AA23: {=IF(P23="", "", _xlfn.XLOOKUP(P23,#REF!,#REF!,NA,0,-1))} | AC23: CannMart Inc | AD23: =IF($AC23="","",_xlfn.XLOOKUP($AC23,'[2]Client Info'!$C$2:$C$2535,'[2]Client Info'!$D$2:$D$2535)) -> 18, Canso rd | AE23: =IF($AC23="","",_xlfn.XLOOKUP($AC23,'[2]Client Info'!$C$2:$C$2715,'[2]Client Info'!$E$2:$E$2715)) -> Etobicoke | AF23: =IF($AC23="","",_xlfn.XLOOKUP($AC23,'[2]Client Info'!$C$2:$C$2715,'[2]Client Info'!$F$2:$F$2715)) -> ON | AG23: CannMart Inc | AI23: =_xlfn.XLOOKUP(Table26[[#This Row],[customerSKU]],customerSKU!G:G,customerSKU!O:O,"not found",0,1) -> not found | AJ23: =Table26[[#This Row],[unitprice]]*Table26[[#This Row],[quantity_unit]] -> 0 | AK23: {=_xlfn.IFS(Table26[[#This Row],[sales_stream]]="BCDD",Table26[[#This Row],[Product Price]]*1.05,Table26[[#This Row],[sales_stream]]="MBLL_redistribution",Table26[[#This Row],[Product Price]]*1.05,Table26[[#This Row],[sales_stream]]="MBLL",Table26[[#This Row],[Product Price]]*1.05)} -> #N/A
A24: 2218 | B24: Not Applicable | C24: Shipped | I24: Sent | J24: MBLL | K24: 45492 | L24: Provincial Distribution | N24: =Table26[[#This Row],[po_number]]&"-"&Table26[[#This Row],[po_line]] -> -1 | O24: 1 | Q24: CPR22102001G1 | R24: Yes | S24: MB | T24: 45492 | U24: 12 | V24: 12 | W24: =IFERROR(U24/V24, "") -> 1 | X24: =IFERROR($AA24*$U24, "") | Y24: 00877579003196 | AA24: {=IF(P24="", "", _xlfn.XLOOKUP(P24,#REF!,#REF!,NA,0,-1))} | AC24: Praire Trichomes Ltd | AD24: =IF($AC24="","",_xlfn.XLOOKUP($AC24,'[2]Client Info'!$C$2:$C$2535,'[2]Client Info'!$D$2:$D$2535)) -> 543 Broadway Ave | AE24: =IF($AC24="","",_xlfn.XLOOKUP($AC24,'[2]Client Info'!$C$2:$C$2715,'[2]Client Info'!$E$2:$E$2715)) -> Killarney | AF24: =IF($AC24="","",_xlfn.XLOOKUP($AC24,'[2]Client Info'!$C$2:$C$2715,'[2]Client Info'!$F$2:$F$2715)) -> MB | AG24: MBLL | AH24: =77.88/12 -> 6.49 | AI24: =_xlfn.XLOOKUP(Table26[[#This Row],[customerSKU]],customerSKU!G:G,customerSKU!O:O,"not found",0,1) -> not found | AJ24: =Table26[[#This Row],[unitprice]]*Table26[[#This Row],[quantity_unit]] -> 77.88 | AK24: {=_xlfn.IFS(Table26[[#This Row],[sales_stream]]="BCDD",Table26[[#This Row],[Product Price]]*1.05,Table26[[#This Row],[sales_stream]]="MBLL_redistribution",Table26[[#This Row],[Product Price]]*1.05,Table26[[#This Row],[sales_stream]]="MBLL",Table26[[#This Row],[Product Price]]*1.05)} -> 81.774
A25: 2219 | B25: Not Applicable | C25: Shipped | I25: Sent | J25: MBLL | K25: 45492 | L25: Provincial Distribution | N25: =Table26[[#This Row],[po_number]]&"-"&Table26[[#This Row],[po_line]] -> -2 | O25: 2 | Q25: CPR22102101G1 | R25: Yes | S25: MB | T25: 45492 | U25: 12 | V25: 12 | W25: =IFERROR(U25/V25, "") -> 1 | X25: =IFERROR($AA25*$U25, "") | Y25: 00877579003165 | AA25: {=IF(P25="", "", _xlfn.XLOOKUP(P25,#REF!,#REF!,NA,0,-1))} | AC25: Praire Trichomes Ltd | AD25: =IF($AC25="","",_xlfn.XLOOKUP($AC25,'[2]Client Info'!$C$2:$C$2535,'[2]Client Info'!$D$2:$D$2535)) -> 543 Broadway Ave | AE25: =IF($AC25="","",_xlfn.XLOOKUP($AC25,'[2]Client Info'!$C$2:$C$2715,'[2]Client Info'!$E$2:$E$2715)) -> Killarney | AF25: =IF($AC25="","",_xlfn.XLOOKUP($AC25,'[2]Client Info'!$C$2:$C$2715,'[2]Client Info'!$F$2:$F$2715)) -> MB | AG25: MBLL | AH25: =77.4/12 -> 6.45 | AI25: =_xlfn.XLOOKUP(Table26[[#This Row],[customerSKU]],customerSKU!G:G,customerSKU!O:O,"not found",0,1) -> not found | AJ25: =Table26[[#This Row],[unitprice]]*Table26[[#This Row],[quantity_unit]] -> 77.4 | AK25: {=_xlfn.IFS(Table26[[#This Row],[sales_stream]]="BCDD",Table26[[#This Row],[Product Price]]*1.05,Table26[[#This Row],[sales_stream]]="MBLL_redistribution",Table26[[#This Row],[Product Price]]*1.05,Table26[[#This Row],[sales_stream]]="MBLL",Table26[[#This Row],[Product Price]]*1.05)} -> 81.27
A26: 2220 | B26: Not Applicable | C26: Shipped | I26: Sent | J26: MBLL | K26: 45492 | L26: Provincial Distribution | N26: =Table26[[#This Row],[po_number]]&"-"&Table26[[#This Row],[po_line]] -> -3 | O26: 3 | Q26: PR22051901G1 | R26: Yes | S26: MB | T26: 45492 | U26: 12 | V26: 12 | W26: =IFERROR(U26/V26, "") -> 1 | X26: =IFERROR($AA26*$U26, "") | Y26: 00877579003158 | AA26: {=IF(P26="", "", _xlfn.XLOOKUP(P26,#REF!,#REF!,NA,0,-1))} | AC26: Praire Trichomes Ltd | AD26: =IF($AC26="","",_xlfn.XLOOKUP($AC26,'[2]Client Info'!$C$2:$C$2535,'[2]Client Info'!$D$2:$D$2535)) -> 543 Broadway Ave | AE26: =IF($AC26="","",_xlfn.XLOOKUP($AC26,'[2]Client Info'!$C$2:$C$2715,'[2]Client Info'!$E$2:$E$2715)) -> Killarney | AF26: =IF($AC26="","",_xlfn.XLOOKUP($AC26,'[2]Client Info'!$C$2:$C$2715,'[2]Client Info'!$F$2:$F$2715)) -> MB | AG26: MBLL | AH26: =74.28/12 -> 6.19 | AI26: =_xlfn.XLOOKUP(Table26[[#This Row],[customerSKU]],customerSKU!G:G,customerSKU!O:O,"not found",0,1) -> not found | AJ26: =Table26[[#This Row],[unitprice]]*Table26[[#This Row],[quantity_unit]] -> 74.28 | AK26: {=_xlfn.IFS(Table26[[#This Row],[sales_stream]]="BCDD",Table26[[#This Row],[Product Price]]*1.05,Table26[[#This Row],[sales_stream]]="MBLL_redistribution",Table26[[#This Row],[Product Price]]*1.05,Table26[[#This Row],[sales_stream]]="MBLL",Table26[[#This Row],[Product Price]]*1.05)} -> 77.994
A27: 2221 | B27: Paid | C27: Shipped | E27: =IF(#REF!>0,#REF!,"") -> #REF! | I27: Sent | J27: BCDD | K27: 45492 | L27: Retail | N27: =Table26[[#This Row],[po_number]]&"-"&Table26[[#This Row],[po_line]] -> -1 | O27: 1 | Q27: EX23100401V30 | R27: No | T27: 45488 | U27: 24 | V27: 12 | W27: =IFERROR(U27/V27, "") -> 2 | X27: =IFERROR($AA27*$U27, "") | AA27: {=IF(P27="", "", _xlfn.XLOOKUP(P27,#REF!,#REF!,NA,0,-1))} | AC27: KOOTENAY CANNABIS CASTLEGAR | AD27: =IF($AC27="","",_xlfn.XLOOKUP($AC27,'[2]Client Info'!$C$2:$C$2535,'[2]Client Info'!$D$2:$D$2535)) -> 1306 COLUMBIA AVE | AE27: =IF($AC27="","",_xlfn.XLOOKUP($AC27,'[2]Client Info'!$C$2:$C$2715,'[2]Client Info'!$E$2:$E$2715)) -> CASTLEGAR | AF27: =IF($AC27="","",_xlfn.XLOOKUP($AC27,'[2]Client Info'!$C$2:$C$2715,'[2]Client Info'!$F$2:$F$2715)) -> BC | AG27: KOOTENAY CANNABIS CASTLEGAR | AI27: =_xlfn.XLOOKUP(Table26[[#This Row],[customerSKU]],customerSKU!G:G,customerSKU!O:O,"not found",0,1) -> not found | AJ27: =Table26[[#This Row],[unitprice]]*Table26[[#This Row],[quantity_unit]] -> 0 | AK27: {=_xlfn.IFS(Table26[[#This Row],[sales_stream]]="BCDD",Table26[[#This Row],[Product Price]]*1.05,Table26[[#This Row],[sales_stream]]="MBLL_redistribution",Table26[[#This Row],[Product Price]]*1.05,Table26[[#This Row],[sales_stream]]="MBLL",Table26[[#This Row],[Product Price]]*1.05)} -> 0
A28: 2222 | B28: Paid | C28: Shipped | E28: =IF(#REF!>0,#REF!,"") -> #REF! | I28: Sent | J28: BCDD | K28: 45492 | L28: Retail | N28: =Table26[[#This Row],[po_number]]&"-"&Table26[[#This Row],[po_line]] -> -2 | O28: 2 | Q28: PR2406F1P3 | R28: Yes | S28: BC | T28: 45448 | U28: 12 | V28: 12 | W28: =IFERROR(U28/V28, "") -> 1 | X28: =IFERROR($AA28*$U28, "") | AA28: {=IF(P28="", "", _xlfn.XLOOKUP(P28,#REF!,#REF!,NA,0,-1))} | AC28: KOOTENAY CANNABIS CASTLEGAR | AD28: =IF($AC28="","",_xlfn.XLOOKUP($AC28,'[2]Client Info'!$C$2:$C$2535,'[2]Client Info'!$D$2:$D$2535)) -> 1306 COLUMBIA AVE | AE28: =IF($AC28="","",_xlfn.XLOOKUP($AC28,'[2]Client Info'!$C$2:$C$2715,'[2]Client Info'!$E$2:$E$2715)) -> CASTLEGAR | AF28: =IF($AC28="","",_xlfn.XLOOKUP($AC28,'[2]Client Info'!$C$2:$C$2715,'[2]Client Info'!$F$2:$F$2715)) -> BC | AG28: KOOTENAY CANNABIS CASTLEGAR | AI28: =_xlfn.XLOOKUP(Table26[[#This Row],[customerSKU]],customerSKU!G:G,customerSKU!O:O,"not found",0,1) -> not found | AJ28: =Table26[[#This Row],[unitprice]]*Table26[[#This Row],[quantity_unit]] -> 0 | AK28: {=_xlfn.IFS(Table26[[#This Row],[sales_stream]]="BCDD",Table26[[#This Row],[Product Price]]*1.05,Table26[[#This Row],[sales_stream]]="MBLL_redistribution",Table26[[#This Row],[Product Price]]*1.05,Table26[[#This Row],[sales_stream]]="MBLL",Table26[[#This Row],[Product Price]]*1.05)} -> 0
A29: 2223 | B29: Paid | C29: Shipped | E29: =IF(#REF!>0,#REF!,"") -> #REF! | I29: Sent | J29: BCDD | K29: 45492 | L29: Retail | N29: =Table26[[#This Row],[po_number]]&"-"&Table26[[#This Row],[po_line]] -> -3 | O29: 3 | Q29: PR2407F5P3 | R29: Yes | S29: BC | T29: 45447 | U29: 12 | V29: 12 | W29: =IFERROR(U29/V29, "") -> 1 | X29: =IFERROR($AA29*$U29, "") | AA29: {=IF(P29="", "", _xlfn.XLOOKUP(P29,#REF!,#REF!,NA,0,-1))} | AC29: KOOTENAY CANNABIS CASTLEGAR | AD29: =IF($AC29="","",_xlfn.XLOOKUP($AC29,'[2]Client Info'!$C$2:$C$2535,'[2]Client Info'!$D$2:$D$2535)) -> 1306 COLUMBIA AVE | AE29: =IF($AC29="","",_xlfn.XLOOKUP($AC29,'[2]Client Info'!$C$2:$C$2715,'[2]Client Info'!$E$2:$E$2715)) -> CASTLEGAR | AF29: =IF($AC29="","",_xlfn.XLOOKUP($AC29,'[2]Client Info'!$C$2:$C$2715,'[2]Client Info'!$F$2:$F$2715)) -> BC | AG29: KOOTENAY CANNABIS CASTLEGAR | AI29: =_xlfn.XLOOKUP(Table26[[#This Row],[customerSKU]],customerSKU!G:G,customerSKU!O:O,"not found",0,1) -> not found | AJ29: =Table26[[#This Row],[unitprice]]*Table26[[#This Row],[quantity_unit]] -> 0 | AK29: {=_xlfn.IFS(Table26[[#This Row],[sales_stream]]="BCDD",Table26[[#This Row],[Product Price]]*1.05,Table26[[#This Row],[sales_stream]]="MBLL_redistribution",Table26[[#This Row],[Product Price]]*1.05,Table26[[#This Row],[sales_stream]]="MBLL",Table26[[#This Row],[Product Price]]*1.05)} -> 0
A30: 2224 | B30: Paid | C30: Shipped | E30: =IF(#REF!>0,#REF!,"") -> #REF! | I30: Sent | J30: BCDD | K30: 45492 | L30: Retail | N30: =Table26[[#This Row],[po_number]]&"-"&Table26[[#This Row],[po_line]] -> -4 | O30: 4 | Q30: PR240601F5P3 | R30: Yes | S30: BC | T30: 45491 | U30: 24 | V30: 12 | W30: =IFERROR(U30/V30, "") -> 2 | X30: =IFERROR($AA30*$U30, "") | AA30: {=IF(P30="", "", _xlfn.XLOOKUP(P30,#REF!,#REF!,NA,0,-1))} | AC30: KOOTENAY CANNABIS CASTLEGAR | AD30: =IF($AC30="","",_xlfn.XLOOKUP($AC30,'[2]Client Info'!$C$2:$C$2535,'[2]Client Info'!$D$2:$D$2535)) -> 1306 COLUMBIA AVE | AE30: =IF($AC30="","",_xlfn.XLOOKUP($AC30,'[2]Client Info'!$C$2:$C$2715,'[2]Client Info'!$E$2:$E$2715)) -> CASTLEGAR | AF30: =IF($AC30="","",_xlfn.XLOOKUP($AC30,'[2]Client Info'!$C$2:$C$2715,'[2]Client Info'!$F$2:$F$2715)) -> BC | AG30: KOOTENAY CANNABIS CASTLEGAR | AI30: =_xlfn.XLOOKUP(Table26[[#This Row],[customerSKU]],customerSKU!G:G,customerSKU!O:O,"not found",0,1) -> not found | AJ30: =Table26[[#This Row],[unitprice]]*Table26[[#This Row],[quantity_unit]] -> 0 | AK30: {=_xlfn.IFS(Table26[[#This Row],[sales_stream]]="BCDD",Table26[[#This Row],[Product Price]]*1.05,Table26[[#This Row],[sales_stream]]="MBLL_redistribution",Table26[[#This Row],[Product Price]]*1.05,Table26[[#This Row],[sales_stream]]="MBLL",Table26[[#This Row],[Product Price]]*1.05)} -> 0
A31: 2225 | B31: Paid | C31: Shipped | I31: Sent | J31: BCDD | K31: 45492 | L31: Retail | N31: =Table26[[#This Row],[po_number]]&"-"&Table26[[#This Row],[po_line]] -> -1 | O31: 1 | Q31: EX24061401V30 | R31: No | S31: BC | T31: 45467 | U31: 12 | V31: 12 | W31: =IFERROR(U31/V31, "") -> 1 | X31: =IFERROR($AA31*$U31, "") | AA31: {=IF(P31="", "", _xlfn.XLOOKUP(P31,#REF!,#REF!,NA,0,-1))} | AC31: Brunette Cannabis Co. | AD31: =IF($AC31="","",_xlfn.XLOOKUP($AC31,'[2]Client Info'!$C$2:$C$2535,'[2]Client Info'!$D$2:$D$2535)) -> #102-935 Brunette Ave | AE31: =IF($AC31="","",_xlfn.XLOOKUP($AC31,'[2]Client Info'!$C$2:$C$2715,'[2]Client Info'!$E$2:$E$2715)) -> Coquitlam | AF31: =IF($AC31="","",_xlfn.XLOOKUP($AC31,'[2]Client Info'!$C$2:$C$2715,'[2]Client Info'!$F$2:$F$2715)) -> BC | AG31: Brunette Cannabis Co. | AH31: =227.76/12 -> 18.98 | AI31: =_xlfn.XLOOKUP(Table26[[#This Row],[customerSKU]],customerSKU!G:G,customerSKU!O:O,"not found",0,1) -> not found | AJ31: =Table26[[#This Row],[unitprice]]*Table26[[#This Row],[quantity_unit]] -> 227.76 | AK31: {=_xlfn.IFS(Table26[[#This Row],[sales_stream]]="BCDD",Table26[[#This Row],[Product Price]]*1.05,Table26[[#This Row],[sales_stream]]="MBLL_redistribution",Table26[[#This Row],[Product Price]]*1.05,Table26[[#This Row],[sales_stream]]="MBLL",Table26[[#This Row],[Product Price]]*1.05)} -> 239.148
A32: 2226 | B32: Paid | C32: Shipped | E32: =IF(#REF!>0,#REF!,"") -> #REF! | I32: Sent | J32: BCDD | K32: 45492 | L32: Retail | N32: =Table26[[#This Row],[po_number]]&"-"&Table26[[#This Row],[po_line]] -> -2 | O32: 2 | Q32: EX23100401V30 | R32: No | T32: 45488 | U32: 12 | V32: 12 | W32: =IFERROR(U32/V32, "") -> 1 | X32: =IFERROR($AA32*$U32, "") | AA32: {=IF(P32="", "", _xlfn.XLOOKUP(P32,#REF!,#REF!,NA,0,-1))} | AC32: Brunette Cannabis Co. | AD32: =IF($AC32="","",_xlfn.XLOOKUP($AC32,'[2]Client Info'!$C$2:$C$2535,'[2]Client Info'!$D$2:$D$2535)) -> #102-935 Brunette Ave | AE32: =IF($AC32="","",_xlfn.XLOOKUP($AC32,'[2]Client Info'!$C$2:$C$2715,'[2]Client Info'!$E$2:$E$2715)) -> Coquitlam | AF32: =IF($AC32="","",_xlfn.XLOOKUP($AC32,'[2]Client Info'!$C$2:$C$2715,'[2]Client Info'!$F$2:$F$2715)) -> BC | AG32: Brunette Cannabis Co. | AH32: =158.76/12 -> 13.23 | AI32: =_xlfn.XLOOKUP(Table26[[#This Row],[customerSKU]],customerSKU!G:G,customerSKU!O:O,"not found",0,1) -> not found | AJ32: =Table26[[#This Row],[unitprice]]*Table26[[#This Row],[quantity_unit]] -> 158.76 | AK32: {=_xlfn.IFS(Table26[[#This Row],[sales_stream]]="BCDD",Table26[[#This Row],[Product Price]]*1.05,Table26[[#This Row],[sales_stream]]="MBLL_redistribution",Table26[[#This Row],[Product Price]]*1.05,Table26[[#This Row],[sales_stream]]="MBLL",Table26[[#This Row],[Product Price]]*1.05)} -> 166.698
A33: 2227 | B33: Paid | C33: Shipped | I33: Sent | J33: BCDD | K33: 45492 | L33: Retail | N33: =Table26[[#This Row],[po_number]]&"-"&Table26[[#This Row],[po_line]] -> -3 | O33: 3 | Q33: TP24041202 | R33: Yes | S33: BC | T33: 45423 | U33: 12 | V33: 12 | W33: =IFERROR(U33/V33, "") -> 1 | X33: =IFERROR($AA33*$U33, "") | AA33: {=IF(P33="", "", _xlfn.XLOOKUP(P33,#REF!,#REF!,NA,0,-1))} | AC33: Brunette Cannabis Co. | AD33: =IF($AC33="","",_xlfn.XLOOKUP($AC33,'[2]Client Info'!$C$2:$C$2535,'[2]Client Info'!$D$2:$D$2535)) -> #102-935 Brunette Ave | AE33: =IF($AC33="","",_xlfn.XLOOKUP($AC33,'[2]Client Info'!$C$2:$C$2715,'[2]Client Info'!$E$2:$E$2715)) -> Coquitlam | AF33: =IF($AC33="","",_xlfn.XLOOKUP($AC33,'[2]Client Info'!$C$2:$C$2715,'[2]Client Info'!$F$2:$F$2715)) -> BC | AG33: Brunette Cannabis Co. | AH33: =239.88/12 -> 19.99 | AI33: =_xlfn.XLOOKUP(Table26[[#This Row],[customerSKU]],customerSKU!G:G,customerSKU!O:O,"not found",0,1) -> not found | AJ33: =Table26[[#This Row],[unitprice]]*Table26[[#This Row],[quantity_unit]] -> 239.88 | AK33: {=_xlfn.IFS(Table26[[#This Row],[sales_stream]]="BCDD",Table26[[#This Row],[Product Price]]*1.05,Table26[[#This Row],[sales_stream]]="MBLL_redistribution",Table26[[#This Row],[Product Price]]*1.05,Table26[[#This Row],[sales_stream]]="MBLL",Table26[[#This Row],[Product Price]]*1.05)} -> 251.874
A34: 2228 | B34: Paid | C34: Shipped | E34: =IF(#REF!>0,#REF!,"") -> #REF! | I34: Sent | J34: BCDD | K34: 45492 | L34: Retail | N34: =Table26[[#This Row],[po_number]]&"-"&Table26[[#This Row],[po_line]] -> -4 | O34: 4 | Q34: PR2406F1P3 | R34: Yes | S34: BC | T34: 45448 | U34: 24 | V34: 12 | W34: =IFERROR(U34/V34, "") -> 2 | X34: =IFERROR($AA34*$U34, "") | AA34: {=IF(P34="", "", _xlfn.XLOOKUP(P34,#REF!,#REF!,NA,0,-1))} | AC34: Brunette Cannabis Co. | AD34: =IF($AC34="","",_xlfn.XLOOKUP($AC34,'[2]Client Info'!$C$2:$C$2535,'[2]Client Info'!$D$2:$D$2535)) -> #102-935 Brunette Ave | AE34: =IF($AC34="","",_xlfn.XLOOKUP($AC34,'[2]Client Info'!$C$2:$C$2715,'[2]Client Info'!$E$2:$E$2715)) -> Coquitlam | AF34: =IF($AC34="","",_xlfn.XLOOKUP($AC34,'[2]Client Info'!$C$2:$C$2715,'[2]Client Info'!$F$2:$F$2715)) -> BC | AG34: Brunette Cannabis Co. | AH34: =202.08/12 -> 16.84 | AI34: =_xlfn.XLOOKUP(Table26[[#This Row],[customerSKU]],customerSKU!G:G,customerSKU!O:O,"not found",0,1) -> not found | AJ34: =Table26[[#This Row],[unitprice]]*Table26[[#This Row],[quantity_unit]] -> 404.16 | AK34: {=_xlfn.IFS(Table26[[#This Row],[sales_stream]]="BCDD",Table26[[#This Row],[Product Price]]*1.05,Table26[[#This Row],[sales_stream]]="MBLL_redistribution",Table26[[#This Row],[Product Price]]*1.05,Table26[[#This Row],[sales_stream]]="MBLL",Table26[[#This Row],[Product Price]]*1.05)} -> 424.368
A35: 2229 | B35: Paid | C35: Shipped | E35: =IF(#REF!>0,#REF!,"") -> #REF! | I35: Sent | J35: BCDD | K35: 45492 | L35: Retail | N35: =Table26[[#This Row],[po_number]]&"-"&Table26[[#This Row],[po_line]] -> -5 | O35: 5 | Q35: PR2406F5P3 | R35: Yes | S35: BC | T35: 45457 | U35: 24 | V35: 12 | W35: =IFERROR(U35/V35, "") -> 2 | X35: =IFERROR($AA35*$U35, "") | AA35: {=IF(P35="", "", _xlfn.XLOOKUP(P35,#REF!,#REF!,NA,0,-1))} | AC35: Brunette Cannabis Co. | AD35: =IF($AC35="","",_xlfn.XLOOKUP($AC35,'[2]Client Info'!$C$2:$C$2535,'[2]Client Info'!$D$2:$D$2535)) -> #102-935 Brunette Ave | AE35: =IF($AC35="","",_xlfn.XLOOKUP($AC35,'[2]Client Info'!$C$2:$C$2715,'[2]Client Info'!$E$2:$E$2715)) -> Coquitlam | AF35: =IF($AC35="","",_xlfn.XLOOKUP($AC35,'[2]Client Info'!$C$2:$C$2715,'[2]Client Info'!$F$2:$F$2715)) -> BC | AG35: Brunette Cannabis Co. | AH35: =264.96/12 -> 22.08 | AI35: =_xlfn.XLOOKUP(Table26[[#This Row],[customerSKU]],customerSKU!G:G,customerSKU!O:O,"not found",0,1) -> not found | AJ35: =Table26[[#This Row],[unitprice]]*Table26[[#This Row],[quantity_unit]] -> 529.92 | AK35: {=_xlfn.IFS(Table26[[#This Row],[sales_stream]]="BCDD",Table26[[#This Row],[Product Price]]*1.05,Table26[[#This Row],[sales_stream]]="MBLL_redistribution",Table26[[#This Row],[Product Price]]*1.05,Table26[[#This Row],[sales_stream]]="MBLL",Table26[[#This Row],[Product Price]]*1.05)} -> 556.416
A36: 2230 | B36: Paid | C36: Shipped | E36: =IF(#REF!>0,#REF!,"") -> #REF! | I36: Sent | J36: BCDD | K36: 45492 | L36: Retail | N36: =Table26[[#This Row],[po_number]]&"-"&Table26[[#This Row],[po_line]] -> -6 | O36: 6 | Q36: PR21071201G1 | R36: Yes | S36: BC | T36: 45447 | U36: 24 | V36: 12 | W36: =IFERROR(U36/V36, "") -> 2 | X36: =IFERROR($AA36*$U36, "") | AA36: {=IF(P36="", "", _xlfn.XLOOKUP(P36,#REF!,#REF!,NA,0,-1))} | AC36: Brunette Cannabis Co. | AD36: =IF($AC36="","",_xlfn.XLOOKUP($AC36,'[2]Client Info'!$C$2:$C$2535,'[2]Client Info'!$D$2:$D$2535)) -> #102-935 Brunette Ave | AE36: =IF($AC36="","",_xlfn.XLOOKUP($AC36,'[2]Client Info'!$C$2:$C$2715,'[2]Client Info'!$E$2:$E$2715)) -> Coquitlam | AF36: =IF($AC36="","",_xlfn.XLOOKUP($AC36,'[2]Client Info'!$C$2:$C$2715,'[2]Client Info'!$F$2:$F$2715)) -> BC | AG36: Brunette Cannabis Co. | AH36: =134.16/12 -> 11.18 | AI36: =_xlfn.XLOOKUP(Table26[[#This Row],[customerSKU]],customerSKU!G:G,customerSKU!O:O,"not found",0,1) -> not found | AJ36: =Table26[[#This Row],[unitprice]]*Table26[[#This Row],[quantity_unit]] -> 268.32 | AK36: {=_xlfn.IFS(Table26[[#This Row],[sales_stream]]="BCDD",Table26[[#This Row],[Product Price]]*1.05,Table26[[#This Row],[sales_stream]]="MBLL_redistribution",Table26[[#This Row],[Product Price]]*1.05,Table26[[#This Row],[sales_stream]]="MBLL",Table26[[#This Row],[Product Price]]*1.05)} -> 281.736
A37: 2231 | B37: Paid | C37: Shipped | E37: =IF(#REF!>0,#REF!,"") -> #REF! | I37: Sent | J37: BCDD | K37: 45492 | L37: Retail | N37: =Table26[[#This Row],[po_number]]&"-"&Table26[[#This Row],[po_line]] -> -7 | O37: 7 | Q37: PR2301F5P3 | R37: Yes | S37: BC | T37: 45457 | U37: 24 | V37: 12 | W37: =IFERROR(U37/V37, "") -> 2 | X37: =IFERROR($AA37*$U37, "") | AA37: {=IF(P37="", "", _xlfn.XLOOKUP(P37,#REF!,#REF!,NA,0,-1))} | AC37: Brunette Cannabis Co. | AD37: =IF($AC37="","",_xlfn.XLOOKUP($AC37,'[2]Client Info'!$C$2:$C$2535,'[2]Client Info'!$D$2:$D$2535)) -> #102-935 Brunette Ave | AE37: =IF($AC37="","",_xlfn.XLOOKUP($AC37,'[2]Client Info'!$C$2:$C$2715,'[2]Client Info'!$E$2:$E$2715)) -> Coquitlam | AF37: =IF($AC37="","",_xlfn.XLOOKUP($AC37,'[2]Client Info'!$C$2:$C$2715,'[2]Client Info'!$F$2:$F$2715)) -> BC | AG37: Brunette Cannabis Co. | AH37: =178.8/12 -> 14.9 | AI37: =_xlfn.XLOOKUP(Table26[[#This Row],[customerSKU]],customerSKU!G:G,customerSKU!O:O,"not found",0,1) -> not found | AJ37: =Table26[[#This Row],[unitprice]]*Table26[[#This Row],[quantity_unit]] -> 357.6 | AK37: {=_xlfn.IFS(Table26[[#This Row],[sales_stream]]="BCDD",Table26[[#This Row],[Product Price]]*1.05,Table26[[#This Row],[sales_stream]]="MBLL_redistribution",Table26[[#This Row],[Product Price]]*1.05,Table26[[#This Row],[sales_stream]]="MBLL",Table26[[#This Row],[Product Price]]*1.05)} -> 375.48
A38: 2232 | B38: Paid | C38: Shipped | E38: =IF(#REF!>0,#REF!,"") -> #REF! | I38: Sent | J38: BCDD | K38: 45492 | L38: Retail | N38: =Table26[[#This Row],[po_number]]&"-"&Table26[[#This Row],[po_line]] -> -8 | O38: 8 | Q38: PR2407F5P3 | R38: Yes | S38: BC | T38: 45447 | U38: 24 | V38: 12 | W38: =IFERROR(U38/V38, "") -> 2 | X38: =IFERROR($AA38*$U38, "") | AA38: {=IF(P38="", "", _xlfn.XLOOKUP(P38,#REF!,#REF!,NA,0,-1))} | AC38: Brunette Cannabis Co. | AD38: =IF($AC38="","",_xlfn.XLOOKUP($AC38,'[2]Client Info'!$C$2:$C$2535,'[2]Client Info'!$D$2:$D$2535)) -> #102-935 Brunette Ave | AE38: =IF($AC38="","",_xlfn.XLOOKUP($AC38,'[2]Client Info'!$C$2:$C$2715,'[2]Client Info'!$E$2:$E$2715)) -> Coquitlam | AF38: =IF($AC38="","",_xlfn.XLOOKUP($AC38,'[2]Client Info'!$C$2:$C$2715,'[2]Client Info'!$F$2:$F$2715)) -> BC | AG38: Brunette Cannabis Co. | AH38: =200.16/12 -> 16.68 | AI38: =_xlfn.XLOOKUP(Table26[[#This Row],[customerSKU]],customerSKU!G:G,customerSKU!O:O,"not found",0,1) -> not found | AJ38: =Table26[[#This Row],[unitprice]]*Table26[[#This Row],[quantity_unit]] -> 400.32 | AK38: {=_xlfn.IFS(Table26[[#This Row],[sales_stream]]="BCDD",Table26[[#This Row],[Product Price]]*1.05,Table26[[#This Row],[sales_stream]]="MBLL_redistribution",Table26[[#This Row],[Product Price]]*1.05,Table26[[#This Row],[sales_stream]]="MBLL",Table26[[#This Row],[Product Price]]*1.05)} -> 420.336
A39: 2233 | B39: Paid | C39: Shipped | I39: Sent | J39: BCDD | K39: 45492 | L39: Retail | N39: =Table26[[#This Row],[po_number]]&"-"&Table26[[#This Row],[po_line]] -> -9 | O39: 9 | Q39: BS23041701G180 | R39: Yes | T39: 45467 | U39: 6 | V39: 6 | W39: =IFERROR(U39/V39, "") -> 1 | X39: =IFERROR($AA39*$U39, "") | AA39: {=IF(P39="", "", _xlfn.XLOOKUP(P39,#REF!,#REF!,NA,0,-1))} | AC39: Brunette Cannabis Co. | AD39: =IF($AC39="","",_xlfn.XLOOKUP($AC39,'[2]Client Info'!$C$2:$C$2535,'[2]Client Info'!$D$2:$D$2535)) -> #102-935 Brunette Ave | AE39: =IF($AC39="","",_xlfn.XLOOKUP($AC39,'[2]Client Info'!$C$2:$C$2715,'[2]Client Info'!$E$2:$E$2715)) -> Coquitlam | AF39: =IF($AC39="","",_xlfn.XLOOKUP($AC39,'[2]Client Info'!$C$2:$C$2715,'[2]Client Info'!$F$2:$F$2715)) -> BC | AG39: Brunette Cannabis Co. | AH39: =74.76/6 -> 12.46 | AI39: =_xlfn.XLOOKUP(Table26[[#This Row],[customerSKU]],customerSKU!G:G,customerSKU!O:O,"not found",0,1) -> not found | AJ39: =Table26[[#This Row],[unitprice]]*Table26[[#This Row],[quantity_unit]] -> 74.76 | AK39: {=_xlfn.IFS(Table26[[#This Row],[sales_stream]]="BCDD",Table26[[#This Row],[Product Price]]*1.05,Table26[[#This Row],[sales_stream]]="MBLL_redistribution",Table26[[#This Row],[Product Price]]*1.05,Table26[[#This Row],[sales_stream]]="MBLL",Table26[[#This Row],[Product Price]]*1.05)} -> 78.498
A40: 2201 | B40: Not Applicable | C40: Shipped | D40: 45485 | H40: N | I40: Sent | J40: YLC | K40: 45495 | L40: Provincial Distribution | N40: =Table26[[#This Row],[po_number]]&"-"&Table26[[#This Row],[po_line]] -> -1 | O40: 1 | Q40: EX24061401V30 | R40: No | S40: YT | T40: 45467 | U40: 24 | V40: 12 | W40: =IFERROR(U40/V40, "") -> 2 | X40: =IFERROR($AA40*$U40, "") | Y40: 0877579002601 | Z40: 991969 | AA40: {=IF(P40="", "", _xlfn.XLOOKUP(P40,#REF!,#REF!,NA,0,-1))} | AC40: Cannabis Yukon | AD40: =IF($AC40="","",_xlfn.XLOOKUP($AC40,'[2]Client Info'!$C$2:$C$2535,'[2]Client Info'!$D$2:$D$2535)) -> 9031 Quartz Road | AE40: =IF($AC40="","",_xlfn.XLOOKUP($AC40,'[2]Client Info'!$C$2:$C$2715,'[2]Client Info'!$E$2:$E$2715)) -> White Horse | AF40: =IF($AC40="","",_xlfn.XLOOKUP($AC40,'[2]Client Info'!$C$2:$C$2715,'[2]Client Info'!$F$2:$F$2715)) -> YT | AG40: Cannabis Yukon | AI40: =_xlfn.XLOOKUP(Table26[[#This Row],[customerSKU]],customerSKU!G:G,customerSKU!O:O,"not found",0,1) -> not found | AJ40: =Table26[[#This Row],[unitprice]]*Table26[[#This Row],[quantity_unit]] -> 0 | AK40: {=_xlfn.IFS(Table26[[#This Row],[sales_stream]]="BCDD",Table26[[#This Row],[Product Price]]*1.05,Table26[[#This Row],[sales_stream]]="MBLL_redistribution",Table26[[#This Row],[Product Price]]*1.05,Table26[[#This Row],[sales_stream]]="MBLL",Table26[[#This Row],[Product Price]]*1.05)} -> #N/A
A41: 2202 | B41: Not Applicable | C41: Shipped | D41: 45485 | H41: N | I41: Sent | J41: YLC | K41: 45495 | L41: Provincial Distribution | N41: =Table26[[#This Row],[po_number]]&"-"&Table26[[#This Row],[po_line]] -> -2 | O41: 2 | Q41: EX23100401V30 | R41: No | S41: YT | T41: 45488 | U41: =6*3 -> 18 | V41: 6 | W41: =IFERROR(U41/V41, "") -> 3 | X41: =IFERROR($AA41*$U41, "") | Y41: 0877579000638 | Z41: 990835 | AA41: {=IF(P41="", "", _xlfn.XLOOKUP(P41,#REF!,#REF!,NA,0,-1))} | AC41: Cannabis Yukon | AD41: =IF($AC41="","",_xlfn.XLOOKUP($AC41,'[2]Client Info'!$C$2:$C$2535,'[2]Client Info'!$D$2:$D$2535)) -> 9031 Quartz Road | AE41: =IF($AC41="","",_xlfn.XLOOKUP($AC41,'[2]Client Info'!$C$2:$C$2715,'[2]Client Info'!$E$2:$E$2715)) -> White Horse | AF41: =IF($AC41="","",_xlfn.XLOOKUP($AC41,'[2]Client Info'!$C$2:$C$2715,'[2]Client Info'!$F$2:$F$2715)) -> YT | AG41: Cannabis Yukon | AI41: =_xlfn.XLOOKUP(Table26[[#This Row],[customerSKU]],customerSKU!G:G,customerSKU!O:O,"not found",0,1) -> not found | AJ41: =Table26[[#This Row],[unitprice]]*Table26[[#This Row],[quantity_unit]] -> 0 | AK41: {=_xlfn.IFS(Table26[[#This Row],[sales_stream]]="BCDD",Table26[[#This Row],[Product Price]]*1.05,Table26[[#This Row],[sales_stream]]="MBLL_redistribution",Table26[[#This Row],[Product Price]]*1.05,Table26[[#This Row],[sales_stream]]="MBLL",Table26[[#This Row],[Product Price]]*1.05)} -> #N/A
A42: 2203 | B42: Not Applicable | C42: Shipped | D42: 45485 | H42: N | I42: Sent | J42: YLC | K42: 45495 | L42: Provincial Distribution | N42: =Table26[[#This Row],[po_number]]&"-"&Table26[[#This Row],[po_line]] -> -3 | O42: 3 | Q42: PR2406F1P3 | R42: Yes | S42: YT | T42: 45448 | U42: =12*6 -> 72 | V42: 12 | W42: =IFERROR(U42/V42, "") -> 6 | X42: =IFERROR($AA42*$U42, "") | Y42: 0877579003219 | Z42: 991650 | AA42: {=IF(P42="", "", _xlfn.XLOOKUP(P42,#REF!,#REF!,NA,0,-1))} | AC42: Cannabis Yukon | AD42: =IF($AC42="","",_xlfn.XLOOKUP($AC42,'[2]Client Info'!$C$2:$C$2535,'[2]Client Info'!$D$2:$D$2535)) -> 9031 Quartz Road | AE42: =IF($AC42="","",_xlfn.XLOOKUP($AC42,'[2]Client Info'!$C$2:$C$2715,'[2]Client Info'!$E$2:$E$2715)) -> White Horse | AF42: =IF($AC42="","",_xlfn.XLOOKUP($AC42,'[2]Client Info'!$C$2:$C$2715,'[2]Client Info'!$F$2:$F$2715)) -> YT | AG42: Cannabis Yukon | AI42: =_xlfn.XLOOKUP(Table26[[#This Row],[customerSKU]],customerSKU!G:G,customerSKU!O:O,"not found",0,1) -> not found | AJ42: =Table26[[#This Row],[unitprice]]*Table26[[#This Row],[quantity_unit]] -> 0 | AK42: {=_xlfn.IFS(Table26[[#This Row],[sales_stream]]="BCDD",Table26[[#This Row],[Product Price]]*1.05,Table26[[#This Row],[sales_stream]]="MBLL_redistribution",Table26[[#This Row],[Product Price]]*1.05,Table26[[#This Row],[sales_stream]]="MBLL",Table26[[#This Row],[Product Price]]*1.05)} -> #N/A
A43: 2204 | B43: Not Applicable | C43: Shipped | D43: 45485 | H43: N | I43: Sent | J43: YLC | K43: 45495 | L43: Provincial Distribution | N43: =Table26[[#This Row],[po_number]]&"-"&Table26[[#This Row],[po_line]] -> -4 | O43: 4 | Q43: CPR22102101G1 | R43: Yes | S43: YT | T43: 45492 | U43: =12*6 -> 72 | V43: 12 | W43: =IFERROR(U43/V43, "") -> 6 | X43: =IFERROR($AA43*$U43, "") | Y43: 0877579003165 | Z43: 991651 | AA43: {=IF(P43="", "", _xlfn.XLOOKUP(P43,#REF!,#REF!,NA,0,-1))} | AC43: Cannabis Yukon | AD43: =IF($AC43="","",_xlfn.XLOOKUP($AC43,'[2]Client Info'!$C$2:$C$2535,'[2]Client Info'!$D$2:$D$2535)) -> 9031 Quartz Road | AE43: =IF($AC43="","",_xlfn.XLOOKUP($AC43,'[2]Client Info'!$C$2:$C$2715,'[2]Client Info'!$E$2:$E$2715)) -> White Horse | AF43: =IF($AC43="","",_xlfn.XLOOKUP($AC43,'[2]Client Info'!$C$2:$C$2715,'[2]Client Info'!$F$2:$F$2715)) -> YT | AG43: Cannabis Yukon | AI43: =_xlfn.XLOOKUP(Table26[[#This Row],[customerSKU]],customerSKU!G:G,customerSKU!O:O,"not found",0,1) -> not found | AJ43: =Table26[[#This Row],[unitprice]]*Table26[[#This Row],[quantity_unit]] -> 0 | AK43: {=_xlfn.IFS(Table26[[#This Row],[sales_stream]]="BCDD",Table26[[#This Row],[Product Price]]*1.05,Table26[[#This Row],[sales_stream]]="MBLL_redistribution",Table26[[#This Row],[Product Price]]*1.05,Table26[[#This Row],[sales_stream]]="MBLL",Table26[[#This Row],[Product Price]]*1.05)} -> #N/A
A44: 2205 | B44: Not Applicable | C44: Shipped | D44: 45485 | H44: N | I44: Sent | J44: YLC | K44: 45495 | L44: Provincial Distribution | N44: =Table26[[#This Row],[po_number]]&"-"&Table26[[#This Row],[po_line]] -> -5 | O44: 5 | Q44: PR22051901G1 | R44: Yes | S44: YT | T44: 45492 | U44: =12*6 -> 72 | V44: 12 | W44: =IFERROR(U44/V44, "") -> 6 | X44: =IFERROR($AA44*$U44, "") | Y44: 0877579003158 | Z44: 991974 | AA44: {=IF(P44="", "", _xlfn.XLOOKUP(P44,#REF!,#REF!,NA,0,-1))} | AC44: Cannabis Yukon | AD44: =IF($AC44="","",_xlfn.XLOOKUP($AC44,'[2]Client Info'!$C$2:$C$2535,'[2]Client Info'!$D$2:$D$2535)) -> 9031 Quartz Road | AE44: =IF($AC44="","",_xlfn.XLOOKUP($AC44,'[2]Client Info'!$C$2:$C$2715,'[2]Client Info'!$E$2:$E$2715)) -> White Horse | AF44: =IF($AC44="","",_xlfn.XLOOKUP($AC44,'[2]Client Info'!$C$2:$C$2715,'[2]Client Info'!$F$2:$F$2715)) -> YT | AG44: Cannabis Yukon | AI44: =_xlfn.XLOOKUP(Table26[[#This Row],[customerSKU]],customerSKU!G:G,customerSKU!O:O,"not found",0,1) -> not found | AJ44: =Table26[[#This Row],[unitprice]]*Table26[[#This Row],[quantity_unit]] -> 0 | AK44: {=_xlfn.IFS(Table26[[#This Row],[sales_stream]]="BCDD",Table26[[#This Row],[Product Price]]*1.05,Table26[[#This Row],[sales_stream]]="MBLL_redistribution",Table26[[#This Row],[Product Price]]*1.05,Table26[[#This Row],[sales_stream]]="MBLL",Table26[[#This Row],[Product Price]]*1.05)} -> #N/A
A45: 2206 | B45: Not Applicable | C45: Shipped | D45: 45485 | H45: N | I45: Sent | J45: YLC | K45: 45495 | L45: Provincial Distribution | N45: =Table26[[#This Row],[po_number]]&"-"&Table26[[#This Row],[po_line]] -> -6 | O45: 6 | Q45: TP24041201 | R45: Yes | S45: YT | T45: 45448 | U45: 24 | V45: 12 | W45: =IFERROR(U45/V45, "") -> 2 | X45: =IFERROR($AA45*$U45, "") | Y45: 0877579003752 | Z45: 994665 | AA45: {=IF(P45="", "", _xlfn.XLOOKUP(P45,#REF!,#REF!,NA,0,-1))} | AC45: Cannabis Yukon | AD45: =IF($AC45="","",_xlfn.XLOOKUP($AC45,'[2]Client Info'!$C$2:$C$2535,'[2]Client Info'!$D$2:$D$2535)) -> 9031 Quartz Road | AE45: =IF($AC45="","",_xlfn.XLOOKUP($AC45,'[2]Client Info'!$C$2:$C$2715,'[2]Client Info'!$E$2:$E$2715)) -> White Horse | AF45: =IF($AC45="","",_xlfn.XLOOKUP($AC45,'[2]Client Info'!$C$2:$C$2715,'[2]Client Info'!$F$2:$F$2715)) -> YT | AG45: Cannabis Yukon | AI45: =_xlfn.XLOOKUP(Table26[[#This Row],[customerSKU]],customerSKU!G:G,customerSKU!O:O,"not found",0,1) -> not found | AJ45: =Table26[[#This Row],[unitprice]]*Table26[[#This Row],[quantity_unit]] -> 0 | AK45: {=_xlfn.IFS(Table26[[#This Row],[sales_stream]]="BCDD",Table26[[#This Row],[Product Price]]*1.05,Table26[[#This Row],[sales_stream]]="MBLL_redistribution",Table26[[#This Row],[Product Price]]*1.05,Table26[[#This Row],[sales_stream]]="MBLL",Table26[[#This Row],[Product Price]]*1.05)} -> #N/A
A46: 2207 | B46: Not Applicable | C46: Shipped | D46: 45485 | H46: N | I46: Sent | J46: YLC | K46: 45495 | L46: Provincial Distribution | N46: =Table26[[#This Row],[po_number]]&"-"&Table26[[#This Row],[po_line]] -> -7 | O46: 7 | Q46: PR240601F5P3 | R46: Yes | S46: YT | T46: 45491 | U46: 12 | V46: 12 | W46: =IFERROR(U46/V46, "") -> 1 | X46: =IFERROR($AA46*$U46, "") | Y46: 0877579003851 | Z46: 994667 | AA46: {=IF(P46="", "", _xlfn.XLOOKUP(P46,#REF!,#REF!,NA,0,-1))} | AC46: Cannabis Yukon | AD46: =IF($AC46="","",_xlfn.XLOOKUP($AC46,'[2]Client Info'!$C$2:$C$2535,'[2]Client Info'!$D$2:$D$2535)) -> 9031 Quartz Road | AE46: =IF($AC46="","",_xlfn.XLOOKUP($AC46,'[2]Client Info'!$C$2:$C$2715,'[2]Client Info'!$E$2:$E$2715)) -> White Horse | AF46: =IF($AC46="","",_xlfn.XLOOKUP($AC46,'[2]Client Info'!$C$2:$C$2715,'[2]Client Info'!$F$2:$F$2715)) -> YT | AG46: Cannabis Yukon | AI46: =_xlfn.XLOOKUP(Table26[[#This Row],[customerSKU]],customerSKU!G:G,customerSKU!O:O,"not found",0,1) -> not found | AJ46: =Table26[[#This Row],[unitprice]]*Table26[[#This Row],[quantity_unit]] -> 0 | AK46: {=_xlfn.IFS(Table26[[#This Row],[sales_stream]]="BCDD",Table26[[#This Row],[Product Price]]*1.05,Table26[[#This Row],[sales_stream]]="MBLL_redistribution",Table26[[#This Row],[Product Price]]*1.05,Table26[[#This Row],[sales_stream]]="MBLL",Table26[[#This Row],[Product Price]]*1.05)} -> #N/A
